Workbook
Name electronicspackagingheterogeneousintegrationandthermalmanagement: 'Official Courses'!#REF!
Name integratedcircuitsystemdesignelectronicdesignautomation: 'Official Courses'!#REF!
Name semiconductormanufacturingandglobalsupplychainmanagement: 'Official Courses'!#REF!
Name semiconductormateriralscharacterizationandprocessing: 'Official Courses'!#REF!

Sheet Updated
N1: Advanced Packaging | O1: Artificial Intelligence & Machine Learning | P1: AI Acceleration (Hardware) | Q1: Analog IC Design | R1: ASIC RTL Design | S1: Characterization & Metrology | T1: Custom Digital IC Design | U1: Data Analysis | V1: Data Center Infrastructure | W1: Design for Sustainability | X1: Design, EDA, and Digital Twins | Y1: Device and Circuit Concepts | Z1: Digital Design | AA1: Embedded Systems | AB1: Fabrication Concepts | AC1: Facilities Design | AD1: FPGA Prototyping | AE1: Functional verification of ASiC/SoC | AF1: Interconnects & Re-Distribution Layers | AG1: Lithography | AH1: Manufacturing & Control Strategies | AI1: Material Properties | AJ1: Memory design | AK1: Micro-Electro-Mechanical Systems (MEMS) | AL1: Mixed Signal IC Design | AM1: Nanoscale Materials, Systems, & Devices | AN1: Optics and Photonics | AO1: Physical layout and verification of ICs | AP1: Power Delivery | AQ1: Power Electronics | AR1: Process Analysis & Scheduling | AS1: Process Development & Assembly | AT1: Processor Design | AU1: Quality Control | AV1: Quantum Computing | AW1: Quantum Mechanics & Solid State Physics | AX1: Radiation Hardening | AY1: Reliability & Failure Analysis | AZ1: RF IC design | BA1: Health & Safety | BB1: Semiconductor Fundamentals & Device Theory | BC1: Sensors and Actuators | BD1: Statistical Analysis | BE1: Statistical Process Control | BF1: Substrates, Materials, and Encapsulation | BG1: Supply Chain Management | BH1: System on Chip Architecture | BI1: Thermal Management | BJ1: Timing Analysis | BK1: Uncertainty Analysis | BL1: VLSI Design
A2: Certificate? | B2: Course Number | C2: ID# | D2: Course | E2: Credits | F2: Primary Certificate Category | G2: Secondary Certificate Category | H2: Pre-Requisites | I2: Other Restrictions / Notes | J2: Course Description | K2: Catalog Link | L2: Additional Information | M2: Topics | N2: =COUNTIFS(N$3:N$400,"x",$A$3:$A$400,"Yes*")+COUNTIFS(N$3:N$400,"x",$A$3:$A$400,"Add*") -> 6 | O2: =COUNTIFS(O$3:O$400,"x",$A$3:$A$400,"Yes*")+COUNTIFS(O$3:O$400,"x",$A$3:$A$400,"Add*") -> 3 | P2: =COUNTIFS(P$3:P$400,"x",$A$3:$A$400,"Yes*")+COUNTIFS(P$3:P$400,"x",$A$3:$A$400,"Add*") -> 1 | Q2: =COUNTIFS(Q$3:Q$400,"x",$A$3:$A$400,"Yes*")+COUNTIFS(Q$3:Q$400,"x",$A$3:$A$400,"Add*") -> 5 | R2: =COUNTIFS(R$3:R$400,"x",$A$3:$A$400,"Yes*")+COUNTIFS(R$3:R$400,"x",$A$3:$A$400,"Add*") -> 3 | S2: =COUNTIFS(S$3:S$400,"x",$A$3:$A$400,"Yes*")+COUNTIFS(S$3:S$400,"x",$A$3:$A$400,"Add*") -> 9 | T2: =COUNTIFS(T$3:T$400,"x",$A$3:$A$400,"Yes*")+COUNTIFS(T$3:T$400,"x",$A$3:$A$400,"Add*") -> 5 | U2: =COUNTIFS(U$3:U$400,"x",$A$3:$A$400,"Yes*")+COUNTIFS(U$3:U$400,"x",$A$3:$A$400,"Add*") -> 22 | ... BL2: =COUNTIFS(BL$3:BL$400,"x",$A$3:$A$400,"Yes*")+COUNTIFS(BL$3:BL$400,"x",$A$3:$A$400,"Add*") -> 7
A3: No | B3: CHE 20500 | C3: CHE 20500 | D3: CHE 20500 Chemical Engineering Calculations | E3: =IF(_xlfn.IFNA(VLOOKUP(B3,Data!B:G,3,FALSE),"")=0, "", _xlfn.IFNA(VLOOKUP(B3,Data!B:G,3,FALSE),"")) -> 4 | F3: N/A | H3: =IF(_xlfn.IFNA(VLOOKUP(C3,Data!A:G,5,FALSE),"")=0, "Check course registration information", _xlfn.IFNA(VLOOKUP(C3,Data!A:G,5,FALSE),"")) -> ENGR 12100 or ENFY 12600 or ENGR 12600 or ENFY 13100 or ENGR 13100 or ENGR 13000 or VIP 17911 or ENGR 17911 or ENGR 16100 or EPCS 11100 or EPCS 12100 or ENFY 19500 or ENGR 19500 or ENGR 14100 or ENGR 16100) and (PHYS 17200 or (PHYS 16200 and PHYS 16300) or (ENGR 16200) and (MA 16100 or MA 16700 Minimum Grade of | J3: =IF(_xlfn.IFNA(VLOOKUP(C3,Data!A:G,6,FALSE),"")=0, "Check course registration information", _xlfn.IFNA(VLOOKUP(C3,Data!A:G,6,FALSE),"")) -> Quantitative applications of steady-state mass and energy balances to solve problems involving multi-component systems and multi-unit chemical processes. Single-component and multi-component phase equilibria, single-reaction and multiple-reaction stoichiometry, coupled mass and energy balances, chemical processes involving bypass and recycle streams | K3: =IF(_xlfn.IFNA(VLOOKUP(C3,Data!A:H,7,FALSE),"")=0, "", _xlfn.IFNA(HYPERLINK(VLOOKUP(C3,Data!A:H,7,FALSE),"Catalog Link"),"")) -> Catalog Link | L3: =IF(_xlfn.IFNA(VLOOKUP(C3,Data!A:I,8,FALSE),"")=0, "", _xlfn.IFNA(HYPERLINK(VLOOKUP(C3,Data!A:I,8,FALSE),"Additional Information"),"")) | M3: =COUNTIF(N3:BL3,"x") -> 2 | AS3: x | BI3: x
A4: No | B4: CHE 21100 | C4: CHE 21100 | D4: CHE 21100 Introductory Chemical Engineering Thermodynamics | E4: =IF(_xlfn.IFNA(VLOOKUP(B4,Data!B:G,3,FALSE),"")=0, "", _xlfn.IFNA(VLOOKUP(B4,Data!B:G,3,FALSE),"")) -> 4 | F4: N/A | H4: =IF(_xlfn.IFNA(VLOOKUP(C4,Data!A:G,5,FALSE),"")=0, "Check course registration information", _xlfn.IFNA(VLOOKUP(C4,Data!A:G,5,FALSE),"")) -> CHE 20500 and (MA 26100 or MATH 26100 or MA 18200 or MA 17400 or MA 27100 or MA 26300 or MA 17200 | J4: =IF(_xlfn.IFNA(VLOOKUP(C4,Data!A:G,6,FALSE),"")=0, "Check course registration information", _xlfn.IFNA(VLOOKUP(C4,Data!A:G,6,FALSE),"")) -> Basic principles and concepts of thermodynamics applied to chemical engineering problems; use of basic thermodynamic functions of enthalpy, entropy, free energy to solutions, phase equilibria, and chemical equilibria; thermodynamic processes and efficiencies; equations of state; and relation of macroscopic to molecular properties | K4: =IF(_xlfn.IFNA(VLOOKUP(C4,Data!A:H,7,FALSE),"")=0, "", _xlfn.IFNA(HYPERLINK(VLOOKUP(C4,Data!A:H,7,FALSE),"Catalog Link"),"")) -> Catalog Link | L4: =IF(_xlfn.IFNA(VLOOKUP(C4,Data!A:I,8,FALSE),"")=0, "", _xlfn.IFNA(HYPERLINK(VLOOKUP(C4,Data!A:I,8,FALSE),"Additional Information"),"")) | M4: =COUNTIF(N4:BL4,"x") -> 4 | S4: x | W4: x | BF4: x | BI4: x
A5: No | B5: CHE 30600 | C5: CHE 30600 | D5: CHE 30600 Design Of Staged Separation Processes | E5: =IF(_xlfn.IFNA(VLOOKUP(B5,Data!B:G,3,FALSE),"")=0, "", _xlfn.IFNA(VLOOKUP(B5,Data!B:G,3,FALSE),"")) -> 3 | F5: N/A | H5: =IF(_xlfn.IFNA(VLOOKUP(C5,Data!A:G,5,FALSE),"")=0, "Check course registration information", _xlfn.IFNA(VLOOKUP(C5,Data!A:G,5,FALSE),"")) -> CHE 20500 and CHE 21100 | J5: =IF(_xlfn.IFNA(VLOOKUP(C5,Data!A:G,6,FALSE),"")=0, "Check course registration information", _xlfn.IFNA(VLOOKUP(C5,Data!A:G,6,FALSE),"")) -> The application of equilibria and mass and energy balances for the design of staged separation processes. Use of various equilibrium data and thermodynamic principles for the design of batch and continuous distillation, absorption, stripping, and extraction systems. Stagewise calculations and graphical methods for design of binary systems. Design of multicomponent separators. Determination of stage efficiency and column size | K5: =IF(_xlfn.IFNA(VLOOKUP(C5,Data!A:H,7,FALSE),"")=0, "", _xlfn.IFNA(HYPERLINK(VLOOKUP(C5,Data!A:H,7,FALSE),"Catalog Link"),"")) -> Catalog Link | L5: =IF(_xlfn.IFNA(VLOOKUP(C5,Data!A:I,8,FALSE),"")=0, "", _xlfn.IFNA(HYPERLINK(VLOOKUP(C5,Data!A:I,8,FALSE),"Additional Information"),"")) | M5: =COUNTIF(N5:BL5,"x") -> 0
A6: Yes | B6: CHE 32000 | C6: CHE 32000 | D6: CHE 32000 Statistical Modeling And Quality Enhancement | E6: =IF(_xlfn.IFNA(VLOOKUP(B6,Data!B:G,3,FALSE),"")=0, "", _xlfn.IFNA(VLOOKUP(B6,Data!B:G,3,FALSE),"")) -> 3 | F6: Semiconductor Manufacturing and Global Supply Chain Management | H6: =IF(_xlfn.IFNA(VLOOKUP(C6,Data!A:G,5,FALSE),"")=0, "Check course registration information", _xlfn.IFNA(VLOOKUP(C6,Data!A:G,5,FALSE),"")) -> CHE 20500 or ABE 20100) and MA 26100 [concurrent ok] and (CHM 26100 or CHM 25500 [concurrent ok] or CHM 25700 [concurrent ok]) and (MA 26200 [concurrent ok] or MATH 26200 or MA 26500 [concurrent ok] or MA 35100 [concurrent ok] | J6: =IF(_xlfn.IFNA(VLOOKUP(C6,Data!A:G,6,FALSE),"")=0, "Check course registration information", _xlfn.IFNA(VLOOKUP(C6,Data!A:G,6,FALSE),"")) -> Statistical modeling methods, design of experiments, error analysis, curve fitting and regression, analysis of variance, confidence intervals, quality control and enhancement: emphasizes preparation for designing chemical engineering laboratory experiments and analyzing data | K6: =IF(_xlfn.IFNA(VLOOKUP(C6,Data!A:H,7,FALSE),"")=0, "", _xlfn.IFNA(HYPERLINK(VLOOKUP(C6,Data!A:H,7,FALSE),"Catalog Link"),"")) -> Catalog Link | L6: =IF(_xlfn.IFNA(VLOOKUP(C6,Data!A:I,8,FALSE),"")=0, "", _xlfn.IFNA(HYPERLINK(VLOOKUP(C6,Data!A:I,8,FALSE),"Additional Information"),"")) | M6: =COUNTIF(N6:BL6,"x") -> 7 | O6: x | U6: x | AH6: x | AU6: x | AY6: x | BD6: x | BK6: x
A7: No | B7: CHE 34800 | C7: CHE 34800 | D7: CHE 34800 Chemical Reaction Engineering | E7: =IF(_xlfn.IFNA(VLOOKUP(B7,Data!B:G,3,FALSE),"")=0, "", _xlfn.IFNA(VLOOKUP(B7,Data!B:G,3,FALSE),"")) -> 4 | F7: N/A | H7: =IF(_xlfn.IFNA(VLOOKUP(C7,Data!A:G,5,FALSE),"")=0, "Check course registration information", _xlfn.IFNA(VLOOKUP(C7,Data!A:G,5,FALSE),"")) -> CHE 21100 and (MA 26600 [concurrent ok] or MA 30300 [concurrent ok] or MA 36600 [concurrent ok] or ME 58100 [concurrent ok] or MA 51400 [concurrent ok] | J7: =IF(_xlfn.IFNA(VLOOKUP(C7,Data!A:G,6,FALSE),"")=0, "Check course registration information", _xlfn.IFNA(VLOOKUP(C7,Data!A:G,6,FALSE),"")) -> Application of kinetic rate equations, mass balances and energy balances to the analysis and design of chemical reactors involving homogeneous and heterogeneous chemical reactions. Chemical equilibria, kinetic rate equations for homogeneous and heterogeneously catalyzed reactions, design of ideal isothermal reactors, effects of non-isothermal operation, effects of diffusion in porous catalysts and non-ideal mixing in continuous flow reactors | K7: =IF(_xlfn.IFNA(VLOOKUP(C7,Data!A:H,7,FALSE),"")=0, "", _xlfn.IFNA(HYPERLINK(VLOOKUP(C7,Data!A:H,7,FALSE),"Catalog Link"),"")) -> Catalog Link | L7: =IF(_xlfn.IFNA(VLOOKUP(C7,Data!A:I,8,FALSE),"")=0, "", _xlfn.IFNA(HYPERLINK(VLOOKUP(C7,Data!A:I,8,FALSE),"Additional Information"),"")) | M7: =COUNTIF(N7:BL7,"x") -> 0
A8: No | B8: CHE 37700 | C8: CHE 37700 | D8: CHE 37700 Momentum Transfer | E8: =IF(_xlfn.IFNA(VLOOKUP(B8,Data!B:G,3,FALSE),"")=0, "", _xlfn.IFNA(VLOOKUP(B8,Data!B:G,3,FALSE),"")) -> 4 | F8: N/A | H8: =IF(_xlfn.IFNA(VLOOKUP(C8,Data!A:G,5,FALSE),"")=0, "Check course registration information", _xlfn.IFNA(VLOOKUP(C8,Data!A:G,5,FALSE),"")) -> CHE 21100 and (MA 26600 [concurrent ok] or MA 30300 [concurrent ok] or MA 36600 [concurrent ok] or MA 51400 [concurrent ok] or ME 58100 [concurrent ok] | J8: =IF(_xlfn.IFNA(VLOOKUP(C8,Data!A:G,6,FALSE),"")=0, "Check course registration information", _xlfn.IFNA(VLOOKUP(C8,Data!A:G,6,FALSE),"")) -> Differential (microscopic) and integral (macroscopic) mass, momentum, and energy balances. Newtonian and non-Newtonian fluids. Fluid statics. One-dimensional steady and transient laminar flows. Turbulence. Dimensional analysis and similarity. Friction factors and drag coefficients. Applications to engineering analysis of practical problems. Introduction to numerical analysis and visualization of flows | K8: =IF(_xlfn.IFNA(VLOOKUP(C8,Data!A:H,7,FALSE),"")=0, "", _xlfn.IFNA(HYPERLINK(VLOOKUP(C8,Data!A:H,7,FALSE),"Catalog Link"),"")) -> Catalog Link | L8: =IF(_xlfn.IFNA(VLOOKUP(C8,Data!A:I,8,FALSE),"")=0, "", _xlfn.IFNA(HYPERLINK(VLOOKUP(C8,Data!A:I,8,FALSE),"Additional Information"),"")) | M8: =COUNTIF(N8:BL8,"x") -> 1 | BI8: x
A9: Yes | B9: CHE 37800 | C9: CHE 37800 | D9: CHE 37800 Heat And Mass Transfer | E9: =IF(_xlfn.IFNA(VLOOKUP(B9,Data!B:G,3,FALSE),"")=0, "", _xlfn.IFNA(VLOOKUP(B9,Data!B:G,3,FALSE),"")) -> 4 | F9: Semiconductor Materials, Characterization, and Processing | H9: =IF(_xlfn.IFNA(VLOOKUP(C9,Data!A:G,5,FALSE),"")=0, "Check course registration information", _xlfn.IFNA(VLOOKUP(C9,Data!A:G,5,FALSE),"")) -> CHE 21100 and CHE 37700 | J9: =IF(_xlfn.IFNA(VLOOKUP(C9,Data!A:G,6,FALSE),"")=0, "Check course registration information", _xlfn.IFNA(VLOOKUP(C9,Data!A:G,6,FALSE),"")) -> Macroscopic and differential energy balances. Heat transfer coefficients for free and forced convection and phase change. Conductive and radiative heat transfer. Applications to heat transfer equipment design and compressible fluid flow. Macroscopic and differential species balances. Mass transfer coefficients and analogies. Mass transfer with and without chemical reaction. Mass transfer equipment design | K9: =IF(_xlfn.IFNA(VLOOKUP(C9,Data!A:H,7,FALSE),"")=0, "", _xlfn.IFNA(HYPERLINK(VLOOKUP(C9,Data!A:H,7,FALSE),"Catalog Link"),"")) -> Catalog Link | L9: =IF(_xlfn.IFNA(VLOOKUP(C9,Data!A:I,8,FALSE),"")=0, "", _xlfn.IFNA(HYPERLINK(VLOOKUP(C9,Data!A:I,8,FALSE),"Additional Information"),"")) | M9: =COUNTIF(N9:BL9,"x") -> 2 | V9: x | BI9: x
A10: Yes | B10: CHE 42000 | C10: CHE 42000 | D10: CHE 42000 Process Safety Management And Analysis | E10: =IF(_xlfn.IFNA(VLOOKUP(B10,Data!B:G,3,FALSE),"")=0, "", _xlfn.IFNA(VLOOKUP(B10,Data!B:G,3,FALSE),"")) -> 3 | F10: Semiconductor Materials, Characterization, and Processing | H10: =IF(_xlfn.IFNA(VLOOKUP(C10,Data!A:G,5,FALSE),"")=0, "Check course registration information", _xlfn.IFNA(VLOOKUP(C10,Data!A:G,5,FALSE),"")) -> CHE 34800 [concurrent ok] and CHE 37800 [concurrent ok] | J10: =IF(_xlfn.IFNA(VLOOKUP(C10,Data!A:G,6,FALSE),"")=0, "Check course registration information", _xlfn.IFNA(VLOOKUP(C10,Data!A:G,6,FALSE),"")) -> Develop knowledge of process safety management and analysis in the process industries, including hazard identification, hazard analysis and risk management | K10: =IF(_xlfn.IFNA(VLOOKUP(C10,Data!A:H,7,FALSE),"")=0, "", _xlfn.IFNA(HYPERLINK(VLOOKUP(C10,Data!A:H,7,FALSE),"Catalog Link"),"")) -> Catalog Link | L10: =IF(_xlfn.IFNA(VLOOKUP(C10,Data!A:I,8,FALSE),"")=0, "", _xlfn.IFNA(HYPERLINK(VLOOKUP(C10,Data!A:I,8,FALSE),"Additional Information"),"")) | M10: =COUNTIF(N10:BL10,"x") -> 4 | AH10: x | AS10: x | AY10: x | BI10: x
A11: No | B11: CHE 43500 | C11: CHE 43500 | D11: CHE 43500 Chemical Engineering Laboratory | E11: =IF(_xlfn.IFNA(VLOOKUP(B11,Data!B:G,3,FALSE),"")=0, "", _xlfn.IFNA(VLOOKUP(B11,Data!B:G,3,FALSE),"")) -> 4 | F11: N/A | H11: =IF(_xlfn.IFNA(VLOOKUP(C11,Data!A:G,5,FALSE),"")=0, "Check course registration information", _xlfn.IFNA(VLOOKUP(C11,Data!A:G,5,FALSE),"")) -> CHE 32000 and CHE 34800 and CHE 37800 and CHE 30600 | J11: =IF(_xlfn.IFNA(VLOOKUP(C11,Data!A:G,6,FALSE),"")=0, "Check course registration information", _xlfn.IFNA(VLOOKUP(C11,Data!A:G,6,FALSE),"")) -> Quantitative experimental study of projects involving problems in fluid mechanics and heat and mass transfer or operation and evaluation of equipment; projects include analysis and data-based design of operations involving mass transfer such as distillation, absorption, drying, humidification, etc.; study of rates and equilibria in simple chemical reaction systems; study of chemical processes; application of methods of data analysis in practice; some library work; emphasis on group work, report writing, and oral communication | K11: =IF(_xlfn.IFNA(VLOOKUP(C11,Data!A:H,7,FALSE),"")=0, "", _xlfn.IFNA(HYPERLINK(VLOOKUP(C11,Data!A:H,7,FALSE),"Catalog Link"),"")) -> Catalog Link | L11: =IF(_xlfn.IFNA(VLOOKUP(C11,Data!A:I,8,FALSE),"")=0, "", _xlfn.IFNA(HYPERLINK(VLOOKUP(C11,Data!A:I,8,FALSE),"Additional Information"),"")) | M11: =COUNTIF(N11:BL11,"x") -> 0
A12: No | B12: CHE 45000 | C12: CHE 45000 | D12: CHE 45000 Design And Analysis Of Processing Systems | E12: =IF(_xlfn.IFNA(VLOOKUP(B12,Data!B:G,3,FALSE),"")=0, "", _xlfn.IFNA(VLOOKUP(B12,Data!B:G,3,FALSE),"")) -> 4 | F12: N/A | H12: =IF(_xlfn.IFNA(VLOOKUP(C12,Data!A:G,5,FALSE),"")=0, "Check course registration information", _xlfn.IFNA(VLOOKUP(C12,Data!A:G,5,FALSE),"")) -> CHE 30600 and CHE 37800 and CHE 42000 and CHE 45600 and CHE 43500 [concurrent ok] | J12: =IF(_xlfn.IFNA(VLOOKUP(C12,Data!A:G,6,FALSE),"")=0, "Check course registration information", _xlfn.IFNA(VLOOKUP(C12,Data!A:G,6,FALSE),"")) -> Use of process synthesis methods and concepts; detailed design of unit operation equipment, the economics of chemical plants and flow sheet optimization methods. Synthesize, develop, and evaluate a preliminary design of a chemical process that meets market requirements for a specific product. Analysis of design alternatives using case studies and optimization methods | K12: =IF(_xlfn.IFNA(VLOOKUP(C12,Data!A:H,7,FALSE),"")=0, "", _xlfn.IFNA(HYPERLINK(VLOOKUP(C12,Data!A:H,7,FALSE),"Catalog Link"),"")) -> Catalog Link | L12: =IF(_xlfn.IFNA(VLOOKUP(C12,Data!A:I,8,FALSE),"")=0, "", _xlfn.IFNA(HYPERLINK(VLOOKUP(C12,Data!A:I,8,FALSE),"Additional Information"),"")) | M12: =COUNTIF(N12:BL12,"x") -> 3 | X12: x | AS12: x | AY12: x
A13: Yes | B13: CHE 45600 | C13: CHE 45600 | D13: CHE 45600 Process Dynamics And Control | E13: =IF(_xlfn.IFNA(VLOOKUP(B13,Data!B:G,3,FALSE),"")=0, "", _xlfn.IFNA(VLOOKUP(B13,Data!B:G,3,FALSE),"")) -> 3 | F13: Semiconductor Materials, Characterization, and Processing | H13: =IF(_xlfn.IFNA(VLOOKUP(C13,Data!A:G,5,FALSE),"")=0, "Check course registration information", _xlfn.IFNA(VLOOKUP(C13,Data!A:G,5,FALSE),"")) -> CHE 37700 and CHE 34800 [concurrent ok] and CHE 37800 [concurrent ok] | J13: =IF(_xlfn.IFNA(VLOOKUP(C13,Data!A:G,6,FALSE),"")=0, "Check course registration information", _xlfn.IFNA(VLOOKUP(C13,Data!A:G,6,FALSE),"")) -> Dynamic response and control of chemical processing equipment, such as heat exchangers, chemical reactors, and absorption towers. Use is made of fundamental techniques of servomechanism theory, such as block diagrams, transfer functions, and frequency response. Introduction to advanced control techniques | K13: =IF(_xlfn.IFNA(VLOOKUP(C13,Data!A:H,7,FALSE),"")=0, "", _xlfn.IFNA(HYPERLINK(VLOOKUP(C13,Data!A:H,7,FALSE),"Catalog Link"),"")) -> Catalog Link | L13: =IF(_xlfn.IFNA(VLOOKUP(C13,Data!A:I,8,FALSE),"")=0, "", _xlfn.IFNA(HYPERLINK(VLOOKUP(C13,Data!A:I,8,FALSE),"Additional Information"),"")) | M13: =COUNTIF(N13:BL13,"x") -> 4 | X13: x | AH13: x | AY13: x | BE13: x
A14: No | B14: CHE 53600 | C14: CHE 53600 | D14: CHE 53600 Particulate Systems | E14: =IF(_xlfn.IFNA(VLOOKUP(B14,Data!B:G,3,FALSE),"")=0, "", _xlfn.IFNA(VLOOKUP(B14,Data!B:G,3,FALSE),"")) -> 3 | F14: N/A | H14: =IF(_xlfn.IFNA(VLOOKUP(C14,Data!A:G,5,FALSE),"")=0, "Check course registration information", _xlfn.IFNA(VLOOKUP(C14,Data!A:G,5,FALSE),"")) -> CHE 37700 | J14: =IF(_xlfn.IFNA(VLOOKUP(C14,Data!A:G,6,FALSE),"")=0, "Check course registration information", _xlfn.IFNA(VLOOKUP(C14,Data!A:G,6,FALSE),"")) -> A broad overview of the fundamental concepts in particulate systems including particle characterization, particle size measurement, sedimentation, fluidization, gas and liquid conveying, particle storage, fluid-particle separation, particle size enlargement and reduction, particle mixing and hazards associated with the handling of particulate solids. Practical applications are emphasized, with a focus on how particles behave differently than fluids | K14: =IF(_xlfn.IFNA(VLOOKUP(C14,Data!A:H,7,FALSE),"")=0, "", _xlfn.IFNA(HYPERLINK(VLOOKUP(C14,Data!A:H,7,FALSE),"Catalog Link"),"")) -> Catalog Link | L14: =IF(_xlfn.IFNA(VLOOKUP(C14,Data!A:I,8,FALSE),"")=0, "", _xlfn.IFNA(HYPERLINK(VLOOKUP(C14,Data!A:I,8,FALSE),"Additional Information"),"")) | M14: =COUNTIF(N14:BL14,"x") -> 0
A15: No | B15: CHE 53800 | C15: CHE 53800 | D15: CHE 53800 Design And Processing Of Particulate Products | E15: =IF(_xlfn.IFNA(VLOOKUP(B15,Data!B:G,3,FALSE),"")=0, "", _xlfn.IFNA(VLOOKUP(B15,Data!B:G,3,FALSE),"")) -> 3 | F15: N/A | H15: =IF(_xlfn.IFNA(VLOOKUP(C15,Data!A:G,5,FALSE),"")=0, "Check course registration information", _xlfn.IFNA(VLOOKUP(C15,Data!A:G,5,FALSE),"")) -> CHE 34800 or CHE 37800 | J15: =IF(_xlfn.IFNA(VLOOKUP(C15,Data!A:G,6,FALSE),"")=0, "Check course registration information", _xlfn.IFNA(VLOOKUP(C15,Data!A:G,6,FALSE),"")) -> Characterization particulate systems, use of population balances to describe processes that make or transform particles, applications in important unit processes including crystallization, granulation, milling, aerosol processes | K15: =IF(_xlfn.IFNA(VLOOKUP(C15,Data!A:H,7,FALSE),"")=0, "", _xlfn.IFNA(HYPERLINK(VLOOKUP(C15,Data!A:H,7,FALSE),"Catalog Link"),"")) -> Catalog Link | L15: =IF(_xlfn.IFNA(VLOOKUP(C15,Data!A:I,8,FALSE),"")=0, "", _xlfn.IFNA(HYPERLINK(VLOOKUP(C15,Data!A:I,8,FALSE),"Additional Information"),"")) | M15: =COUNTIF(N15:BL15,"x") -> 0
A16: Yes | B16: CHE 54000 | C16: CHE 54000 | D16: CHE 54000 Transport Penomena | E16: =IF(_xlfn.IFNA(VLOOKUP(B16,Data!B:G,3,FALSE),"")=0, "", _xlfn.IFNA(VLOOKUP(B16,Data!B:G,3,FALSE),"")) -> 3 | F16: Semiconductor Materials, Characterization, and Processing | H16: =IF(_xlfn.IFNA(VLOOKUP(C16,Data!A:G,5,FALSE),"")=0, "Check course registration information", _xlfn.IFNA(VLOOKUP(C16,Data!A:G,5,FALSE),"")) -> CHE 37800 | J16: =IF(_xlfn.IFNA(VLOOKUP(C16,Data!A:G,6,FALSE),"")=0, "Check course registration information", _xlfn.IFNA(VLOOKUP(C16,Data!A:G,6,FALSE),"")) -> Continuation of CHE 37700 and 37800. Topics in fluid mechanics, heat transfer and mass transfer including unsteady state transport problems, stream functions, potential flow, hydrodynamic and thermal layers, turbulence, and multicomponent diffusion | K16: =IF(_xlfn.IFNA(VLOOKUP(C16,Data!A:H,7,FALSE),"")=0, "", _xlfn.IFNA(HYPERLINK(VLOOKUP(C16,Data!A:H,7,FALSE),"Catalog Link"),"")) -> Catalog Link | L16: =IF(_xlfn.IFNA(VLOOKUP(C16,Data!A:I,8,FALSE),"")=0, "", _xlfn.IFNA(HYPERLINK(VLOOKUP(C16,Data!A:I,8,FALSE),"Additional Information"),"")) | M16: =COUNTIF(N16:BL16,"x") -> 3 | V16: x | AH16: x | BI16: x
A17: No | B17: CHE 54300 | C17: CHE 54300 | D17: CHE 54300 Polym Reaction Engr & Reactor Analy | E17: =IF(_xlfn.IFNA(VLOOKUP(B17,Data!B:G,3,FALSE),"")=0, "", _xlfn.IFNA(VLOOKUP(B17,Data!B:G,3,FALSE),"")) -> 3 | F17: N/A | H17: =IF(_xlfn.IFNA(VLOOKUP(C17,Data!A:G,5,FALSE),"")=0, "Check course registration information", _xlfn.IFNA(VLOOKUP(C17,Data!A:G,5,FALSE),"")) -> CHE 34800 | J17: =IF(_xlfn.IFNA(VLOOKUP(C17,Data!A:G,6,FALSE),"")=0, "Check course registration information", _xlfn.IFNA(VLOOKUP(C17,Data!A:G,6,FALSE),"")) -> Polymerization kinetics, polycondensation, gelation, radical polymerization, ionic polymerization, copolymerizations, Ziegler-Natta polymerizations, polymerization in bulk, solution, suspension and emulsion, modeling, stochastic processes, Z-transforms, batch, CSTR and tubular reactors, stability analysis, computer control, separation, and drying | K17: =IF(_xlfn.IFNA(VLOOKUP(C17,Data!A:H,7,FALSE),"")=0, "", _xlfn.IFNA(HYPERLINK(VLOOKUP(C17,Data!A:H,7,FALSE),"Catalog Link"),"")) -> Catalog Link | L17: =IF(_xlfn.IFNA(VLOOKUP(C17,Data!A:I,8,FALSE),"")=0, "", _xlfn.IFNA(HYPERLINK(VLOOKUP(C17,Data!A:I,8,FALSE),"Additional Information"),"")) | M17: =COUNTIF(N17:BL17,"x") -> 2 | W17: x | BF17: x
A18: Yes | B18: CHE 54400 | C18: CHE 54400 | D18: CHE 54400 Struct & Behav of Polymer Sys | E18: =IF(_xlfn.IFNA(VLOOKUP(B18,Data!B:G,3,FALSE),"")=0, "", _xlfn.IFNA(VLOOKUP(B18,Data!B:G,3,FALSE),"")) -> 3 | F18: Semiconductor Materials, Characterization, and Processing | H18: =IF(_xlfn.IFNA(VLOOKUP(C18,Data!A:G,5,FALSE),"")=0, "Check course registration information", _xlfn.IFNA(VLOOKUP(C18,Data!A:G,5,FALSE),"")) -> CHM 26200 or CHM 37000 | J18: =IF(_xlfn.IFNA(VLOOKUP(C18,Data!A:G,6,FALSE),"")=0, "Check course registration information", _xlfn.IFNA(VLOOKUP(C18,Data!A:G,6,FALSE),"")) -> Statistical mechanics of chain molecules, thermodynamics of polymer solutions, phase separations, experimental methods of molecular weight determination, crystallization of polymers, polymer physics, rubber elasticity, viscoelasticity | K18: =IF(_xlfn.IFNA(VLOOKUP(C18,Data!A:H,7,FALSE),"")=0, "", _xlfn.IFNA(HYPERLINK(VLOOKUP(C18,Data!A:H,7,FALSE),"Catalog Link"),"")) -> Catalog Link | L18: =IF(_xlfn.IFNA(VLOOKUP(C18,Data!A:I,8,FALSE),"")=0, "", _xlfn.IFNA(HYPERLINK(VLOOKUP(C18,Data!A:I,8,FALSE),"Additional Information"),"")) | M18: =COUNTIF(N18:BL18,"x") -> 5 | S18: x | W18: x | AH18: x | AI18: x | BF18: x
A19: No | B19: CHE 55000 | C19: CHE 55000 | D19: CHE 55000 Optimization In Chemical Engineering | E19: =IF(_xlfn.IFNA(VLOOKUP(B19,Data!B:G,3,FALSE),"")=0, "", _xlfn.IFNA(VLOOKUP(B19,Data!B:G,3,FALSE),"")) -> 3 | F19: N/A | H19: =IF(_xlfn.IFNA(VLOOKUP(C19,Data!A:G,5,FALSE),"")=0, "Check course registration information", _xlfn.IFNA(VLOOKUP(C19,Data!A:G,5,FALSE),"")) -> Senior status and above | J19: =IF(_xlfn.IFNA(VLOOKUP(C19,Data!A:G,6,FALSE),"")=0, "Check course registration information", _xlfn.IFNA(VLOOKUP(C19,Data!A:G,6,FALSE),"")) -> Survey of the basic computational tools for solving nonlinear constrained and unconstrained optimization problems. Emphasis on methods applicable to problems arising in chemical plant design, process operations and scheduling, parameter estimation, and waste energy reutilization | K19: =IF(_xlfn.IFNA(VLOOKUP(C19,Data!A:H,7,FALSE),"")=0, "", _xlfn.IFNA(HYPERLINK(VLOOKUP(C19,Data!A:H,7,FALSE),"Catalog Link"),"")) -> Catalog Link | L19: =IF(_xlfn.IFNA(VLOOKUP(C19,Data!A:I,8,FALSE),"")=0, "", _xlfn.IFNA(HYPERLINK(VLOOKUP(C19,Data!A:I,8,FALSE),"Additional Information"),"")) | M19: =COUNTIF(N19:BL19,"x") -> 2 | O19: x | AS19: x
A20: No | B20: CHE 55500 | C20: CHE 55500 | D20: CHE 55500 Computer Integrated Process Operations | E20: =IF(_xlfn.IFNA(VLOOKUP(B20,Data!B:G,3,FALSE),"")=0, "", _xlfn.IFNA(VLOOKUP(B20,Data!B:G,3,FALSE),"")) -> 3 | F20: N/A | H20: =IF(_xlfn.IFNA(VLOOKUP(C20,Data!A:G,5,FALSE),"")=0, "Check course registration information", _xlfn.IFNA(VLOOKUP(C20,Data!A:G,5,FALSE),"")) -> Senior status and above | J20: =IF(_xlfn.IFNA(VLOOKUP(C20,Data!A:G,6,FALSE),"")=0, "Check course registration information", _xlfn.IFNA(VLOOKUP(C20,Data!A:G,6,FALSE),"")) -> Introduction to computer-aided process operations management. Topics include: process monitoring, regulatory control, data reconciliation, unit and plant-wide optimization, process fault diagnosis, supervisory control, planning, and scheduling. A design project involving a unified application of the presented methodologies is taken from a published industrial benchmark problem | K20: =IF(_xlfn.IFNA(VLOOKUP(C20,Data!A:H,7,FALSE),"")=0, "", _xlfn.IFNA(HYPERLINK(VLOOKUP(C20,Data!A:H,7,FALSE),"Catalog Link"),"")) -> Catalog Link | L20: =IF(_xlfn.IFNA(VLOOKUP(C20,Data!A:I,8,FALSE),"")=0, "", _xlfn.IFNA(HYPERLINK(VLOOKUP(C20,Data!A:I,8,FALSE),"Additional Information"),"")) | M20: =COUNTIF(N20:BL20,"x") -> 2 | O20: x | AS20: x
A21: No | B21: CHE 55700 | C21: CHE 55700 | D21: CHE 55700 Intelligent Systems In Process Engineering | E21: =IF(_xlfn.IFNA(VLOOKUP(B21,Data!B:G,3,FALSE),"")=0, "", _xlfn.IFNA(VLOOKUP(B21,Data!B:G,3,FALSE),"")) -> 3 | F21: N/A | H21: =IF(_xlfn.IFNA(VLOOKUP(C21,Data!A:G,5,FALSE),"")=0, "Check course registration information", _xlfn.IFNA(VLOOKUP(C21,Data!A:G,5,FALSE),"")) -> Senior status and above | J21: =IF(_xlfn.IFNA(VLOOKUP(C21,Data!A:G,6,FALSE),"")=0, "Check course registration information", _xlfn.IFNA(VLOOKUP(C21,Data!A:G,6,FALSE),"")) -> Introduction to artificial intelligence concepts and techniques and their application to important problems in process systems engineering. Topics covered include: introduction to artificial intelligence, knowledge representation and search, knowledge-based systems, neural networks, genetic algorithms, inexact reasoning techniques, industrial case studies in process fault diagnosis and control, design and synthesis, planning and scheduling, AI languages, tools, and environments | K21: =IF(_xlfn.IFNA(VLOOKUP(C21,Data!A:H,7,FALSE),"")=0, "", _xlfn.IFNA(HYPERLINK(VLOOKUP(C21,Data!A:H,7,FALSE),"Catalog Link"),"")) -> Catalog Link | L21: =IF(_xlfn.IFNA(VLOOKUP(C21,Data!A:I,8,FALSE),"")=0, "", _xlfn.IFNA(HYPERLINK(VLOOKUP(C21,Data!A:I,8,FALSE),"Additional Information"),"")) | M21: =COUNTIF(N21:BL21,"x") -> 0
A22: No | B22: CHE 55800 | C22: CHE 55800 | D22: CHE 55800 Rate Control Sep Process | E22: =IF(_xlfn.IFNA(VLOOKUP(B22,Data!B:G,3,FALSE),"")=0, "", _xlfn.IFNA(VLOOKUP(B22,Data!B:G,3,FALSE),"")) -> 3 | F22: N/A | H22: =IF(_xlfn.IFNA(VLOOKUP(C22,Data!A:G,5,FALSE),"")=0, "Check course registration information", _xlfn.IFNA(VLOOKUP(C22,Data!A:G,5,FALSE),"")) -> CHE 30600 or CHE 37800 | J22: =IF(_xlfn.IFNA(VLOOKUP(C22,Data!A:G,6,FALSE),"")=0, "Check course registration information", _xlfn.IFNA(VLOOKUP(C22,Data!A:G,6,FALSE),"")) -> Rate-controlled separation processes based on solute movement (adsorption, chromatography and ion exchange), membranes (reverse osmosis, ultrafiltration, and gas permeation), and crystallization | K22: =IF(_xlfn.IFNA(VLOOKUP(C22,Data!A:H,7,FALSE),"")=0, "", _xlfn.IFNA(HYPERLINK(VLOOKUP(C22,Data!A:H,7,FALSE),"Catalog Link"),"")) -> Catalog Link | L22: =IF(_xlfn.IFNA(VLOOKUP(C22,Data!A:I,8,FALSE),"")=0, "", _xlfn.IFNA(HYPERLINK(VLOOKUP(C22,Data!A:I,8,FALSE),"Additional Information"),"")) | M22: =COUNTIF(N22:BL22,"x") -> 0
A23: No | B23: CHE 56000 | C23: CHE 56000 | D23: CHE 56000 Introduction To Energy Storage Systems | E23: 3 | F23: N/A | H23: =IF(_xlfn.IFNA(VLOOKUP(C23,Data!A:G,5,FALSE),"")=0, "Check course registration information", _xlfn.IFNA(VLOOKUP(C23,Data!A:G,5,FALSE),"")) -> Senior status and above | J23: =IF(_xlfn.IFNA(VLOOKUP(C23,Data!A:G,6,FALSE),"")=0, "Check course registration information", _xlfn.IFNA(VLOOKUP(C23,Data!A:G,6,FALSE),"")) -> Energy Storage Systems Laboratory course is designed to introduce fundamentals of electrochemistry and electrochemical engineering of rechargeable lithium ion batteries (LIBs) to undergraduate and graduate students. The course will be reviewing working principles of LIBs, hands-on experience on their assembly, charge-discharge testing, data analysis and related safety aspects. Strong emphasis will be given on the Li-ion battery technology, nanotechnology implementation and the materials design. Beyond conventional Li-ion systems and Pb-acid batteries, next generation Na-ion, K-ion and Li-S batteries will be discussed and designed. Students will be fabricating and testing high energy density batteries utilizing engineered electrodes, electrolytes and separators. Broader perspectives on sustainable, cost effective, longer lasting battery manufacturing will be provided. | K23: =IF(_xlfn.IFNA(VLOOKUP(C23,Data!A:H,7,FALSE),"")=0, "", _xlfn.IFNA(HYPERLINK(VLOOKUP(C23,Data!A:H,7,FALSE),"Catalog Link"),"")) -> Catalog Link | L23: =IF(_xlfn.IFNA(VLOOKUP(C23,Data!A:I,8,FALSE),"")=0, "", _xlfn.IFNA(HYPERLINK(VLOOKUP(C23,Data!A:I,8,FALSE),"Additional Information"),"")) | M23: =COUNTIF(N23:BL23,"x") -> 0
A24: No | B24: CHE 56400 | C24: CHE 56400 | D24: CHE 56400 Organic Electronic Materials And Devices | E24: =IF(_xlfn.IFNA(VLOOKUP(B24,Data!B:G,3,FALSE),"")=0, "", _xlfn.IFNA(VLOOKUP(B24,Data!B:G,3,FALSE),"")) -> 3 | F24: Semiconductor Materials, Characterization, and Processing | H24: =IF(_xlfn.IFNA(VLOOKUP(C24,Data!A:G,5,FALSE),"")=0, "Check course registration information", _xlfn.IFNA(VLOOKUP(C24,Data!A:G,5,FALSE),"")) -> CHM 26100 or CHM 25500 or CHM 25700 | J24: =IF(_xlfn.IFNA(VLOOKUP(C24,Data!A:G,6,FALSE),"")=0, "Check course registration information", _xlfn.IFNA(VLOOKUP(C24,Data!A:G,6,FALSE),"")) -> This course introduces the synthesis, optoelectronic properties, transport physics, and device operation of organic and hybrid electronic materials and devices. This course will review how the molecular architecture of small molecule and polymer semiconductors can be turned to alter the optoelectronic properties of the materials in solution and in the solid state. A number of relevant materials interactions will be covered, including: photoexcitation and recombination, intermolecular charge transport mechanisms, and energy transfer processes. Additionally, we will observe how these processes are relevant to applications such as organic field-effect transistors (OFETs), organic light-emitting diodes (OLEDs), organic photovoltaic (OPV) devices, and organic memory elements. Finally, a new type of organic-inorganic hybrid material called hybrid halide perovskite will be introduced | K24: =IF(_xlfn.IFNA(VLOOKUP(C24,Data!A:H,7,FALSE),"")=0, "", _xlfn.IFNA(HYPERLINK(VLOOKUP(C24,Data!A:H,7,FALSE),"Catalog Link"),"")) -> Catalog Link | L24: =IF(_xlfn.IFNA(VLOOKUP(C24,Data!A:I,8,FALSE),"")=0, "", _xlfn.IFNA(HYPERLINK(VLOOKUP(C24,Data!A:I,8,FALSE),"Additional Information"),"")) | M24: =COUNTIF(N24:BL24,"x") -> 3 | S24: x | W24: x | BF24: x
A25: No | B25: CHE 59700 | C25: CHE 59700 | D25: CHE 59700 Crystallization Systems in Engr | E25: =IF(_xlfn.IFNA(VLOOKUP(B25,Data!B:G,3,FALSE),"")=0, "", _xlfn.IFNA(VLOOKUP(B25,Data!B:G,3,FALSE),"")) | F25: N/A | H25: =IF(_xlfn.IFNA(VLOOKUP(C25,Data!A:G,5,FALSE),"")=0, "Check course registration information", _xlfn.IFNA(VLOOKUP(C25,Data!A:G,5,FALSE),"")) -> Check course registration information | J25: =IF(_xlfn.IFNA(VLOOKUP(C25,Data!A:G,6,FALSE),"")=0, "Check course registration information", _xlfn.IFNA(VLOOKUP(C25,Data!A:G,6,FALSE),"")) -> Check course registration information | K25: =IF(_xlfn.IFNA(VLOOKUP(C25,Data!A:H,7,FALSE),"")=0, "", _xlfn.IFNA(HYPERLINK(VLOOKUP(C25,Data!A:H,7,FALSE),"Catalog Link"),"")) -> Catalog Link | L25: =IF(_xlfn.IFNA(VLOOKUP(C25,Data!A:I,8,FALSE),"")=0, "", _xlfn.IFNA(HYPERLINK(VLOOKUP(C25,Data!A:I,8,FALSE),"Additional Information"),"")) | M25: =COUNTIF(N25:BL25,"x") -> 1 | BF25: x
A26: No | B26: CHE 59700 | C26: CHE 59700-1 | D26: CHE 59700 Industial Catalytic Processes | E26: =IF(_xlfn.IFNA(VLOOKUP(B26,Data!B:G,3,FALSE),"")=0, "", _xlfn.IFNA(VLOOKUP(B26,Data!B:G,3,FALSE),"")) | F26: N/A | H26: =IF(_xlfn.IFNA(VLOOKUP(C26,Data!A:G,5,FALSE),"")=0, "Check course registration information", _xlfn.IFNA(VLOOKUP(C26,Data!A:G,5,FALSE),"")) -> Check course registration information | J26: =IF(_xlfn.IFNA(VLOOKUP(C26,Data!A:G,6,FALSE),"")=0, "Check course registration information", _xlfn.IFNA(VLOOKUP(C26,Data!A:G,6,FALSE),"")) -> Check course registration information | K26: =IF(_xlfn.IFNA(VLOOKUP(C26,Data!A:H,7,FALSE),"")=0, "", _xlfn.IFNA(HYPERLINK(VLOOKUP(C26,Data!A:H,7,FALSE),"Catalog Link"),"")) -> Catalog Link | L26: =IF(_xlfn.IFNA(VLOOKUP(C26,Data!A:I,8,FALSE),"")=0, "", _xlfn.IFNA(HYPERLINK(VLOOKUP(C26,Data!A:I,8,FALSE),"Additional Information"),"")) | M26: =COUNTIF(N26:BL26,"x") -> 0
A27: No | B27: CHE 59700 | C27: CHE 59700-2 | D27: CHE 59700 Industrial Chemical Technology | E27: =IF(_xlfn.IFNA(VLOOKUP(B27,Data!B:G,3,FALSE),"")=0, "", _xlfn.IFNA(VLOOKUP(B27,Data!B:G,3,FALSE),"")) | F27: N/A | H27: =IF(_xlfn.IFNA(VLOOKUP(C27,Data!A:G,5,FALSE),"")=0, "Check course registration information", _xlfn.IFNA(VLOOKUP(C27,Data!A:G,5,FALSE),"")) -> Check course registration information | J27: =IF(_xlfn.IFNA(VLOOKUP(C27,Data!A:G,6,FALSE),"")=0, "Check course registration information", _xlfn.IFNA(VLOOKUP(C27,Data!A:G,6,FALSE),"")) -> Check course registration information | K27: =IF(_xlfn.IFNA(VLOOKUP(C27,Data!A:H,7,FALSE),"")=0, "", _xlfn.IFNA(HYPERLINK(VLOOKUP(C27,Data!A:H,7,FALSE),"Catalog Link"),"")) -> Catalog Link | L27: =IF(_xlfn.IFNA(VLOOKUP(C27,Data!A:I,8,FALSE),"")=0, "", _xlfn.IFNA(HYPERLINK(VLOOKUP(C27,Data!A:I,8,FALSE),"Additional Information"),"")) | M27: =COUNTIF(N27:BL27,"x") -> 0
A28: No | B28: CHE 59700 | C28: CHE 59700-3 | D28: CHE 59700 Org Elec Materials and Devices | E28: =IF(_xlfn.IFNA(VLOOKUP(B28,Data!B:G,3,FALSE),"")=0, "", _xlfn.IFNA(VLOOKUP(B28,Data!B:G,3,FALSE),"")) | F28: N/A | H28: =IF(_xlfn.IFNA(VLOOKUP(C28,Data!A:G,5,FALSE),"")=0, "Check course registration information", _xlfn.IFNA(VLOOKUP(C28,Data!A:G,5,FALSE),"")) -> Check course registration information | J28: =IF(_xlfn.IFNA(VLOOKUP(C28,Data!A:G,6,FALSE),"")=0, "Check course registration information", _xlfn.IFNA(VLOOKUP(C28,Data!A:G,6,FALSE),"")) -> Check course registration information | K28: =IF(_xlfn.IFNA(VLOOKUP(C28,Data!A:H,7,FALSE),"")=0, "", _xlfn.IFNA(HYPERLINK(VLOOKUP(C28,Data!A:H,7,FALSE),"Catalog Link"),"")) -> Catalog Link | L28: =IF(_xlfn.IFNA(VLOOKUP(C28,Data!A:I,8,FALSE),"")=0, "", _xlfn.IFNA(HYPERLINK(VLOOKUP(C28,Data!A:I,8,FALSE),"Additional Information"),"")) | M28: =COUNTIF(N28:BL28,"x") -> 3 | S28: x | W28: x | BF28: x
A29: No | B29: CHE 59700 | C29: CHE 59700-4 | D29: CHE 59700 Process Synthesis | E29: =IF(_xlfn.IFNA(VLOOKUP(B29,Data!B:G,3,FALSE),"")=0, "", _xlfn.IFNA(VLOOKUP(B29,Data!B:G,3,FALSE),"")) | F29: N/A | H29: =IF(_xlfn.IFNA(VLOOKUP(C29,Data!A:G,5,FALSE),"")=0, "Check course registration information", _xlfn.IFNA(VLOOKUP(C29,Data!A:G,5,FALSE),"")) -> Check course registration information | J29: =IF(_xlfn.IFNA(VLOOKUP(C29,Data!A:G,6,FALSE),"")=0, "Check course registration information", _xlfn.IFNA(VLOOKUP(C29,Data!A:G,6,FALSE),"")) -> Check course registration information | K29: =IF(_xlfn.IFNA(VLOOKUP(C29,Data!A:H,7,FALSE),"")=0, "", _xlfn.IFNA(HYPERLINK(VLOOKUP(C29,Data!A:H,7,FALSE),"Catalog Link"),"")) -> Catalog Link | L29: =IF(_xlfn.IFNA(VLOOKUP(C29,Data!A:I,8,FALSE),"")=0, "", _xlfn.IFNA(HYPERLINK(VLOOKUP(C29,Data!A:I,8,FALSE),"Additional Information"),"")) | M29: =COUNTIF(N29:BL29,"x") -> 3 | X29: x | AS29: x | AY29: x
A30: No | B30: CHE 59700 | C30: CHE 59700-5 | D30: CHE 59700 System Analysis of Energy Prod/ Energy Systems | E30: =IF(_xlfn.IFNA(VLOOKUP(B30,Data!B:G,3,FALSE),"")=0, "", _xlfn.IFNA(VLOOKUP(B30,Data!B:G,3,FALSE),"")) | F30: N/A | H30: =IF(_xlfn.IFNA(VLOOKUP(C30,Data!A:G,5,FALSE),"")=0, "Check course registration information", _xlfn.IFNA(VLOOKUP(C30,Data!A:G,5,FALSE),"")) -> Check course registration information | J30: =IF(_xlfn.IFNA(VLOOKUP(C30,Data!A:G,6,FALSE),"")=0, "Check course registration information", _xlfn.IFNA(VLOOKUP(C30,Data!A:G,6,FALSE),"")) -> Check course registration information | K30: =IF(_xlfn.IFNA(VLOOKUP(C30,Data!A:H,7,FALSE),"")=0, "", _xlfn.IFNA(HYPERLINK(VLOOKUP(C30,Data!A:H,7,FALSE),"Catalog Link"),"")) -> Catalog Link | L30: =IF(_xlfn.IFNA(VLOOKUP(C30,Data!A:I,8,FALSE),"")=0, "", _xlfn.IFNA(HYPERLINK(VLOOKUP(C30,Data!A:I,8,FALSE),"Additional Information"),"")) | M30: =COUNTIF(N30:BL30,"x") -> 1 | AY30: x
A31: No | B31: CHE 59700 | C31: CHE 59700-6 | D31: CHE 59700 Data Science in ChE | E31: =IF(_xlfn.IFNA(VLOOKUP(B31,Data!B:G,3,FALSE),"")=0, "", _xlfn.IFNA(VLOOKUP(B31,Data!B:G,3,FALSE),"")) | F31: N/A | H31: =IF(_xlfn.IFNA(VLOOKUP(C31,Data!A:G,5,FALSE),"")=0, "Check course registration information", _xlfn.IFNA(VLOOKUP(C31,Data!A:G,5,FALSE),"")) -> Check course registration information | J31: =IF(_xlfn.IFNA(VLOOKUP(C31,Data!A:G,6,FALSE),"")=0, "Check course registration information", _xlfn.IFNA(VLOOKUP(C31,Data!A:G,6,FALSE),"")) -> Check course registration information | K31: =IF(_xlfn.IFNA(VLOOKUP(C31,Data!A:H,7,FALSE),"")=0, "", _xlfn.IFNA(HYPERLINK(VLOOKUP(C31,Data!A:H,7,FALSE),"Catalog Link"),"")) -> Catalog Link | L31: =IF(_xlfn.IFNA(VLOOKUP(C31,Data!A:I,8,FALSE),"")=0, "", _xlfn.IFNA(HYPERLINK(VLOOKUP(C31,Data!A:I,8,FALSE),"Additional Information"),"")) | M31: =COUNTIF(N31:BL31,"x") -> 5 | O31: x | U31: x | AY31: x | BD31: x | BK31: x
A32: No | B32: CHE 59700 | C32: CHE 59700-7 | D32: CHE 59700 Manufacturing Advanced Composites | E32: =IF(_xlfn.IFNA(VLOOKUP(B32,Data!B:G,3,FALSE),"")=0, "", _xlfn.IFNA(VLOOKUP(B32,Data!B:G,3,FALSE),"")) | F32: Semiconductor Materials, Characterization, and Processing | H32: =IF(_xlfn.IFNA(VLOOKUP(C32,Data!A:G,5,FALSE),"")=0, "Check course registration information", _xlfn.IFNA(VLOOKUP(C32,Data!A:G,5,FALSE),"")) -> Check course registration information | J32: =IF(_xlfn.IFNA(VLOOKUP(C32,Data!A:G,6,FALSE),"")=0, "Check course registration information", _xlfn.IFNA(VLOOKUP(C32,Data!A:G,6,FALSE),"")) -> Check course registration information | K32: =IF(_xlfn.IFNA(VLOOKUP(C32,Data!A:H,7,FALSE),"")=0, "", _xlfn.IFNA(HYPERLINK(VLOOKUP(C32,Data!A:H,7,FALSE),"Catalog Link"),"")) -> Catalog Link | L32: =IF(_xlfn.IFNA(VLOOKUP(C32,Data!A:I,8,FALSE),"")=0, "", _xlfn.IFNA(HYPERLINK(VLOOKUP(C32,Data!A:I,8,FALSE),"Additional Information"),"")) | M32: =COUNTIF(N32:BL32,"x") -> 0
A33: No | B33: CHE 59700A | C33: CHE 59700A | D33: CHE 59700A Risk Mgmt. Proc. Develop | E33: =IF(_xlfn.IFNA(VLOOKUP(B33,Data!B:G,3,FALSE),"")=0, "", _xlfn.IFNA(VLOOKUP(B33,Data!B:G,3,FALSE),"")) -> 3 | F33: N/A | H33: =IF(_xlfn.IFNA(VLOOKUP(C33,Data!A:G,5,FALSE),"")=0, "Check course registration information", _xlfn.IFNA(VLOOKUP(C33,Data!A:G,5,FALSE),"")) -> Check course registration information | J33: =IF(_xlfn.IFNA(VLOOKUP(C33,Data!A:G,6,FALSE),"")=0, "Check course registration information", _xlfn.IFNA(VLOOKUP(C33,Data!A:G,6,FALSE),"")) -> Legacy information online. | K33: =IF(_xlfn.IFNA(VLOOKUP(C33,Data!A:H,7,FALSE),"")=0, "", _xlfn.IFNA(HYPERLINK(VLOOKUP(C33,Data!A:H,7,FALSE),"Catalog Link"),"")) -> Catalog Link | L33: =IF(_xlfn.IFNA(VLOOKUP(C33,Data!A:I,8,FALSE),"")=0, "", _xlfn.IFNA(HYPERLINK(VLOOKUP(C33,Data!A:I,8,FALSE),"Additional Information"),"")) -> Additional Information | M33: =COUNTIF(N33:BL33,"x") -> 2 | X33: x | AS33: x
A34: No | B34: CHE 59700C | C34: CHE 59700C | D34: CHE 59700C Intro to Energy Stor Sys | E34: 3 | F34: N/A | H34: =IF(_xlfn.IFNA(VLOOKUP(C34,Data!A:G,5,FALSE),"")=0, "Check course registration information", _xlfn.IFNA(VLOOKUP(C34,Data!A:G,5,FALSE),"")) -> Check course registration information | J34: =IF(_xlfn.IFNA(VLOOKUP(C34,Data!A:G,6,FALSE),"")=0, "Check course registration information", _xlfn.IFNA(VLOOKUP(C34,Data!A:G,6,FALSE),"")) -> Now CHE 56000 | K34: =IF(_xlfn.IFNA(VLOOKUP(C34,Data!A:H,7,FALSE),"")=0, "", _xlfn.IFNA(HYPERLINK(VLOOKUP(C34,Data!A:H,7,FALSE),"Catalog Link"),"")) -> Catalog Link | L34: =IF(_xlfn.IFNA(VLOOKUP(C34,Data!A:I,8,FALSE),"")=0, "", _xlfn.IFNA(HYPERLINK(VLOOKUP(C34,Data!A:I,8,FALSE),"Additional Information"),"")) | M34: =COUNTIF(N34:BL34,"x") -> 0
A35: No | B35: CHE 59700N | C35: CHE 59700N | D35: CHE 59700N Intro to Nanoscale | E35: =IF(_xlfn.IFNA(VLOOKUP(B35,Data!B:G,3,FALSE),"")=0, "", _xlfn.IFNA(VLOOKUP(B35,Data!B:G,3,FALSE),"")) -> 3 | F35: N/A | H35: =IF(_xlfn.IFNA(VLOOKUP(C35,Data!A:G,5,FALSE),"")=0, "Check course registration information", _xlfn.IFNA(VLOOKUP(C35,Data!A:G,5,FALSE),"")) -> Check course registration information | J35: =IF(_xlfn.IFNA(VLOOKUP(C35,Data!A:G,6,FALSE),"")=0, "Check course registration information", _xlfn.IFNA(VLOOKUP(C35,Data!A:G,6,FALSE),"")) -> Legacy information online. | K35: =IF(_xlfn.IFNA(VLOOKUP(C35,Data!A:H,7,FALSE),"")=0, "", _xlfn.IFNA(HYPERLINK(VLOOKUP(C35,Data!A:H,7,FALSE),"Catalog Link"),"")) -> Catalog Link | L35: =IF(_xlfn.IFNA(VLOOKUP(C35,Data!A:I,8,FALSE),"")=0, "", _xlfn.IFNA(HYPERLINK(VLOOKUP(C35,Data!A:I,8,FALSE),"Additional Information"),"")) -> Additional Information | M35: =COUNTIF(N35:BL35,"x") -> 4 | N35: x | S35: x | W35: x | BF35: x
A36: No | B36: CHE 59700Q | C36: CHE 59700Q | D36: CHE 59700Q Intr. Quantum Cntrl Engr | E36: =IF(_xlfn.IFNA(VLOOKUP(B36,Data!B:G,3,FALSE),"")=0, "", _xlfn.IFNA(VLOOKUP(B36,Data!B:G,3,FALSE),"")) | F36: N/A | H36: =IF(_xlfn.IFNA(VLOOKUP(C36,Data!A:G,5,FALSE),"")=0, "Check course registration information", _xlfn.IFNA(VLOOKUP(C36,Data!A:G,5,FALSE),"")) -> Check course registration information | J36: =IF(_xlfn.IFNA(VLOOKUP(C36,Data!A:G,6,FALSE),"")=0, "Check course registration information", _xlfn.IFNA(VLOOKUP(C36,Data!A:G,6,FALSE),"")) -> Check course registration information | K36: =IF(_xlfn.IFNA(VLOOKUP(C36,Data!A:H,7,FALSE),"")=0, "", _xlfn.IFNA(HYPERLINK(VLOOKUP(C36,Data!A:H,7,FALSE),"Catalog Link"),"")) -> Catalog Link | L36: =IF(_xlfn.IFNA(VLOOKUP(C36,Data!A:I,8,FALSE),"")=0, "", _xlfn.IFNA(HYPERLINK(VLOOKUP(C36,Data!A:I,8,FALSE),"Additional Information"),"")) | M36: =COUNTIF(N36:BL36,"x") -> 2 | O36: x | AS36: x
A37: No | B37: CHE 59700S | C37: CHE 59700S | D37: CHE 59700S Advanced Solar Conversion | E37: =IF(_xlfn.IFNA(VLOOKUP(B37,Data!B:G,3,FALSE),"")=0, "", _xlfn.IFNA(VLOOKUP(B37,Data!B:G,3,FALSE),"")) | F37: N/A | H37: =IF(_xlfn.IFNA(VLOOKUP(C37,Data!A:G,5,FALSE),"")=0, "Check course registration information", _xlfn.IFNA(VLOOKUP(C37,Data!A:G,5,FALSE),"")) -> Check course registration information | J37: =IF(_xlfn.IFNA(VLOOKUP(C37,Data!A:G,6,FALSE),"")=0, "Check course registration information", _xlfn.IFNA(VLOOKUP(C37,Data!A:G,6,FALSE),"")) -> Check course registration information | K37: =IF(_xlfn.IFNA(VLOOKUP(C37,Data!A:H,7,FALSE),"")=0, "", _xlfn.IFNA(HYPERLINK(VLOOKUP(C37,Data!A:H,7,FALSE),"Catalog Link"),"")) -> Catalog Link | L37: =IF(_xlfn.IFNA(VLOOKUP(C37,Data!A:I,8,FALSE),"")=0, "", _xlfn.IFNA(HYPERLINK(VLOOKUP(C37,Data!A:I,8,FALSE),"Additional Information"),"")) | M37: =COUNTIF(N37:BL37,"x") -> 1 | BF37: x
A38: No | B38: CHM 11500 | C38: CHM 11500 | D38: CHM 11500 General Chemistry-I (UCC: SCI) | E38: =IF(_xlfn.IFNA(VLOOKUP(B38,Data!B:G,3,FALSE),"")=0, "", _xlfn.IFNA(VLOOKUP(B38,Data!B:G,3,FALSE),"")) -> 4 | F38: Semiconductor Materials, Characterization, and Processing | H38: =IF(_xlfn.IFNA(VLOOKUP(C38,Data!A:G,5,FALSE),"")=0, "Check course registration information", _xlfn.IFNA(VLOOKUP(C38,Data!A:G,5,FALSE),"")) -> MA 15900 or MA 15800 or MA 15400 or MATH 15400 or MA 16100 [concurrent ok] or MA 16500 [concurrent ok] or MA 22300 [concurrent ok] or MA 23100 [concurrent ok] or MA 16010 [concurrent ok]) or ALEKS Math Assessment 075 or SATR Math 620 or SAT Mathematics 600 or ACT Math 26 | J38: =IF(_xlfn.IFNA(VLOOKUP(C38,Data!A:G,6,FALSE),"")=0, "Check course registration information", _xlfn.IFNA(VLOOKUP(C38,Data!A:G,6,FALSE),"")) -> Stoichiometry; atomic structure; periodic properties; ionic and covalent bonding; molecular geometry; gases, liquids, and solids; crystal structure; thermochemistry; descriptive chemistry of metals and non-metals. Required of students majoring in science and students in engineering who are not in CHM 12300. One year of high school chemistry or one semester of college chemistry required. CTL:IPS 1721 General Chemistry I w/lab | K38: =IF(_xlfn.IFNA(VLOOKUP(C38,Data!A:H,7,FALSE),"")=0, "", _xlfn.IFNA(HYPERLINK(VLOOKUP(C38,Data!A:H,7,FALSE),"Catalog Link"),"")) -> Catalog Link | L38: =IF(_xlfn.IFNA(VLOOKUP(C38,Data!A:I,8,FALSE),"")=0, "", _xlfn.IFNA(HYPERLINK(VLOOKUP(C38,Data!A:I,8,FALSE),"Additional Information"),"")) | M38: =COUNTIF(N38:BL38,"x") -> 3 | W38: x | AS38: x | BF38: x
A39: No | B39: CHM 11600 | C39: CHM 11600 | D39: CHM 11600 General Chemistry-II (UCC: SCI) | E39: =IF(_xlfn.IFNA(VLOOKUP(B39,Data!B:G,3,FALSE),"")=0, "", _xlfn.IFNA(VLOOKUP(B39,Data!B:G,3,FALSE),"")) -> 4 | F39: Semiconductor Materials, Characterization, and Processing | H39: =IF(_xlfn.IFNA(VLOOKUP(C39,Data!A:G,5,FALSE),"")=0, "Check course registration information", _xlfn.IFNA(VLOOKUP(C39,Data!A:G,5,FALSE),"")) -> CHM 11200 or CHM 11500 or CHM 12500 or CHM 10901 or CHM 12901 or CHM 12300 or CHM 13500 or (CHEM C1050 and CHEM C1250) or (CHEM C1010 and CHEM C1210 | J39: =IF(_xlfn.IFNA(VLOOKUP(C39,Data!A:G,6,FALSE),"")=0, "Check course registration information", _xlfn.IFNA(VLOOKUP(C39,Data!A:G,6,FALSE),"")) -> A continuation of CHM 11500. Solutions; quantitative equilibria in aqueous solution; introductory thermodynamics; oxidation-reduction and electrochemistry; chemical kinetics; qualitative analysis; further descriptive chemistry of metals and nonmetals. CTL:IPS 1722 General Chemistry II w/lab | K39: =IF(_xlfn.IFNA(VLOOKUP(C39,Data!A:H,7,FALSE),"")=0, "", _xlfn.IFNA(HYPERLINK(VLOOKUP(C39,Data!A:H,7,FALSE),"Catalog Link"),"")) -> Catalog Link | L39: =IF(_xlfn.IFNA(VLOOKUP(C39,Data!A:I,8,FALSE),"")=0, "", _xlfn.IFNA(HYPERLINK(VLOOKUP(C39,Data!A:I,8,FALSE),"Additional Information"),"")) | M39: =COUNTIF(N39:BL39,"x") -> 4 | S39: x | W39: x | AS39: x | BF39: x
A40: No | B40: CHM 22404 | C40: CHM 22404 | D40: CHM 22404 Quantitative Analysis | E40: =IF(_xlfn.IFNA(VLOOKUP(B40,Data!B:G,3,FALSE),"")=0, "", _xlfn.IFNA(VLOOKUP(B40,Data!B:G,3,FALSE),"")) -> 3 | F40: N/A | H40: =IF(_xlfn.IFNA(VLOOKUP(C40,Data!A:G,5,FALSE),"")=0, "Check course registration information", _xlfn.IFNA(VLOOKUP(C40,Data!A:G,5,FALSE),"")) -> CHM 11600 or CHM 12600 or CHM 12901 or CHM 13600 or (CHM 11610 and CHM 11620 | J40: =IF(_xlfn.IFNA(VLOOKUP(C40,Data!A:G,6,FALSE),"")=0, "Check course registration information", _xlfn.IFNA(VLOOKUP(C40,Data!A:G,6,FALSE),"")) -> Introduction to approaches analytical chemists use to analyze the composition of matter, including statistics, calibration, and understanding chemical equilibrium (acid/base, complexation, solubility, polyprotic acid treatment, acid/base/redox/precipitation titrations); general approaches to analysis at the trace level; recognition and evaluation of possible sources of error and how error propagates; introduction to how light interacts with matter (and how analytical chemists can take advantage of this) | K40: =IF(_xlfn.IFNA(VLOOKUP(C40,Data!A:H,7,FALSE),"")=0, "", _xlfn.IFNA(HYPERLINK(VLOOKUP(C40,Data!A:H,7,FALSE),"Catalog Link"),"")) -> Catalog Link | L40: =IF(_xlfn.IFNA(VLOOKUP(C40,Data!A:I,8,FALSE),"")=0, "", _xlfn.IFNA(HYPERLINK(VLOOKUP(C40,Data!A:I,8,FALSE),"Additional Information"),"")) | M40: =COUNTIF(N40:BL40,"x") -> 2 | S40: x | BC40: x
A41: No | B41: CHM 24100 | C41: CHM 24100 | D41: CHM 24100 Introductory Inorganic Chemistry | E41: =IF(_xlfn.IFNA(VLOOKUP(B41,Data!B:G,3,FALSE),"")=0, "", _xlfn.IFNA(VLOOKUP(B41,Data!B:G,3,FALSE),"")) -> 4 | F41: N/A | H41: =IF(_xlfn.IFNA(VLOOKUP(C41,Data!A:G,5,FALSE),"")=0, "Check course registration information", _xlfn.IFNA(VLOOKUP(C41,Data!A:G,5,FALSE),"")) -> CHM 11600 or CHM 12600 or CHM 13600 or (CHEM C1020 and CHEM C1220) or (CHEM C1060 and CHEM C1260 | J41: =IF(_xlfn.IFNA(VLOOKUP(C41,Data!A:G,6,FALSE),"")=0, "Check course registration information", _xlfn.IFNA(VLOOKUP(C41,Data!A:G,6,FALSE),"")) -> Descriptive inorganic chemistry dealing in a systematic way with the elements and the structures, properties, and reactions of their compounds. Required of students majoring in chemistry | K41: =IF(_xlfn.IFNA(VLOOKUP(C41,Data!A:H,7,FALSE),"")=0, "", _xlfn.IFNA(HYPERLINK(VLOOKUP(C41,Data!A:H,7,FALSE),"Catalog Link"),"")) -> Catalog Link | L41: =IF(_xlfn.IFNA(VLOOKUP(C41,Data!A:I,8,FALSE),"")=0, "", _xlfn.IFNA(HYPERLINK(VLOOKUP(C41,Data!A:I,8,FALSE),"Additional Information"),"")) | M41: =COUNTIF(N41:BL41,"x") -> 0
A42: No | B42: CHM 26100 | C42: CHM 26100 | D42: CHM 26100 Organic Chemistry I | E42: =IF(_xlfn.IFNA(VLOOKUP(B42,Data!B:G,3,FALSE),"")=0, "", _xlfn.IFNA(VLOOKUP(B42,Data!B:G,3,FALSE),"")) -> 3 | F42: N/A | H42: =IF(_xlfn.IFNA(VLOOKUP(C42,Data!A:G,5,FALSE),"")=0, "Check course registration information", _xlfn.IFNA(VLOOKUP(C42,Data!A:G,5,FALSE),"")) -> CHM 11600 or CHM 11610 or CHM 12600 or CHM 13600 or CHM 12901 or (CHEM C1060 and CHEM C1260 | J42: =IF(_xlfn.IFNA(VLOOKUP(C42,Data!A:G,6,FALSE),"")=0, "Check course registration information", _xlfn.IFNA(VLOOKUP(C42,Data!A:G,6,FALSE),"")) -> A comprehensive study of the chemical principles underlying aliphatic and aromatic compounds. The syntheses and reactions of these materials are discussed. Modern theory and stereochemistry are stressed to illustrate the logic inherent in the subject matter and to demonstrate the predictability of many chemical transformations. Recommended for students majoring in chemical engineering. If not a chemical engineering major, see CHM 26505 Organic Chemistry | K42: =IF(_xlfn.IFNA(VLOOKUP(C42,Data!A:H,7,FALSE),"")=0, "", _xlfn.IFNA(HYPERLINK(VLOOKUP(C42,Data!A:H,7,FALSE),"Catalog Link"),"")) -> Catalog Link | L42: =IF(_xlfn.IFNA(VLOOKUP(C42,Data!A:I,8,FALSE),"")=0, "", _xlfn.IFNA(HYPERLINK(VLOOKUP(C42,Data!A:I,8,FALSE),"Additional Information"),"")) | M42: =COUNTIF(N42:BL42,"x") -> 3 | W42: x | AS42: x | BF42: x
A43: No | B43: CHM 26200 | C43: CHM 26200 | D43: CHM 26200 Organic Chemistry II | E43: =IF(_xlfn.IFNA(VLOOKUP(B43,Data!B:G,3,FALSE),"")=0, "", _xlfn.IFNA(VLOOKUP(B43,Data!B:G,3,FALSE),"")) -> 3 | F43: N/A | H43: =IF(_xlfn.IFNA(VLOOKUP(C43,Data!A:G,5,FALSE),"")=0, "Check course registration information", _xlfn.IFNA(VLOOKUP(C43,Data!A:G,5,FALSE),"")) -> CHM 26100 or CHEM C3410 or CHM 26505 | J43: =IF(_xlfn.IFNA(VLOOKUP(C43,Data!A:G,6,FALSE),"")=0, "Check course registration information", _xlfn.IFNA(VLOOKUP(C43,Data!A:G,6,FALSE),"")) -> A continuation of CHM 26100, but a broader scope. The chemistry of a variety of functional groups is discussed. Theory is employed extensively to demonstrate the coherence underlying seemingly diverse transformations. Qualitative organic analysis is introduced, with particular emphasis on spectroscopic methods | K43: =IF(_xlfn.IFNA(VLOOKUP(C43,Data!A:H,7,FALSE),"")=0, "", _xlfn.IFNA(HYPERLINK(VLOOKUP(C43,Data!A:H,7,FALSE),"Catalog Link"),"")) -> Catalog Link | L43: =IF(_xlfn.IFNA(VLOOKUP(C43,Data!A:I,8,FALSE),"")=0, "", _xlfn.IFNA(HYPERLINK(VLOOKUP(C43,Data!A:I,8,FALSE),"Additional Information"),"")) | M43: =COUNTIF(N43:BL43,"x") -> 3 | W43: x | AS43: x | BF43: x
A44: No | B44: CHM 32100 | C44: CHM 32100 | D44: CHM 32100 Analytical Chemistry I | E44: =IF(_xlfn.IFNA(VLOOKUP(B44,Data!B:G,3,FALSE),"")=0, "", _xlfn.IFNA(VLOOKUP(B44,Data!B:G,3,FALSE),"")) -> 4 | F44: N/A | H44: =IF(_xlfn.IFNA(VLOOKUP(C44,Data!A:G,5,FALSE),"")=0, "Check course registration information", _xlfn.IFNA(VLOOKUP(C44,Data!A:G,5,FALSE),"")) -> CHM 22404 or FS 16300 | J44: =IF(_xlfn.IFNA(VLOOKUP(C44,Data!A:G,6,FALSE),"")=0, "Check course registration information", _xlfn.IFNA(VLOOKUP(C44,Data!A:G,6,FALSE),"")) -> Quantitative measurements on complex chemical systems that show matrix effects or require isolation of a component prior to its determination; general approaches to quantitative problems at the trace level; critical comparisons of competitive procedures with emphasis on principles of separation processes, including chromatography; recognition and evaluation of possible sources of error; approaches for optimizing conditions so as to minimize time and/or effort required to attain prescribed levels of accuracy and precision. Required of students majoring in chemistry | K44: =IF(_xlfn.IFNA(VLOOKUP(C44,Data!A:H,7,FALSE),"")=0, "", _xlfn.IFNA(HYPERLINK(VLOOKUP(C44,Data!A:H,7,FALSE),"Catalog Link"),"")) -> Catalog Link | L44: =IF(_xlfn.IFNA(VLOOKUP(C44,Data!A:I,8,FALSE),"")=0, "", _xlfn.IFNA(HYPERLINK(VLOOKUP(C44,Data!A:I,8,FALSE),"Additional Information"),"")) | M44: =COUNTIF(N44:BL44,"x") -> 2 | S44: x | BC44: x
A45: Yes | B45: CHM 34200 | C45: CHM 34200 | D45: CHM 34200 Inorganic Chemistry | E45: =IF(_xlfn.IFNA(VLOOKUP(B45,Data!B:G,3,FALSE),"")=0, "", _xlfn.IFNA(VLOOKUP(B45,Data!B:G,3,FALSE),"")) -> 3 | F45: Semiconductor Materials, Characterization, and Processing | H45: =IF(_xlfn.IFNA(VLOOKUP(C45,Data!A:G,5,FALSE),"")=0, "Check course registration information", _xlfn.IFNA(VLOOKUP(C45,Data!A:G,5,FALSE),"")) -> CHM 25600 or CHM 26200 or CHM 26605 or MCMP 20500 or PHSC 20500 | J45: =IF(_xlfn.IFNA(VLOOKUP(C45,Data!A:G,6,FALSE),"")=0, "Check course registration information", _xlfn.IFNA(VLOOKUP(C45,Data!A:G,6,FALSE),"")) -> Interpretation and correlation of the reactions and properties of inorganic compounds in terms of their electronic and molecular structures. A survey of the preparations and reactivities of important compounds of the representative elements, with an emphasis on group trends. The elementary chemistry of the transition metals, including magnetic and spectral properties of coordination compounds | K45: =IF(_xlfn.IFNA(VLOOKUP(C45,Data!A:H,7,FALSE),"")=0, "", _xlfn.IFNA(HYPERLINK(VLOOKUP(C45,Data!A:H,7,FALSE),"Catalog Link"),"")) -> Catalog Link | L45: =IF(_xlfn.IFNA(VLOOKUP(C45,Data!A:I,8,FALSE),"")=0, "", _xlfn.IFNA(HYPERLINK(VLOOKUP(C45,Data!A:I,8,FALSE),"Additional Information"),"")) | M45: =COUNTIF(N45:BL45,"x") -> 2 | W45: x | BF45: x
A46: No | B46: CHM 37300 | C46: CHM 37300 | D46: CHM 37300 Physical Chemistry I | E46: =IF(_xlfn.IFNA(VLOOKUP(B46,Data!B:G,3,FALSE),"")=0, "", _xlfn.IFNA(VLOOKUP(B46,Data!B:G,3,FALSE),"")) -> 3 | F46: N/A | H46: =IF(_xlfn.IFNA(VLOOKUP(C46,Data!A:G,5,FALSE),"")=0, "Check course registration information", _xlfn.IFNA(VLOOKUP(C46,Data!A:G,5,FALSE),"")) -> CHM 11600 or CHM 12600 or CHM 12901 or CHM 13600) and (MA 16200 or MA 16600 or MATH 16600) and (PHYS 22100 or PHYS 24100 or PHYS 25100 or PHYS 27200 | J46: =IF(_xlfn.IFNA(VLOOKUP(C46,Data!A:G,6,FALSE),"")=0, "Check course registration information", _xlfn.IFNA(VLOOKUP(C46,Data!A:G,6,FALSE),"")) -> Physical chemistry of matter. Properties of gases, liquids, and solids; equations of state; thermodynamics; energy, heat, and work; entropy; spontaneity and equilibrium; chemical potential; chemical equilibrium; phase diagrams; colligative properties | K46: =IF(_xlfn.IFNA(VLOOKUP(C46,Data!A:H,7,FALSE),"")=0, "", _xlfn.IFNA(HYPERLINK(VLOOKUP(C46,Data!A:H,7,FALSE),"Catalog Link"),"")) -> Catalog Link | L46: =IF(_xlfn.IFNA(VLOOKUP(C46,Data!A:I,8,FALSE),"")=0, "", _xlfn.IFNA(HYPERLINK(VLOOKUP(C46,Data!A:I,8,FALSE),"Additional Information"),"")) | M46: =COUNTIF(N46:BL46,"x") -> 1 | AN46: x
A47: No | B47: CHM 37301 | C47: CHM 37301 | D47: CHM 37301 Physical Chemistry Laboratory I | E47: =IF(_xlfn.IFNA(VLOOKUP(B47,Data!B:G,3,FALSE),"")=0, "", _xlfn.IFNA(VLOOKUP(B47,Data!B:G,3,FALSE),"")) -> 1 | F47: N/A | H47: =IF(_xlfn.IFNA(VLOOKUP(C47,Data!A:G,5,FALSE),"")=0, "Check course registration information", _xlfn.IFNA(VLOOKUP(C47,Data!A:G,5,FALSE),"")) -> CHM 37300 [concurrent ok] | J47: =IF(_xlfn.IFNA(VLOOKUP(C47,Data!A:G,6,FALSE),"")=0, "Check course registration information", _xlfn.IFNA(VLOOKUP(C47,Data!A:G,6,FALSE),"")) -> A physical chemistry laboratory course that will provide students with hands-on experience that illustrates the core concepts presented in the associated physical chemistry lecture course CHM 37300 | K47: =IF(_xlfn.IFNA(VLOOKUP(C47,Data!A:H,7,FALSE),"")=0, "", _xlfn.IFNA(HYPERLINK(VLOOKUP(C47,Data!A:H,7,FALSE),"Catalog Link"),"")) -> Catalog Link | L47: =IF(_xlfn.IFNA(VLOOKUP(C47,Data!A:I,8,FALSE),"")=0, "", _xlfn.IFNA(HYPERLINK(VLOOKUP(C47,Data!A:I,8,FALSE),"Additional Information"),"")) | M47: =COUNTIF(N47:BL47,"x") -> 1 | AS47: x
A48: No | B48: CHM 37400 | C48: CHM 37400 | D48: CHM 37400 Physical Chemistry II | E48: =IF(_xlfn.IFNA(VLOOKUP(B48,Data!B:G,3,FALSE),"")=0, "", _xlfn.IFNA(VLOOKUP(B48,Data!B:G,3,FALSE),"")) -> 3 | F48: N/A | H48: =IF(_xlfn.IFNA(VLOOKUP(C48,Data!A:G,5,FALSE),"")=0, "Check course registration information", _xlfn.IFNA(VLOOKUP(C48,Data!A:G,5,FALSE),"")) -> CHM 37300 | J48: =IF(_xlfn.IFNA(VLOOKUP(C48,Data!A:G,6,FALSE),"")=0, "Check course registration information", _xlfn.IFNA(VLOOKUP(C48,Data!A:G,6,FALSE),"")) -> Physical chemistry of molecules. Wave properties of matter; quantum mechanics of translation, rotation, and vibration; atomic structure; molecular orbitals; quantum states; statistical mechanics; chemical kinetics; collision theory; transition state theory | K48: =IF(_xlfn.IFNA(VLOOKUP(C48,Data!A:H,7,FALSE),"")=0, "", _xlfn.IFNA(HYPERLINK(VLOOKUP(C48,Data!A:H,7,FALSE),"Catalog Link"),"")) -> Catalog Link | L48: =IF(_xlfn.IFNA(VLOOKUP(C48,Data!A:I,8,FALSE),"")=0, "", _xlfn.IFNA(HYPERLINK(VLOOKUP(C48,Data!A:I,8,FALSE),"Additional Information"),"")) | M48: =COUNTIF(N48:BL48,"x") -> 1 | BF48: x
A49: No | B49: CHM 37401 | C49: CHM 37401 | D49: CHM 37401 Physical Chemistry Laboratory II | E49: =IF(_xlfn.IFNA(VLOOKUP(B49,Data!B:G,3,FALSE),"")=0, "", _xlfn.IFNA(VLOOKUP(B49,Data!B:G,3,FALSE),"")) -> 1 | F49: N/A | H49: =IF(_xlfn.IFNA(VLOOKUP(C49,Data!A:G,5,FALSE),"")=0, "Check course registration information", _xlfn.IFNA(VLOOKUP(C49,Data!A:G,5,FALSE),"")) -> CHM 37000 [concurrent ok] or CHM 37400 [concurrent ok] | J49: =IF(_xlfn.IFNA(VLOOKUP(C49,Data!A:G,6,FALSE),"")=0, "Check course registration information", _xlfn.IFNA(VLOOKUP(C49,Data!A:G,6,FALSE),"")) -> A physical chemistry laboratory course that will provide students with hands-on experience that illustrates the core concepts presented in the associated physical chemistry lecture course CHM 37400 | K49: =IF(_xlfn.IFNA(VLOOKUP(C49,Data!A:H,7,FALSE),"")=0, "", _xlfn.IFNA(HYPERLINK(VLOOKUP(C49,Data!A:H,7,FALSE),"Catalog Link"),"")) -> Catalog Link | L49: =IF(_xlfn.IFNA(VLOOKUP(C49,Data!A:I,8,FALSE),"")=0, "", _xlfn.IFNA(HYPERLINK(VLOOKUP(C49,Data!A:I,8,FALSE),"Additional Information"),"")) | M49: =COUNTIF(N49:BL49,"x") -> 1 | AS49: x
A50: No | B50: CHM 42400 | C50: CHM 42400 | D50: CHM 42400 Instrumental Analysis | E50: =IF(_xlfn.IFNA(VLOOKUP(B50,Data!B:G,3,FALSE),"")=0, "", _xlfn.IFNA(VLOOKUP(B50,Data!B:G,3,FALSE),"")) -> 4 | F50: N/A | H50: =IF(_xlfn.IFNA(VLOOKUP(C50,Data!A:G,5,FALSE),"")=0, "Check course registration information", _xlfn.IFNA(VLOOKUP(C50,Data!A:G,5,FALSE),"")) -> CHM 22404 or CHM 32100 or CHM 32300) and (PHYS 22100 or PHYS 24100 or PHYS 27200 | J50: =IF(_xlfn.IFNA(VLOOKUP(C50,Data!A:G,6,FALSE),"")=0, "Check course registration information", _xlfn.IFNA(VLOOKUP(C50,Data!A:G,6,FALSE),"")) -> Principles and application of optical and electrical methods of chemical analysis, including topics in instrumentation | K50: =IF(_xlfn.IFNA(VLOOKUP(C50,Data!A:H,7,FALSE),"")=0, "", _xlfn.IFNA(HYPERLINK(VLOOKUP(C50,Data!A:H,7,FALSE),"Catalog Link"),"")) -> Catalog Link | L50: =IF(_xlfn.IFNA(VLOOKUP(C50,Data!A:I,8,FALSE),"")=0, "", _xlfn.IFNA(HYPERLINK(VLOOKUP(C50,Data!A:I,8,FALSE),"Additional Information"),"")) | M50: =COUNTIF(N50:BL50,"x") -> 3 | S50: x | BC50: x | BK50: x
A51: No | B51: CHM 46200 | C51: CHM 46200 | D51: CHM 46200 Intermediate Organic Chemistry | E51: =IF(_xlfn.IFNA(VLOOKUP(B51,Data!B:G,3,FALSE),"")=0, "", _xlfn.IFNA(VLOOKUP(B51,Data!B:G,3,FALSE),"")) -> 3 | F51: N/A | H51: =IF(_xlfn.IFNA(VLOOKUP(C51,Data!A:G,5,FALSE),"")=0, "Check course registration information", _xlfn.IFNA(VLOOKUP(C51,Data!A:G,5,FALSE),"")) -> CHM 26200 or CHEM C3420 or CHM 26605 or CHM 25600 or MCMP 20500 or PHSC 20500 | J51: =IF(_xlfn.IFNA(VLOOKUP(C51,Data!A:G,6,FALSE),"")=0, "Check course registration information", _xlfn.IFNA(VLOOKUP(C51,Data!A:G,6,FALSE),"")) -> Theory and application of organic chemistry and reaction mechanisms to organic synthesis and contemporary research topics in closely related areas. Topics include stereochemistry, reactive organic intermediates, molecular orbital theory, photochemistry, organic materials chemistry, and chemical biology | K51: =IF(_xlfn.IFNA(VLOOKUP(C51,Data!A:H,7,FALSE),"")=0, "", _xlfn.IFNA(HYPERLINK(VLOOKUP(C51,Data!A:H,7,FALSE),"Catalog Link"),"")) -> Catalog Link | L51: =IF(_xlfn.IFNA(VLOOKUP(C51,Data!A:I,8,FALSE),"")=0, "", _xlfn.IFNA(HYPERLINK(VLOOKUP(C51,Data!A:I,8,FALSE),"Additional Information"),"")) | M51: =COUNTIF(N51:BL51,"x") -> 1 | BF51: x
A52: No | B52: CHM 48100 | C52: CHM 48100 | D52: CHM 48100 Environmental Chemistry | E52: =IF(_xlfn.IFNA(VLOOKUP(B52,Data!B:G,3,FALSE),"")=0, "", _xlfn.IFNA(VLOOKUP(B52,Data!B:G,3,FALSE),"")) -> 3 | F52: N/A | H52: =IF(_xlfn.IFNA(VLOOKUP(C52,Data!A:G,5,FALSE),"")=0, "Check course registration information", _xlfn.IFNA(VLOOKUP(C52,Data!A:G,5,FALSE),"")) -> CHM 11600 or CHM 10901 or CHM 12901 or CHM 12600 or CHM 13600) and (MA 16100 or MA 16500 or MA 16010 | J52: =IF(_xlfn.IFNA(VLOOKUP(C52,Data!A:G,6,FALSE),"")=0, "Check course registration information", _xlfn.IFNA(VLOOKUP(C52,Data!A:G,6,FALSE),"")) -> Survey of chemical aspects of environmental problems and the application of chemistry to their solution. Topics will include atmospheric pollution problems, groundwater pollution and waste disposal problems, inorganic water pollutants, and the occurrence and fate of toxic organic compounds and other substances in the environment | K52: =IF(_xlfn.IFNA(VLOOKUP(C52,Data!A:H,7,FALSE),"")=0, "", _xlfn.IFNA(HYPERLINK(VLOOKUP(C52,Data!A:H,7,FALSE),"Catalog Link"),"")) -> Catalog Link | L52: =IF(_xlfn.IFNA(VLOOKUP(C52,Data!A:I,8,FALSE),"")=0, "", _xlfn.IFNA(HYPERLINK(VLOOKUP(C52,Data!A:I,8,FALSE),"Additional Information"),"")) | M52: =COUNTIF(N52:BL52,"x") -> 2 | W52: x | BF52: x
A53: No | B53: CHM 48700 | C53: CHM 48700 | D53: CHM 48700 Cooperative Work Experience V | E53: =IF(_xlfn.IFNA(VLOOKUP(B53,Data!B:G,3,FALSE),"")=0, "", _xlfn.IFNA(VLOOKUP(B53,Data!B:G,3,FALSE),"")) | F53: N/A | H53: =IF(_xlfn.IFNA(VLOOKUP(C53,Data!A:G,5,FALSE),"")=0, "Check course registration information", _xlfn.IFNA(VLOOKUP(C53,Data!A:G,5,FALSE),"")) -> CHM 38600 | J53: =IF(_xlfn.IFNA(VLOOKUP(C53,Data!A:G,6,FALSE),"")=0, "Check course registration information", _xlfn.IFNA(VLOOKUP(C53,Data!A:G,6,FALSE),"")) -> Cooperative Work Experience | K53: =IF(_xlfn.IFNA(VLOOKUP(C53,Data!A:H,7,FALSE),"")=0, "", _xlfn.IFNA(HYPERLINK(VLOOKUP(C53,Data!A:H,7,FALSE),"Catalog Link"),"")) -> Catalog Link | L53: =IF(_xlfn.IFNA(VLOOKUP(C53,Data!A:I,8,FALSE),"")=0, "", _xlfn.IFNA(HYPERLINK(VLOOKUP(C53,Data!A:I,8,FALSE),"Additional Information"),"")) | M53: =COUNTIF(N53:BL53,"x") -> 1 | AS53: x
A54: Yes | B54: CHM 49000 | C54: CHM 49000 | D54: CHM 49000 Chemistry of the Smartphone | F54: Semiconductor Materials, Characterization, and Processing | J54: =IF(_xlfn.IFNA(VLOOKUP(C54,Data!A:G,6,FALSE),"")=0, "Check course registration information", _xlfn.IFNA(VLOOKUP(C54,Data!A:G,6,FALSE),"")) -> Have you ever wondered about the materials in your smartphone and how chemistry was used to shape them? If you want to dive into the relationship between chemistry and technology, then this is the course for you! Over the semester we will discuss the role of solid-state chemistry in the design of the materials that make your phone function. This course explores the underlying chemistry that makes the touchscreen, light display, battery, and central processing unit function.The total cost of the raw elements in a smart phone is <$2, but the average cost of a new smart phone is ~$300-1000! In a smart phone weighing only ~130 grams, over 80% of its total weight is owed to just six elements: aluminum, carbon, oxygen, iron, silicon, and copper. Yet mining the elements required to make the smart phone in your pocket requires the extraction of >34,000 grams of complex ore, the use of >100 liters of reverse osmosis purified water, and ~20.5 grams of potassium cyanide, (among many other acids, etc.). This course uses the “smart phone” and it’s design as a vehicle to discuss (1) inorganic chemistry in the context of solid state materials (2) how chemistry can be applied to design materials for specific function, (3) how that function emerges not just from combinations of specific elements, but also how specific elements are arranged in crystalline lattices, and (4) how we should consider the impact of materials design and technological development on the environment, a globally interconnected society, and the sustainability of our current consumption of critical elemental resources. | K54: =IF(_xlfn.IFNA(VLOOKUP(C54,Data!A:H,7,FALSE),"")=0, "", _xlfn.IFNA(HYPERLINK(VLOOKUP(C54,Data!A:H,7,FALSE),"Catalog Link"),"")) | L54: =IF(_xlfn.IFNA(VLOOKUP(C54,Data!A:I,8,FALSE),"")=0, "", _xlfn.IFNA(HYPERLINK(VLOOKUP(C54,Data!A:I,8,FALSE),"Additional Information"),"")) | M54: =COUNTIF(N54:BL54,"x") -> 1 | BF54: x
A55: No | B55: CHM 57900 | C55: CHM 57900 | D55: CHM 57900 Computational Chemistry | E55: =IF(_xlfn.IFNA(VLOOKUP(B55,Data!B:G,3,FALSE),"")=0, "", _xlfn.IFNA(VLOOKUP(B55,Data!B:G,3,FALSE),"")) -> 3 | F55: N/A | H55: =IF(_xlfn.IFNA(VLOOKUP(C55,Data!A:G,5,FALSE),"")=0, "Check course registration information", _xlfn.IFNA(VLOOKUP(C55,Data!A:G,5,FALSE),"")) -> CHM 37400 | J55: =IF(_xlfn.IFNA(VLOOKUP(C55,Data!A:G,6,FALSE),"")=0, "Check course registration information", _xlfn.IFNA(VLOOKUP(C55,Data!A:G,6,FALSE),"")) -> Theoretical basis and practical applications of computational methods relevant to chemical and biochemical research problems | K55: =IF(_xlfn.IFNA(VLOOKUP(C55,Data!A:H,7,FALSE),"")=0, "", _xlfn.IFNA(HYPERLINK(VLOOKUP(C55,Data!A:H,7,FALSE),"Catalog Link"),"")) -> Catalog Link | L55: =IF(_xlfn.IFNA(VLOOKUP(C55,Data!A:I,8,FALSE),"")=0, "", _xlfn.IFNA(HYPERLINK(VLOOKUP(C55,Data!A:I,8,FALSE),"Additional Information"),"")) | M55: =COUNTIF(N55:BL55,"x") -> 1 | O55: x
A56: No | B56: CHM 58100 | C56: CHM 58100 | D56: CHM 58100 Atmospheric Chemistry | E56: =IF(_xlfn.IFNA(VLOOKUP(B56,Data!B:G,3,FALSE),"")=0, "", _xlfn.IFNA(VLOOKUP(B56,Data!B:G,3,FALSE),"")) -> 3 | F56: N/A | H56: =IF(_xlfn.IFNA(VLOOKUP(C56,Data!A:G,5,FALSE),"")=0, "Check course registration information", _xlfn.IFNA(VLOOKUP(C56,Data!A:G,5,FALSE),"")) -> CHM 24100 or CHM 25500 or CHM 26100 or CHM 26505 or EAS 23000 or NRES 23000 | J56: =IF(_xlfn.IFNA(VLOOKUP(C56,Data!A:G,6,FALSE),"")=0, "Check course registration information", _xlfn.IFNA(VLOOKUP(C56,Data!A:G,6,FALSE),"")) -> (EAPS 52100) An introduction to the chemistry of the earth's atmosphere. Covers evolution of the earth's atmosphere, its physical and chemical structure, its natural chemical composition and oxidative properties, and human impacts, including increasing tropospheric ozone, decreasing stratospheric ozone, climate change, and acidic deposition | K56: =IF(_xlfn.IFNA(VLOOKUP(C56,Data!A:H,7,FALSE),"")=0, "", _xlfn.IFNA(HYPERLINK(VLOOKUP(C56,Data!A:H,7,FALSE),"Catalog Link"),"")) -> Catalog Link | L56: =IF(_xlfn.IFNA(VLOOKUP(C56,Data!A:I,8,FALSE),"")=0, "", _xlfn.IFNA(HYPERLINK(VLOOKUP(C56,Data!A:I,8,FALSE),"Additional Information"),"")) | M56: =COUNTIF(N56:BL56,"x") -> 2 | W56: x | BF56: x
A57: No | B57: CHM 60500 | C57: CHM 60500 | D57: CHM 60500 Safety In The Chemistry Laboratory | E57: =IF(_xlfn.IFNA(VLOOKUP(B57,Data!B:G,3,FALSE),"")=0, "", _xlfn.IFNA(VLOOKUP(B57,Data!B:G,3,FALSE),"")) | F57: N/A | H57: =IF(_xlfn.IFNA(VLOOKUP(C57,Data!A:G,5,FALSE),"")=0, "Check course registration information", _xlfn.IFNA(VLOOKUP(C57,Data!A:G,5,FALSE),"")) -> Check course registration information | J57: =IF(_xlfn.IFNA(VLOOKUP(C57,Data!A:G,6,FALSE),"")=0, "Check course registration information", _xlfn.IFNA(VLOOKUP(C57,Data!A:G,6,FALSE),"")) -> Lectures on safe practices in the chemistry laboratory. Required of students doing research in chemistry | K57: =IF(_xlfn.IFNA(VLOOKUP(C57,Data!A:H,7,FALSE),"")=0, "", _xlfn.IFNA(HYPERLINK(VLOOKUP(C57,Data!A:H,7,FALSE),"Catalog Link"),"")) -> Catalog Link | L57: =IF(_xlfn.IFNA(VLOOKUP(C57,Data!A:I,8,FALSE),"")=0, "", _xlfn.IFNA(HYPERLINK(VLOOKUP(C57,Data!A:I,8,FALSE),"Additional Information"),"")) | M57: =COUNTIF(N57:BL57,"x") -> 1 | AS57: x
A58: No | B58: CHM 62000 | C58: CHM 62000 | D58: CHM 62000 Spectrochemical Instrumentation | E58: =IF(_xlfn.IFNA(VLOOKUP(B58,Data!B:G,3,FALSE),"")=0, "", _xlfn.IFNA(VLOOKUP(B58,Data!B:G,3,FALSE),"")) -> 3 | F58: N/A | H58: =IF(_xlfn.IFNA(VLOOKUP(C58,Data!A:G,5,FALSE),"")=0, "Check course registration information", _xlfn.IFNA(VLOOKUP(C58,Data!A:G,5,FALSE),"")) -> Check course registration information | J58: =IF(_xlfn.IFNA(VLOOKUP(C58,Data!A:G,6,FALSE),"")=0, "Check course registration information", _xlfn.IFNA(VLOOKUP(C58,Data!A:G,6,FALSE),"")) -> A critical review of instrumental methods of analysis, with particular emphasis on spectroscopic techniques. Topics include: methods of measurement; analog and digital electronics; optics and spectrophotometric modules; and instrumental methods in UV-visible, infrared, and NMR spectroscopies. Prerequisite: introductory analytical and two semesters of physical chemistry | K58: =IF(_xlfn.IFNA(VLOOKUP(C58,Data!A:H,7,FALSE),"")=0, "", _xlfn.IFNA(HYPERLINK(VLOOKUP(C58,Data!A:H,7,FALSE),"Catalog Link"),"")) -> Catalog Link | L58: =IF(_xlfn.IFNA(VLOOKUP(C58,Data!A:I,8,FALSE),"")=0, "", _xlfn.IFNA(HYPERLINK(VLOOKUP(C58,Data!A:I,8,FALSE),"Additional Information"),"")) | M58: =COUNTIF(N58:BL58,"x") -> 3 | S58: x | AN58: x | BC58: x
A59: No | B59: CHM 62100 | C59: CHM 62100 | D59: CHM 62100 Advanced Analytical Chemistry | E59: =IF(_xlfn.IFNA(VLOOKUP(B59,Data!B:G,3,FALSE),"")=0, "", _xlfn.IFNA(VLOOKUP(B59,Data!B:G,3,FALSE),"")) -> 3 | F59: N/A | H59: =IF(_xlfn.IFNA(VLOOKUP(C59,Data!A:G,5,FALSE),"")=0, "Check course registration information", _xlfn.IFNA(VLOOKUP(C59,Data!A:G,5,FALSE),"")) -> Check course registration information | J59: =IF(_xlfn.IFNA(VLOOKUP(C59,Data!A:G,6,FALSE),"")=0, "Check course registration information", _xlfn.IFNA(VLOOKUP(C59,Data!A:G,6,FALSE),"")) -> A critical survey of recent developments in chemical and instrumental methods of analysis. Prerequisite: CHM 32100, 42400 | K59: =IF(_xlfn.IFNA(VLOOKUP(C59,Data!A:H,7,FALSE),"")=0, "", _xlfn.IFNA(HYPERLINK(VLOOKUP(C59,Data!A:H,7,FALSE),"Catalog Link"),"")) -> Catalog Link | L59: =IF(_xlfn.IFNA(VLOOKUP(C59,Data!A:I,8,FALSE),"")=0, "", _xlfn.IFNA(HYPERLINK(VLOOKUP(C59,Data!A:I,8,FALSE),"Additional Information"),"")) | M59: =COUNTIF(N59:BL59,"x") -> 3 | S59: x | BC59: x | BK59: x
A60: No | B60: CHM 64100 | C60: CHM 64100 | D60: CHM 64100 Advanced Inorganic Chemistry-I | E60: =IF(_xlfn.IFNA(VLOOKUP(B60,Data!B:G,3,FALSE),"")=0, "", _xlfn.IFNA(VLOOKUP(B60,Data!B:G,3,FALSE),"")) -> 3 | F60: N/A | H60: =IF(_xlfn.IFNA(VLOOKUP(C60,Data!A:G,5,FALSE),"")=0, "Check course registration information", _xlfn.IFNA(VLOOKUP(C60,Data!A:G,5,FALSE),"")) -> Check course registration information | J60: =IF(_xlfn.IFNA(VLOOKUP(C60,Data!A:G,6,FALSE),"")=0, "Check course registration information", _xlfn.IFNA(VLOOKUP(C60,Data!A:G,6,FALSE),"")) -> Survey of main group and transition metal chemistry. Main group special topics, bonding and structure of boron hydrides. Coordination chemistry, bonding models in coordination compounds. Transition metal organometallic chemistry, ligand types and reactivity patterns. Survey of inorganic NMR spectroscopy. Prerequisite: CHM 34200 | K60: =IF(_xlfn.IFNA(VLOOKUP(C60,Data!A:H,7,FALSE),"")=0, "", _xlfn.IFNA(HYPERLINK(VLOOKUP(C60,Data!A:H,7,FALSE),"Catalog Link"),"")) -> Catalog Link | L60: =IF(_xlfn.IFNA(VLOOKUP(C60,Data!A:I,8,FALSE),"")=0, "", _xlfn.IFNA(HYPERLINK(VLOOKUP(C60,Data!A:I,8,FALSE),"Additional Information"),"")) | M60: =COUNTIF(N60:BL60,"x") -> 1 | BF60: x
A61: No | B61: CHM 64200 | C61: CHM 64200 | D61: CHM 64200 Advanced Inorganic Chemistry-II | E61: =IF(_xlfn.IFNA(VLOOKUP(B61,Data!B:G,3,FALSE),"")=0, "", _xlfn.IFNA(VLOOKUP(B61,Data!B:G,3,FALSE),"")) -> 3 | F61: N/A | H61: =IF(_xlfn.IFNA(VLOOKUP(C61,Data!A:G,5,FALSE),"")=0, "Check course registration information", _xlfn.IFNA(VLOOKUP(C61,Data!A:G,5,FALSE),"")) -> Check course registration information | J61: =IF(_xlfn.IFNA(VLOOKUP(C61,Data!A:G,6,FALSE),"")=0, "Check course registration information", _xlfn.IFNA(VLOOKUP(C61,Data!A:G,6,FALSE),"")) -> Physical inorganic chemistry. Applications of group theory to chemistry and spectroscopy, especially vibrational and electronic spectra of transition metal complexes. Molecular orbital theory and theoretical bases for reactivity. Magnetic properties and electron paramagnetic resonance (EPR) spectroscopy of inorganic materials. Prerequisite: CHM 34200 | K61: =IF(_xlfn.IFNA(VLOOKUP(C61,Data!A:H,7,FALSE),"")=0, "", _xlfn.IFNA(HYPERLINK(VLOOKUP(C61,Data!A:H,7,FALSE),"Catalog Link"),"")) -> Catalog Link | L61: =IF(_xlfn.IFNA(VLOOKUP(C61,Data!A:I,8,FALSE),"")=0, "", _xlfn.IFNA(HYPERLINK(VLOOKUP(C61,Data!A:I,8,FALSE),"Additional Information"),"")) | M61: =COUNTIF(N61:BL61,"x") -> 1 | BF61: x
A62: No | B62: CHM 64400 | C62: CHM 64400 | D62: CHM 64400 Solid State Chemistry | E62: =IF(_xlfn.IFNA(VLOOKUP(B62,Data!B:G,3,FALSE),"")=0, "", _xlfn.IFNA(VLOOKUP(B62,Data!B:G,3,FALSE),"")) -> 3 | F62: Semiconductor Materials, Characterization, and Processing | H62: =IF(_xlfn.IFNA(VLOOKUP(C62,Data!A:G,5,FALSE),"")=0, "Check course registration information", _xlfn.IFNA(VLOOKUP(C62,Data!A:G,5,FALSE),"")) -> Check course registration information | J62: =IF(_xlfn.IFNA(VLOOKUP(C62,Data!A:G,6,FALSE),"")=0, "Check course registration information", _xlfn.IFNA(VLOOKUP(C62,Data!A:G,6,FALSE),"")) -> The chemistry of solids, including a discussion of ionic crystals, metals, alloys, and binary compounds, and their characterizations by various physical methods. Description of chemical reactions, phase changes, and catalysis in terms of current theories of the solid state. Prerequisite: CHM 34200, 37400 | K62: =IF(_xlfn.IFNA(VLOOKUP(C62,Data!A:H,7,FALSE),"")=0, "", _xlfn.IFNA(HYPERLINK(VLOOKUP(C62,Data!A:H,7,FALSE),"Catalog Link"),"")) -> Catalog Link | L62: =IF(_xlfn.IFNA(VLOOKUP(C62,Data!A:I,8,FALSE),"")=0, "", _xlfn.IFNA(HYPERLINK(VLOOKUP(C62,Data!A:I,8,FALSE),"Additional Information"),"")) | M62: =COUNTIF(N62:BL62,"x") -> 1 | BF62: x
A63: No | B63: CHM 64600 | C63: CHM 64600 | D63: CHM 64600 Kinetics. Mech. Inorganic Reactions | E63: =IF(_xlfn.IFNA(VLOOKUP(B63,Data!B:G,3,FALSE),"")=0, "", _xlfn.IFNA(VLOOKUP(B63,Data!B:G,3,FALSE),"")) -> 3 | F63: N/A | H63: =IF(_xlfn.IFNA(VLOOKUP(C63,Data!A:G,5,FALSE),"")=0, "Check course registration information", _xlfn.IFNA(VLOOKUP(C63,Data!A:G,5,FALSE),"")) -> Check course registration information | J63: =IF(_xlfn.IFNA(VLOOKUP(C63,Data!A:G,6,FALSE),"")=0, "Check course registration information", _xlfn.IFNA(VLOOKUP(C63,Data!A:G,6,FALSE),"")) -> Chemical kinetics, reaction orders, mechanisms and rate expressions; experimental techniques; transition state theory; reactions in solution; complex mechanisms; linear free-energy relationships; acid-base catalysis and proton-transfer reactions; redox reactions (electron and atom transfer, oxidative addition-reductive elimination); substitution reactions of metal ion and organometallic complexes; homogeneous catalysis; and heterogeneous reactions. Prerequisite: CHM 34200 | K63: =IF(_xlfn.IFNA(VLOOKUP(C63,Data!A:H,7,FALSE),"")=0, "", _xlfn.IFNA(HYPERLINK(VLOOKUP(C63,Data!A:H,7,FALSE),"Catalog Link"),"")) -> Catalog Link | L63: =IF(_xlfn.IFNA(VLOOKUP(C63,Data!A:I,8,FALSE),"")=0, "", _xlfn.IFNA(HYPERLINK(VLOOKUP(C63,Data!A:I,8,FALSE),"Additional Information"),"")) | M63: =COUNTIF(N63:BL63,"x") -> 1 | BF63: x
A64: No | B64: CHM 64700 | C64: CHM 64700 | D64: CHM 64700 Transition Metal-Organomet. Chem. | E64: =IF(_xlfn.IFNA(VLOOKUP(B64,Data!B:G,3,FALSE),"")=0, "", _xlfn.IFNA(VLOOKUP(B64,Data!B:G,3,FALSE),"")) -> 3 | F64: N/A | H64: =IF(_xlfn.IFNA(VLOOKUP(C64,Data!A:G,5,FALSE),"")=0, "Check course registration information", _xlfn.IFNA(VLOOKUP(C64,Data!A:G,5,FALSE),"")) -> Check course registration information | J64: =IF(_xlfn.IFNA(VLOOKUP(C64,Data!A:G,6,FALSE),"")=0, "Check course registration information", _xlfn.IFNA(VLOOKUP(C64,Data!A:G,6,FALSE),"")) -> A study of the chemistry and physical properties of compounds of the transition metals. Halides, oxides, and oxy-salts; transition metal carbonyls and derivatives; pi-bonded organometallic compounds; catalysis; spectral and magnetic properties of compounds. Prerequisite: CHM 64100 | K64: =IF(_xlfn.IFNA(VLOOKUP(C64,Data!A:H,7,FALSE),"")=0, "", _xlfn.IFNA(HYPERLINK(VLOOKUP(C64,Data!A:H,7,FALSE),"Catalog Link"),"")) -> Catalog Link | L64: =IF(_xlfn.IFNA(VLOOKUP(C64,Data!A:I,8,FALSE),"")=0, "", _xlfn.IFNA(HYPERLINK(VLOOKUP(C64,Data!A:I,8,FALSE),"Additional Information"),"")) | M64: =COUNTIF(N64:BL64,"x") -> 1 | BF64: x
A65: No | B65: CHM 65100 | C65: CHM 65100 | D65: CHM 65100 Advanced Organic Chemistry | E65: =IF(_xlfn.IFNA(VLOOKUP(B65,Data!B:G,3,FALSE),"")=0, "", _xlfn.IFNA(VLOOKUP(B65,Data!B:G,3,FALSE),"")) -> 3 | F65: N/A | H65: =IF(_xlfn.IFNA(VLOOKUP(C65,Data!A:G,5,FALSE),"")=0, "Check course registration information", _xlfn.IFNA(VLOOKUP(C65,Data!A:G,5,FALSE),"")) -> Check course registration information | J65: =IF(_xlfn.IFNA(VLOOKUP(C65,Data!A:G,6,FALSE),"")=0, "Check course registration information", _xlfn.IFNA(VLOOKUP(C65,Data!A:G,6,FALSE),"")) -> Modern structural organic chemistry, including introductions to molecular orbital theory and reaction mechanisms. Prerequisite: a year's course in organic chemistry | K65: =IF(_xlfn.IFNA(VLOOKUP(C65,Data!A:H,7,FALSE),"")=0, "", _xlfn.IFNA(HYPERLINK(VLOOKUP(C65,Data!A:H,7,FALSE),"Catalog Link"),"")) -> Catalog Link | L65: =IF(_xlfn.IFNA(VLOOKUP(C65,Data!A:I,8,FALSE),"")=0, "", _xlfn.IFNA(HYPERLINK(VLOOKUP(C65,Data!A:I,8,FALSE),"Additional Information"),"")) | M65: =COUNTIF(N65:BL65,"x") -> 1 | BF65: x
A66: No | B66: CHM 66800 | C66: CHM 66800 | D66: CHM 66800 Physical Organic Chemistry | E66: =IF(_xlfn.IFNA(VLOOKUP(B66,Data!B:G,3,FALSE),"")=0, "", _xlfn.IFNA(VLOOKUP(B66,Data!B:G,3,FALSE),"")) -> 3 | F66: N/A | H66: =IF(_xlfn.IFNA(VLOOKUP(C66,Data!A:G,5,FALSE),"")=0, "Check course registration information", _xlfn.IFNA(VLOOKUP(C66,Data!A:G,5,FALSE),"")) -> Check course registration information | J66: =IF(_xlfn.IFNA(VLOOKUP(C66,Data!A:G,6,FALSE),"")=0, "Check course registration information", _xlfn.IFNA(VLOOKUP(C66,Data!A:G,6,FALSE),"")) -> The theoretical and mechanistic bases for structure and reactivity in organic chemistry is discussed. Individual topics include kinetics and thermodynamics, molecular orbital theory, stereochemistry and reactive intermediates as applied to the mechanisms of organic reactions. Prerequisite: CHM 56300 or 65100 | K66: =IF(_xlfn.IFNA(VLOOKUP(C66,Data!A:H,7,FALSE),"")=0, "", _xlfn.IFNA(HYPERLINK(VLOOKUP(C66,Data!A:H,7,FALSE),"Catalog Link"),"")) -> Catalog Link | L66: =IF(_xlfn.IFNA(VLOOKUP(C66,Data!A:I,8,FALSE),"")=0, "", _xlfn.IFNA(HYPERLINK(VLOOKUP(C66,Data!A:I,8,FALSE),"Additional Information"),"")) | M66: =COUNTIF(N66:BL66,"x") -> 0
A67: No | B67: CHM 67100 | C67: CHM 67100 | D67: CHM 67100 Advanced Physical Chemistry | E67: =IF(_xlfn.IFNA(VLOOKUP(B67,Data!B:G,3,FALSE),"")=0, "", _xlfn.IFNA(VLOOKUP(B67,Data!B:G,3,FALSE),"")) -> 3 | F67: N/A | H67: =IF(_xlfn.IFNA(VLOOKUP(C67,Data!A:G,5,FALSE),"")=0, "Check course registration information", _xlfn.IFNA(VLOOKUP(C67,Data!A:G,5,FALSE),"")) -> Check course registration information | J67: =IF(_xlfn.IFNA(VLOOKUP(C67,Data!A:G,6,FALSE),"")=0, "Check course registration information", _xlfn.IFNA(VLOOKUP(C67,Data!A:G,6,FALSE),"")) -> Selected topics, including atomic and molecular structure and modern theories underlying thermodynamics and chemical kinetics. Prerequisite: CHM 57800 | K67: =IF(_xlfn.IFNA(VLOOKUP(C67,Data!A:H,7,FALSE),"")=0, "", _xlfn.IFNA(HYPERLINK(VLOOKUP(C67,Data!A:H,7,FALSE),"Catalog Link"),"")) -> Catalog Link | L67: =IF(_xlfn.IFNA(VLOOKUP(C67,Data!A:I,8,FALSE),"")=0, "", _xlfn.IFNA(HYPERLINK(VLOOKUP(C67,Data!A:I,8,FALSE),"Additional Information"),"")) | M67: =COUNTIF(N67:BL67,"x") -> 0
A68: No | B68: CHM 67300 | C68: CHM 67300 | D68: CHM 67300 Computational Quantum Chemistry | E68: =IF(_xlfn.IFNA(VLOOKUP(B68,Data!B:G,3,FALSE),"")=0, "", _xlfn.IFNA(VLOOKUP(B68,Data!B:G,3,FALSE),"")) -> 3 | F68: N/A | H68: =IF(_xlfn.IFNA(VLOOKUP(C68,Data!A:G,5,FALSE),"")=0, "Check course registration information", _xlfn.IFNA(VLOOKUP(C68,Data!A:G,5,FALSE),"")) -> Check course registration information | J68: =IF(_xlfn.IFNA(VLOOKUP(C68,Data!A:G,6,FALSE),"")=0, "Check course registration information", _xlfn.IFNA(VLOOKUP(C68,Data!A:G,6,FALSE),"")) -> Semiempirical and molecular-mechanics treatments of large molecules, ab initio methods, modern density functional theory, Green's functions, multichannel quantum defect theory, global optimization methods. Prerequisite: CHM 67100 | K68: =IF(_xlfn.IFNA(VLOOKUP(C68,Data!A:H,7,FALSE),"")=0, "", _xlfn.IFNA(HYPERLINK(VLOOKUP(C68,Data!A:H,7,FALSE),"Catalog Link"),"")) -> Catalog Link | L68: =IF(_xlfn.IFNA(VLOOKUP(C68,Data!A:I,8,FALSE),"")=0, "", _xlfn.IFNA(HYPERLINK(VLOOKUP(C68,Data!A:I,8,FALSE),"Additional Information"),"")) | M68: =COUNTIF(N68:BL68,"x") -> 1 | O68: x
A69: No | B69: CHM 67500 | C69: CHM 67500 | D69: CHM 67500 Chemical Kinetics | E69: =IF(_xlfn.IFNA(VLOOKUP(B69,Data!B:G,3,FALSE),"")=0, "", _xlfn.IFNA(VLOOKUP(B69,Data!B:G,3,FALSE),"")) -> 3 | F69: N/A | H69: =IF(_xlfn.IFNA(VLOOKUP(C69,Data!A:G,5,FALSE),"")=0, "Check course registration information", _xlfn.IFNA(VLOOKUP(C69,Data!A:G,5,FALSE),"")) -> Check course registration information | J69: =IF(_xlfn.IFNA(VLOOKUP(C69,Data!A:G,6,FALSE),"")=0, "Check course registration information", _xlfn.IFNA(VLOOKUP(C69,Data!A:G,6,FALSE),"")) -> Or 3.00. Experimental and theoretical consideration of chemical reaction rates and mechanisms | K69: =IF(_xlfn.IFNA(VLOOKUP(C69,Data!A:H,7,FALSE),"")=0, "", _xlfn.IFNA(HYPERLINK(VLOOKUP(C69,Data!A:H,7,FALSE),"Catalog Link"),"")) -> Catalog Link | L69: =IF(_xlfn.IFNA(VLOOKUP(C69,Data!A:I,8,FALSE),"")=0, "", _xlfn.IFNA(HYPERLINK(VLOOKUP(C69,Data!A:I,8,FALSE),"Additional Information"),"")) | M69: =COUNTIF(N69:BL69,"x") -> 0
A70: No | B70: CHM 67605 | C70: CHM 67605 | D70: CHM 67605 Molecular Spectroscopy | E70: =IF(_xlfn.IFNA(VLOOKUP(B70,Data!B:G,3,FALSE),"")=0, "", _xlfn.IFNA(VLOOKUP(B70,Data!B:G,3,FALSE),"")) -> 3 | F70: N/A | H70: =IF(_xlfn.IFNA(VLOOKUP(C70,Data!A:G,5,FALSE),"")=0, "Check course registration information", _xlfn.IFNA(VLOOKUP(C70,Data!A:G,5,FALSE),"")) -> CHM 67100 | J70: =IF(_xlfn.IFNA(VLOOKUP(C70,Data!A:G,6,FALSE),"")=0, "Check course registration information", _xlfn.IFNA(VLOOKUP(C70,Data!A:G,6,FALSE),"")) -> Theoretical and experimental fundamentals of the interactions between molecules and electromagnetic waves. Topics include electronic, vibrational, and rotational spectroscopies, and laser-based methods. Prerequisites: CHM 67100 | K70: =IF(_xlfn.IFNA(VLOOKUP(C70,Data!A:H,7,FALSE),"")=0, "", _xlfn.IFNA(HYPERLINK(VLOOKUP(C70,Data!A:H,7,FALSE),"Catalog Link"),"")) -> Catalog Link | L70: =IF(_xlfn.IFNA(VLOOKUP(C70,Data!A:I,8,FALSE),"")=0, "", _xlfn.IFNA(HYPERLINK(VLOOKUP(C70,Data!A:I,8,FALSE),"Additional Information"),"")) | M70: =COUNTIF(N70:BL70,"x") -> 3 | S70: x | AN70: x | BC70: x
A71: No | B71: CHM 67900 | C71: CHM 67900 | D71: CHM 67900 Chemical Thermodynamics | E71: =IF(_xlfn.IFNA(VLOOKUP(B71,Data!B:G,3,FALSE),"")=0, "", _xlfn.IFNA(VLOOKUP(B71,Data!B:G,3,FALSE),"")) -> 3 | F71: N/A | H71: =IF(_xlfn.IFNA(VLOOKUP(C71,Data!A:G,5,FALSE),"")=0, "Check course registration information", _xlfn.IFNA(VLOOKUP(C71,Data!A:G,5,FALSE),"")) -> Check course registration information | J71: =IF(_xlfn.IFNA(VLOOKUP(C71,Data!A:G,6,FALSE),"")=0, "Check course registration information", _xlfn.IFNA(VLOOKUP(C71,Data!A:G,6,FALSE),"")) -> Advanced thermodynamics of chemical and phase equilibria, of electrolytic and non-electrolytic solutions, and of imperfect gases. Prerequisite: CHM 57800 | K71: =IF(_xlfn.IFNA(VLOOKUP(C71,Data!A:H,7,FALSE),"")=0, "", _xlfn.IFNA(HYPERLINK(VLOOKUP(C71,Data!A:H,7,FALSE),"Catalog Link"),"")) -> Catalog Link | L71: =IF(_xlfn.IFNA(VLOOKUP(C71,Data!A:I,8,FALSE),"")=0, "", _xlfn.IFNA(HYPERLINK(VLOOKUP(C71,Data!A:I,8,FALSE),"Additional Information"),"")) | M71: =COUNTIF(N71:BL71,"x") -> 1 | AS71: x
A72: No | B72: CHM 68200 | C72: CHM 68200 | D72: CHM 68200 Statistical Thermodynamics | E72: =IF(_xlfn.IFNA(VLOOKUP(B72,Data!B:G,3,FALSE),"")=0, "", _xlfn.IFNA(VLOOKUP(B72,Data!B:G,3,FALSE),"")) -> 3 | F72: N/A | H72: =IF(_xlfn.IFNA(VLOOKUP(C72,Data!A:G,5,FALSE),"")=0, "Check course registration information", _xlfn.IFNA(VLOOKUP(C72,Data!A:G,5,FALSE),"")) -> Check course registration information | J72: =IF(_xlfn.IFNA(VLOOKUP(C72,Data!A:G,6,FALSE),"")=0, "Check course registration information", _xlfn.IFNA(VLOOKUP(C72,Data!A:G,6,FALSE),"")) -> Application of statistical mechanics to the description of imperfect gases, liquids, and solutions; to order-disorder phenomena in solids and surfaces; and to absolute reaction rate theory. Prerequisite: CHM 67100, 67900 | K72: =IF(_xlfn.IFNA(VLOOKUP(C72,Data!A:H,7,FALSE),"")=0, "", _xlfn.IFNA(HYPERLINK(VLOOKUP(C72,Data!A:H,7,FALSE),"Catalog Link"),"")) -> Catalog Link | L72: =IF(_xlfn.IFNA(VLOOKUP(C72,Data!A:I,8,FALSE),"")=0, "", _xlfn.IFNA(HYPERLINK(VLOOKUP(C72,Data!A:I,8,FALSE),"Additional Information"),"")) | M72: =COUNTIF(N72:BL72,"x") -> 0
A73: No | B73: CHM 69600 | C73: CHM 69600 | D73: CHM 69600 Sustainability and Green Chemistry | E73: =IF(_xlfn.IFNA(VLOOKUP(B73,Data!B:G,3,FALSE),"")=0, "", _xlfn.IFNA(VLOOKUP(B73,Data!B:G,3,FALSE),"")) | F73: N/A | H73: =IF(_xlfn.IFNA(VLOOKUP(C73,Data!A:G,5,FALSE),"")=0, "Check course registration information", _xlfn.IFNA(VLOOKUP(C73,Data!A:G,5,FALSE),"")) -> Check course registration information | J73: =IF(_xlfn.IFNA(VLOOKUP(C73,Data!A:G,6,FALSE),"")=0, "Check course registration information", _xlfn.IFNA(VLOOKUP(C73,Data!A:G,6,FALSE),"")) -> Check course registration information | K73: =IF(_xlfn.IFNA(VLOOKUP(C73,Data!A:H,7,FALSE),"")=0, "", _xlfn.IFNA(HYPERLINK(VLOOKUP(C73,Data!A:H,7,FALSE),"Catalog Link"),"")) -> Catalog Link | L73: =IF(_xlfn.IFNA(VLOOKUP(C73,Data!A:I,8,FALSE),"")=0, "", _xlfn.IFNA(HYPERLINK(VLOOKUP(C73,Data!A:I,8,FALSE),"Additional Information"),"")) | M73: =COUNTIF(N73:BL73,"x") -> 3 | W73: x | AS73: x | BF73: x
A74: No | B74: CHM 69600 | C74: CHM 69600-1 | D74: CHM 69600 Foundations of Soft Materials | E74: =IF(_xlfn.IFNA(VLOOKUP(B74,Data!B:G,3,FALSE),"")=0, "", _xlfn.IFNA(VLOOKUP(B74,Data!B:G,3,FALSE),"")) | F74: N/A | H74: =IF(_xlfn.IFNA(VLOOKUP(C74,Data!A:G,5,FALSE),"")=0, "Check course registration information", _xlfn.IFNA(VLOOKUP(C74,Data!A:G,5,FALSE),"")) -> Check course registration information | J74: =IF(_xlfn.IFNA(VLOOKUP(C74,Data!A:G,6,FALSE),"")=0, "Check course registration information", _xlfn.IFNA(VLOOKUP(C74,Data!A:G,6,FALSE),"")) -> Check course registration information | K74: =IF(_xlfn.IFNA(VLOOKUP(C74,Data!A:H,7,FALSE),"")=0, "", _xlfn.IFNA(HYPERLINK(VLOOKUP(C74,Data!A:H,7,FALSE),"Catalog Link"),"")) -> Catalog Link | L74: =IF(_xlfn.IFNA(VLOOKUP(C74,Data!A:I,8,FALSE),"")=0, "", _xlfn.IFNA(HYPERLINK(VLOOKUP(C74,Data!A:I,8,FALSE),"Additional Information"),"")) | M74: =COUNTIF(N74:BL74,"x") -> 3 | W74: x | AS74: x | BF74: x
A75: No | B75: ECE 20001 | C75: ECE 20001 | D75: ECE 20001 Electrical Engineering Fundamentals I | E75: =IF(_xlfn.IFNA(VLOOKUP(B75,Data!B:G,3,FALSE),"")=0, "", _xlfn.IFNA(VLOOKUP(B75,Data!B:G,3,FALSE),"")) -> 3 | F75: N/A | H75: =IF(_xlfn.IFNA(VLOOKUP(C75,Data!A:G,5,FALSE),"")=0, "Check course registration information", _xlfn.IFNA(VLOOKUP(C75,Data!A:G,5,FALSE),"")) -> ENGR 13000 or ENGR 13100 or ENGR 14100 or ENGR 16100 or ENGR 13300 or ENGR 19600) and ((ENGR 16100 and ENGR 16200) or PHYS 17200 or PHYS 15200) and (MA 16600 or MA 16200 or MATH 16600) and (MA 26100 [concurrent ok] or MA 17400 [concurrent ok] or MA 18200 [concurrent ok] or MA 27101 [concurrent ok] | J75: =IF(_xlfn.IFNA(VLOOKUP(C75,Data!A:G,6,FALSE),"")=0, "Check course registration information", _xlfn.IFNA(VLOOKUP(C75,Data!A:G,6,FALSE),"")) -> This course covers fundamental concepts and applications for electrical and computer engineers as well as for engineers who need to gain a broad understanding of these disciplines. The course starts by the basic concepts of charge, current, and voltage as well as their expressions with regards to resistors and resistive circuits. Essential concepts, devices, theorems, and applications of direct-current (DC), 1st order, and alternating-current (AC) circuits are subsequently discussed. Besides electrical devices and circuits, basic electronic components including diodes and transistors as well as their primary applications are also discussed | K75: =IF(_xlfn.IFNA(VLOOKUP(C75,Data!A:H,7,FALSE),"")=0, "", _xlfn.IFNA(HYPERLINK(VLOOKUP(C75,Data!A:H,7,FALSE),"Catalog Link"),"")) -> Catalog Link | L75: =IF(_xlfn.IFNA(VLOOKUP(C75,Data!A:I,8,FALSE),"")=0, "", _xlfn.IFNA(HYPERLINK(VLOOKUP(C75,Data!A:I,8,FALSE),"Additional Information"),"")) -> Additional Information | M75: =COUNTIF(N75:BL75,"x") -> 2 | Y75: x | BB75: x
A76: No | B76: ECE 20002 | C76: ECE 20002 | D76: ECE 20002 Electrical Engineering Fundamentals II | E76: =IF(_xlfn.IFNA(VLOOKUP(B76,Data!B:G,3,FALSE),"")=0, "", _xlfn.IFNA(VLOOKUP(B76,Data!B:G,3,FALSE),"")) -> 3 | F76: N/A | H76: =IF(_xlfn.IFNA(VLOOKUP(C76,Data!A:G,5,FALSE),"")=0, "Check course registration information", _xlfn.IFNA(VLOOKUP(C76,Data!A:G,5,FALSE),"")) -> ECE 20001 and (MA 26200 [concurrent ok] or MA 26600 [concurrent ok] or MA 36600 [concurrent ok] | J76: =IF(_xlfn.IFNA(VLOOKUP(C76,Data!A:G,6,FALSE),"")=0, "Check course registration information", _xlfn.IFNA(VLOOKUP(C76,Data!A:G,6,FALSE),"")) -> Continuation of Electrical and Computer Engineering Fundamentals I. The course covers the mathematical and computational foundations of (1) linear circuit analysis and (2) simple nonlinear circuits with a small number of transistors. Topics include: AC and DC analysis of simple MOSFET circuits, especially single-transistor amplifiers; op-amp circuits; mathematical methods for time-domain analysis of linear, time-invariant (LTI) systems (homogeneous and particular solutions, convolution, the Laplace transform, and the transfer function); and frequency-domain analysis and design of LTI systems (especially Bode plots and filter design). Permission of Department required | K76: =IF(_xlfn.IFNA(VLOOKUP(C76,Data!A:H,7,FALSE),"")=0, "", _xlfn.IFNA(HYPERLINK(VLOOKUP(C76,Data!A:H,7,FALSE),"Catalog Link"),"")) -> Catalog Link | L76: =IF(_xlfn.IFNA(VLOOKUP(C76,Data!A:I,8,FALSE),"")=0, "", _xlfn.IFNA(HYPERLINK(VLOOKUP(C76,Data!A:I,8,FALSE),"Additional Information"),"")) -> Additional Information | M76: =COUNTIF(N76:BL76,"x") -> 2 | Y76: x | BB76: x
A77: Yes | B77: ECE 30500 | C77: ECE 30500 | D77: ECE 30500 Semiconductor Devices | E77: =IF(_xlfn.IFNA(VLOOKUP(B77,Data!B:G,3,FALSE),"")=0, "", _xlfn.IFNA(VLOOKUP(B77,Data!B:G,3,FALSE),"")) -> 3 | F77: Semiconductor and Microelectronic Devices | H77: =IF(_xlfn.IFNA(VLOOKUP(C77,Data!A:G,5,FALSE),"")=0, "Check course registration information", _xlfn.IFNA(VLOOKUP(C77,Data!A:G,5,FALSE),"")) -> ECE 20002 or ECE 25500) and (PHYS 27200 or PHYS 24100 or PHYS 26100 or PHYS 25100) and (MA 26600 or MA 26200 or MA 36600 | J77: =IF(_xlfn.IFNA(VLOOKUP(C77,Data!A:G,6,FALSE),"")=0, "Check course registration information", _xlfn.IFNA(VLOOKUP(C77,Data!A:G,6,FALSE),"")) -> Introduces and explains terminology, models, properties, and concepts associated with semiconductor devices. Provides detailed insight into the internal workings of the "building-block" device structures such as the pn-junction diode, Schottky diode, BJT, and MOSFET. Presents information about a wide variety of other devices including solar cells, LEDs, HBTs, and modern field-effect devices. Systematically develops the analytical tools needed to solve practical device problems | K77: =IF(_xlfn.IFNA(VLOOKUP(C77,Data!A:H,7,FALSE),"")=0, "", _xlfn.IFNA(HYPERLINK(VLOOKUP(C77,Data!A:H,7,FALSE),"Catalog Link"),"")) -> Catalog Link | L77: =IF(_xlfn.IFNA(VLOOKUP(C77,Data!A:I,8,FALSE),"")=0, "", _xlfn.IFNA(HYPERLINK(VLOOKUP(C77,Data!A:I,8,FALSE),"Additional Information"),"")) -> Additional Information | M77: =COUNTIF(N77:BL77,"x") -> 2 | Y77: x | BB77: x
A78: No | B78: ECE 30600 | C78: ECE 30600 | D78: ECE 30600 Electronic Circuits and Systems Laboratory | E78: =IF(_xlfn.IFNA(VLOOKUP(B78,Data!B:G,3,FALSE),"")=0, "", _xlfn.IFNA(VLOOKUP(B78,Data!B:G,3,FALSE),"")) -> 1 | F78: N/A | H78: =IF(_xlfn.IFNA(VLOOKUP(C78,Data!A:G,5,FALSE),"")=0, "Check course registration information", _xlfn.IFNA(VLOOKUP(C78,Data!A:G,5,FALSE),"")) -> ECE 20008 or ECE 20800) and ECE 30100 [concurrent ok] and ECE 30200 [concurrent ok] | J78: =IF(_xlfn.IFNA(VLOOKUP(C78,Data!A:G,6,FALSE),"")=0, "Check course registration information", _xlfn.IFNA(VLOOKUP(C78,Data!A:G,6,FALSE),"")) -> Experiments in electronic circuits and systems, including spectral analysis techniques, sampling, distortion measurements, random signals, signal-to-noise ratio and correlation | K78: =IF(_xlfn.IFNA(VLOOKUP(C78,Data!A:H,7,FALSE),"")=0, "", _xlfn.IFNA(HYPERLINK(VLOOKUP(C78,Data!A:H,7,FALSE),"Catalog Link"),"")) -> Catalog Link | L78: =IF(_xlfn.IFNA(VLOOKUP(C78,Data!A:I,8,FALSE),"")=0, "", _xlfn.IFNA(HYPERLINK(VLOOKUP(C78,Data!A:I,8,FALSE),"Additional Information"),"")) -> Additional Information | M78: =COUNTIF(N78:BL78,"x") -> 2 | Y78: x | BB78: x
A79: No | B79: ECE 30653 | C79: ECE 30653 | D79: ECE 30653 Introduction to Nanotechnology and Quantum Science and Technology | E79: =IF(_xlfn.IFNA(VLOOKUP(B79,Data!B:G,3,FALSE),"")=0, "", _xlfn.IFNA(VLOOKUP(B79,Data!B:G,3,FALSE),"")) -> 3 | F79: N/A | H79: =IF(_xlfn.IFNA(VLOOKUP(C79,Data!A:G,5,FALSE),"")=0, "Check course registration information", _xlfn.IFNA(VLOOKUP(C79,Data!A:G,5,FALSE),"")) -> MA 26100 and (MA 26600 or MA 26200) and (PHYS 27200 or PHYS 24100) and (CHM 11500 or (CHM 11100 and CHM 11200 | J79: =IF(_xlfn.IFNA(VLOOKUP(C79,Data!A:G,6,FALSE),"")=0, "Check course registration information", _xlfn.IFNA(VLOOKUP(C79,Data!A:G,6,FALSE),"")) -> This interdisciplinary course offers an introduction to nanotechnology and quantum science and technology for undergraduate students in science and engineering. The students will develop understanding of interdisciplinary nature of these fields and utilize concepts in physics, chemistry and mechanics to describe and analyze unique properties of quantum and nanoscale objects. The course will provide the opportunity to get exposed to highly interdisciplinary nature of today's most active and rapidly expanding fields of research and technologies | K79: =IF(_xlfn.IFNA(VLOOKUP(C79,Data!A:H,7,FALSE),"")=0, "", _xlfn.IFNA(HYPERLINK(VLOOKUP(C79,Data!A:H,7,FALSE),"Catalog Link"),"")) -> Catalog Link | L79: =IF(_xlfn.IFNA(VLOOKUP(C79,Data!A:I,8,FALSE),"")=0, "", _xlfn.IFNA(HYPERLINK(VLOOKUP(C79,Data!A:I,8,FALSE),"Additional Information"),"")) -> Additional Information | M79: =COUNTIF(N79:BL79,"x") -> 1 | AW79: x
A80: No | B80: ECE 31033 | C80: ECE 31033 | D80: ECE 31033 Power Electronics | E80: =IF(_xlfn.IFNA(VLOOKUP(B80,Data!B:G,3,FALSE),"")=0, "", _xlfn.IFNA(VLOOKUP(B80,Data!B:G,3,FALSE),"")) -> 3 | F80: N/A | H80: =IF(_xlfn.IFNA(VLOOKUP(C80,Data!A:G,5,FALSE),"")=0, "Check course registration information", _xlfn.IFNA(VLOOKUP(C80,Data!A:G,5,FALSE),"")) -> ECE 20002 or ECE 25500 | J80: =IF(_xlfn.IFNA(VLOOKUP(C80,Data!A:G,6,FALSE),"")=0, "Check course registration information", _xlfn.IFNA(VLOOKUP(C80,Data!A:G,6,FALSE),"")) -> Introduction to the fundamental operating principles of power conditioning circuits that are currently being used to effect power flow from AC to DC and vice versa. Emphasis is on the relationship between form and function of these circuits. Circuits discussed will include AC/DC line-commutated converters, DC/DC converters, DC/variable frequency converters, resonant converters, and AC/AC converters. Computer simulations will be used as a part of the coursework | K80: =IF(_xlfn.IFNA(VLOOKUP(C80,Data!A:H,7,FALSE),"")=0, "", _xlfn.IFNA(HYPERLINK(VLOOKUP(C80,Data!A:H,7,FALSE),"Catalog Link"),"")) -> Catalog Link | L80: =IF(_xlfn.IFNA(VLOOKUP(C80,Data!A:I,8,FALSE),"")=0, "", _xlfn.IFNA(HYPERLINK(VLOOKUP(C80,Data!A:I,8,FALSE),"Additional Information"),"")) -> Additional Information | M80: =COUNTIF(N80:BL80,"x") -> 2 | AQ80: x | BB80: x
A81: Yes | B81: ECE 33700 | C81: ECE 33700 | D81: ECE 33700 ASIC Design Laboratory | E81: =IF(_xlfn.IFNA(VLOOKUP(B81,Data!B:G,3,FALSE),"")=0, "", _xlfn.IFNA(VLOOKUP(B81,Data!B:G,3,FALSE),"")) -> 2 | F81: Integrated Circuit & System Design, Electronic Design Automation | H81: =IF(_xlfn.IFNA(VLOOKUP(C81,Data!A:G,5,FALSE),"")=0, "Check course registration information", _xlfn.IFNA(VLOOKUP(C81,Data!A:G,5,FALSE),"")) -> ECE 27000 | J81: =IF(_xlfn.IFNA(VLOOKUP(C81,Data!A:G,6,FALSE),"")=0, "Check course registration information", _xlfn.IFNA(VLOOKUP(C81,Data!A:G,6,FALSE),"")) -> Introduction to standard cell design of Application Specific Integrated Circuits (ASICs) using modern hardware description languages (HDLs). Emphasis on how to write HDL code that will map readily to hardware. Laboratory experiments using commercial grade computer-aided design (CAD) tools for HDL based design, logic simulation, automatic placement and routing, timing analysis and verification | K81: =IF(_xlfn.IFNA(VLOOKUP(C81,Data!A:H,7,FALSE),"")=0, "", _xlfn.IFNA(HYPERLINK(VLOOKUP(C81,Data!A:H,7,FALSE),"Catalog Link"),"")) -> Catalog Link | L81: =IF(_xlfn.IFNA(VLOOKUP(C81,Data!A:I,8,FALSE),"")=0, "", _xlfn.IFNA(HYPERLINK(VLOOKUP(C81,Data!A:I,8,FALSE),"Additional Information"),"")) -> Additional Information | M81: =COUNTIF(N81:BL81,"x") -> 6 | N81: x | R81: x | AE81: x | BB81: x | BH81: x | BJ81: x
A82: Yes | B82: ECE 36200 | C82: ECE 36200 | D82: ECE 36200 Microprocessor Systems And Interfacing | E82: =IF(_xlfn.IFNA(VLOOKUP(B82,Data!B:G,3,FALSE),"")=0, "", _xlfn.IFNA(VLOOKUP(B82,Data!B:G,3,FALSE),"")) -> 4 | F82: Integrated Circuit & System Design, Electronic Design Automation | H82: =IF(_xlfn.IFNA(VLOOKUP(C82,Data!A:G,5,FALSE),"")=0, "Check course registration information", _xlfn.IFNA(VLOOKUP(C82,Data!A:G,5,FALSE),"")) -> ECE 27000 and (ENGR 11700 or CS 15900 | J82: =IF(_xlfn.IFNA(VLOOKUP(C82,Data!A:G,6,FALSE),"")=0, "Check course registration information", _xlfn.IFNA(VLOOKUP(C82,Data!A:G,6,FALSE),"")) -> An introduction to basic computer organization, microprocessor instruction sets, assembly language programming, and microcontroller peripherals | K82: =IF(_xlfn.IFNA(VLOOKUP(C82,Data!A:H,7,FALSE),"")=0, "", _xlfn.IFNA(HYPERLINK(VLOOKUP(C82,Data!A:H,7,FALSE),"Catalog Link"),"")) -> Catalog Link | L82: =IF(_xlfn.IFNA(VLOOKUP(C82,Data!A:I,8,FALSE),"")=0, "", _xlfn.IFNA(HYPERLINK(VLOOKUP(C82,Data!A:I,8,FALSE),"Additional Information"),"")) -> Additional Information | M82: =COUNTIF(N82:BL82,"x") -> 3 | N82: x | BB82: x | BH82: x
A83: Yes | B83: ECE 39595 | C83: ECE 39595-1 | D83: ECE 39595 Semiconductor Manufacturing Unit Process | E83: 1 | F83: Semiconductor Materials, Characterization, and Processing | H83: =IF(_xlfn.IFNA(VLOOKUP(C83,Data!A:G,5,FALSE),"")=0, "Check course registration information", _xlfn.IFNA(VLOOKUP(C83,Data!A:G,5,FALSE),"")) -> Check course registration information | J83: =IF(_xlfn.IFNA(VLOOKUP(C83,Data!A:G,6,FALSE),"")=0, "Check course registration information", _xlfn.IFNA(VLOOKUP(C83,Data!A:G,6,FALSE),"")) -> This course introduces the principles and practices of modern semiconductor manufacturing. The course is organized into three modules covering semiconductor unit processes, process integration, and statistical process control (SPC). In the first module, students learn the fundamentals of key fabrication processes such as oxidation, lithography, etching, deposition, doping, and interconnect formation. Each module is offered as a one-credit course, and students may take individual modules or complete all three modules for a total of three credit hours. The goal of the course is to develop a systems-level understanding of semiconductor fabrication and to provide the background needed for work in semiconductor research and industry. | K83: =IF(_xlfn.IFNA(VLOOKUP(C83,Data!A:H,7,FALSE),"")=0, "", _xlfn.IFNA(HYPERLINK(VLOOKUP(C83,Data!A:H,7,FALSE),"Catalog Link"),"")) -> Catalog Link | L83: =IF(_xlfn.IFNA(VLOOKUP(C83,Data!A:I,8,FALSE),"")=0, "", _xlfn.IFNA(HYPERLINK(VLOOKUP(C83,Data!A:I,8,FALSE),"Additional Information"),"")) | M83: =COUNTIF(N83:BL83,"x") -> 5 | AA83: x | AE83: x | AF83: x | AG83: x | AH83: x
A84: Yes | B84: ECE 39595 | C84: ECE 39595-2 | D84: ECE 39595 Semiconductor Manufacturing Process Integration | E84: 1 | F84: Semiconductor Materials, Characterization, and Processing | H84: =IF(_xlfn.IFNA(VLOOKUP(C84,Data!A:G,5,FALSE),"")=0, "Check course registration information", _xlfn.IFNA(VLOOKUP(C84,Data!A:G,5,FALSE),"")) -> ECE 39595 Semiconductor Manufacturing Unit Process | J84: =IF(_xlfn.IFNA(VLOOKUP(C84,Data!A:G,6,FALSE),"")=0, "Check course registration information", _xlfn.IFNA(VLOOKUP(C84,Data!A:G,6,FALSE),"")) -> This course introduces the principles and practices of modern semiconductor manufacturing. The course is organized into three modules covering semiconductor unit processes, process integration, and statistical process control (SPC). In the second module, students examine process integration and learn how individual unit processes are combined to realize a complete CMOS fabrication flow. Each module is offered as a one-credit course, and students may take individual modules or complete all three modules for a total of three credit hours. The goal of the course is to develop a systems-level understanding of semiconductor fabrication and to provide the background needed for work in semiconductor research and industry. | K84: =IF(_xlfn.IFNA(VLOOKUP(C84,Data!A:H,7,FALSE),"")=0, "", _xlfn.IFNA(HYPERLINK(VLOOKUP(C84,Data!A:H,7,FALSE),"Catalog Link"),"")) -> Catalog Link | L84: =IF(_xlfn.IFNA(VLOOKUP(C84,Data!A:I,8,FALSE),"")=0, "", _xlfn.IFNA(HYPERLINK(VLOOKUP(C84,Data!A:I,8,FALSE),"Additional Information"),"")) | M84: =COUNTIF(N84:BL84,"x") -> 2 | AA84: x | AH84: x
A85: Yes | B85: ECE 39595 | C85: ECE 39595-3 | D85: ECE 39595 Statistical Process Control in Semiconductor Manufacturing | E85: 1 | F85: Semiconductor Materials, Characterization, and Processing | H85: =IF(_xlfn.IFNA(VLOOKUP(C85,Data!A:G,5,FALSE),"")=0, "Check course registration information", _xlfn.IFNA(VLOOKUP(C85,Data!A:G,5,FALSE),"")) -> ECE 39595 Semiconductor Manufacturing Process Integration | J85: =IF(_xlfn.IFNA(VLOOKUP(C85,Data!A:G,6,FALSE),"")=0, "Check course registration information", _xlfn.IFNA(VLOOKUP(C85,Data!A:G,6,FALSE),"")) -> This course introduces the principles and practices of modern semiconductor manufacturing. The course is organized into three modules covering semiconductor unit processes, process integration, and statistical process control (SPC). In the third module, students are introduced to statistical process control and manufacturing variability, with emphasis on process monitoring, data analysis, and yield improvement. Each module is offered as a one-credit course, and students may take individual modules or complete all three modules for a total of three credit hours. The goal of the course is to develop a systems-level understanding of semiconductor fabrication and to provide the background needed for work in semiconductor research and industry. | K85: =IF(_xlfn.IFNA(VLOOKUP(C85,Data!A:H,7,FALSE),"")=0, "", _xlfn.IFNA(HYPERLINK(VLOOKUP(C85,Data!A:H,7,FALSE),"Catalog Link"),"")) -> Catalog Link | L85: =IF(_xlfn.IFNA(VLOOKUP(C85,Data!A:I,8,FALSE),"")=0, "", _xlfn.IFNA(HYPERLINK(VLOOKUP(C85,Data!A:I,8,FALSE),"Additional Information"),"")) | M85: =COUNTIF(N85:BL85,"x") -> 2 | BD85: x | BE85: x
A86: Yes | B86: ECE 40655 | C86: ECE 40655 | D86: ECE 40655 Digital Integrated Circuit Analysis and Design | E86: =IF(_xlfn.IFNA(VLOOKUP(B86,Data!B:G,3,FALSE),"")=0, "", _xlfn.IFNA(VLOOKUP(B86,Data!B:G,3,FALSE),"")) -> 3 | F86: Integrated Circuit & System Design, Electronic Design Automation | H86: =IF(_xlfn.IFNA(VLOOKUP(C86,Data!A:G,5,FALSE),"")=0, "Check course registration information", _xlfn.IFNA(VLOOKUP(C86,Data!A:G,5,FALSE),"")) -> ECE 20002 and ECE 30500 [concurrent ok] | J86: =IF(_xlfn.IFNA(VLOOKUP(C86,Data!A:G,6,FALSE),"")=0, "Check course registration information", _xlfn.IFNA(VLOOKUP(C86,Data!A:G,6,FALSE),"")) -> As applied to digital integrated circuits, the MDs transistor is studied in depth-from its fabrication to its electrical characteristics. Combinational, sequential, and dynamic logic circuits are considered. While the focus of the course is on CMOS technology, bipolar, nMOS, and BiCMOS circuits are introduced as well. SPICE is used as both an analysis and design tool. Semiconductor memory circuits are also discussed | K86: =IF(_xlfn.IFNA(VLOOKUP(C86,Data!A:H,7,FALSE),"")=0, "", _xlfn.IFNA(HYPERLINK(VLOOKUP(C86,Data!A:H,7,FALSE),"Catalog Link"),"")) -> Catalog Link | L86: =IF(_xlfn.IFNA(VLOOKUP(C86,Data!A:I,8,FALSE),"")=0, "", _xlfn.IFNA(HYPERLINK(VLOOKUP(C86,Data!A:I,8,FALSE),"Additional Information"),"")) -> Additional Information | M86: =COUNTIF(N86:BL86,"x") -> 3 | T86: x | Y86: x | BB86: x
A87: Yes | B87: ECE 40656 | C87: ECE 40656 | D87: ECE 40656 CMOS Analog and Mixed Signal Integrated Circuits | E87: =IF(_xlfn.IFNA(VLOOKUP(B87,Data!B:G,3,FALSE),"")=0, "", _xlfn.IFNA(VLOOKUP(B87,Data!B:G,3,FALSE),"")) -> 3 | F87: Integrated Circuit & System Design, Electronic Design Automation | H87: =IF(_xlfn.IFNA(VLOOKUP(C87,Data!A:G,5,FALSE),"")=0, "Check course registration information", _xlfn.IFNA(VLOOKUP(C87,Data!A:G,5,FALSE),"")) -> ECE 20002 | J87: =IF(_xlfn.IFNA(VLOOKUP(C87,Data!A:G,6,FALSE),"")=0, "Check course registration information", _xlfn.IFNA(VLOOKUP(C87,Data!A:G,6,FALSE),"")) -> This course is a review of technology and modeling of CMOS transistors; Analysis, and design of CMOS monolithic integrated circuits for analog and mixed-signal applications. Consideration of amplifier circuit design, and fabrication techniques with circuit simulation using Cadence. Simple and advanced CMOS operational amplifiers, comparators, sample and hold circuits, switch capacitor circuits and data converters; Design of analog and mixed-signal circuit building blocks | K87: =IF(_xlfn.IFNA(VLOOKUP(C87,Data!A:H,7,FALSE),"")=0, "", _xlfn.IFNA(HYPERLINK(VLOOKUP(C87,Data!A:H,7,FALSE),"Catalog Link"),"")) -> Catalog Link | L87: =IF(_xlfn.IFNA(VLOOKUP(C87,Data!A:I,8,FALSE),"")=0, "", _xlfn.IFNA(HYPERLINK(VLOOKUP(C87,Data!A:I,8,FALSE),"Additional Information"),"")) -> Additional Information | M87: =COUNTIF(N87:BL87,"x") -> 3 | Q87: x | Y87: x | BB87: x
A88: No | B88: ECE 43300 | C88: ECE 43300 | D88: ECE 43300 Power Electronics | E88: =IF(_xlfn.IFNA(VLOOKUP(B88,Data!B:G,3,FALSE),"")=0, "", _xlfn.IFNA(VLOOKUP(B88,Data!B:G,3,FALSE),"")) -> 3 | F88: N/A | H88: =IF(_xlfn.IFNA(VLOOKUP(C88,Data!A:G,5,FALSE),"")=0, "Check course registration information", _xlfn.IFNA(VLOOKUP(C88,Data!A:G,5,FALSE),"")) -> ECE 20002 or ECE 25500 | J88: =IF(_xlfn.IFNA(VLOOKUP(C88,Data!A:G,6,FALSE),"")=0, "Check course registration information", _xlfn.IFNA(VLOOKUP(C88,Data!A:G,6,FALSE),"")) -> Introduction to the fundamental operating principles of power conditioning circuits that are currently being used to effect power flow from AC to DC and vice versa. Emphasis is on the relationship between form and function of these circuits. Circuits discussed will include AC/DC line-commutated converters, DC/DC converters, DC/variable frequency converters, resonant converters, and AC/AC converters. Computer simulations will be used as a part of the coursework | K88: =IF(_xlfn.IFNA(VLOOKUP(C88,Data!A:H,7,FALSE),"")=0, "", _xlfn.IFNA(HYPERLINK(VLOOKUP(C88,Data!A:H,7,FALSE),"Catalog Link"),"")) -> Catalog Link | L88: =IF(_xlfn.IFNA(VLOOKUP(C88,Data!A:I,8,FALSE),"")=0, "", _xlfn.IFNA(HYPERLINK(VLOOKUP(C88,Data!A:I,8,FALSE),"Additional Information"),"")) -> Additional Information | M88: =COUNTIF(N88:BL88,"x") -> 2 | AQ88: x | BB88: x
A89: No | B89: ECE 43700 | C89: ECE 43700 | D89: ECE 43700 Computer Design and Prototyping | E89: =IF(_xlfn.IFNA(VLOOKUP(B89,Data!B:G,3,FALSE),"")=0, "", _xlfn.IFNA(VLOOKUP(B89,Data!B:G,3,FALSE),"")) -> 4 | F89: N/A | H89: =IF(_xlfn.IFNA(VLOOKUP(C89,Data!A:G,5,FALSE),"")=0, "Check course registration information", _xlfn.IFNA(VLOOKUP(C89,Data!A:G,5,FALSE),"")) -> ECE 33700 and ECE 36200 | J89: =IF(_xlfn.IFNA(VLOOKUP(C89,Data!A:G,6,FALSE),"")=0, "Check course registration information", _xlfn.IFNA(VLOOKUP(C89,Data!A:G,6,FALSE),"")) -> An introduction to computer organization and design, including instruction set selection, arithmetic logic unit design, data path design, control strategies, pipelining, memory hierarchy, and I/O interface design | K89: =IF(_xlfn.IFNA(VLOOKUP(C89,Data!A:H,7,FALSE),"")=0, "", _xlfn.IFNA(HYPERLINK(VLOOKUP(C89,Data!A:H,7,FALSE),"Catalog Link"),"")) -> Catalog Link | L89: =IF(_xlfn.IFNA(VLOOKUP(C89,Data!A:I,8,FALSE),"")=0, "", _xlfn.IFNA(HYPERLINK(VLOOKUP(C89,Data!A:I,8,FALSE),"Additional Information"),"")) -> Additional Information | M89: =COUNTIF(N89:BL89,"x") -> 5 | R89: x | AD89: x | AE89: x | AT89: x | BB89: x
A90: Yes | B90: ECE 45300 | C90: ECE 45300 | D90: ECE 45300 Fundamentals Of Nanoelectronics | E90: =IF(_xlfn.IFNA(VLOOKUP(B90,Data!B:G,3,FALSE),"")=0, "", _xlfn.IFNA(VLOOKUP(B90,Data!B:G,3,FALSE),"")) -> 3 | F90: Semiconductor and Microelectronic Devices | H90: =IF(_xlfn.IFNA(VLOOKUP(C90,Data!A:G,5,FALSE),"")=0, "Check course registration information", _xlfn.IFNA(VLOOKUP(C90,Data!A:G,5,FALSE),"")) -> MA 26600 and MA 26500) or MA 26200 | J90: =IF(_xlfn.IFNA(VLOOKUP(C90,Data!A:G,6,FALSE),"")=0, "Check course registration information", _xlfn.IFNA(VLOOKUP(C90,Data!A:G,6,FALSE),"")) -> Nanoelectronic devices are an integral part of our life, including the billion-plus transistors in every smartphone, each of which has an active region that is only a few hundred atoms long. This course is designed to convey the key concepts developed in the last 25 years which constitute the fundamentals of nanoelectronics and mesoscopic physics, assuming a minimal set of prerequisites. Topics covered include the new Ohm's law, conductance quantization, the nanotransistor, spin valves, thermoelectricity, quantum systems and the non-equilibrium Green's function (NEGF) method | K90: =IF(_xlfn.IFNA(VLOOKUP(C90,Data!A:H,7,FALSE),"")=0, "", _xlfn.IFNA(HYPERLINK(VLOOKUP(C90,Data!A:H,7,FALSE),"Catalog Link"),"")) -> Catalog Link | L90: =IF(_xlfn.IFNA(VLOOKUP(C90,Data!A:I,8,FALSE),"")=0, "", _xlfn.IFNA(HYPERLINK(VLOOKUP(C90,Data!A:I,8,FALSE),"Additional Information"),"")) -> Additional Information | M90: =COUNTIF(N90:BL90,"x") -> 2 | AM90: x | BB90: x
A91: Yes | B91: ECE 45500 | C91: ECE 45500 | D91: ECE 45500 Integrated Circuit Engineering | E91: =IF(_xlfn.IFNA(VLOOKUP(B91,Data!B:G,3,FALSE),"")=0, "", _xlfn.IFNA(VLOOKUP(B91,Data!B:G,3,FALSE),"")) -> 3 | F91: Integrated Circuit & System Design, Electronic Design Automation | H91: =IF(_xlfn.IFNA(VLOOKUP(C91,Data!A:G,5,FALSE),"")=0, "Check course registration information", _xlfn.IFNA(VLOOKUP(C91,Data!A:G,5,FALSE),"")) -> ECE 20002 or (ECE 20200 and ECE 25500) and ECE 30500 [concurrent ok] | J91: =IF(_xlfn.IFNA(VLOOKUP(C91,Data!A:G,6,FALSE),"")=0, "Check course registration information", _xlfn.IFNA(VLOOKUP(C91,Data!A:G,6,FALSE),"")) -> Analysis, design, and fabrication of silicon bipolar and MOSFET monolithic integrated circuits. Consideration of amplifier circuit design and fabrication techniques with circuit simulation using Spice-2. Integrated operational amplifiers with difference amplifiers, current sources, active loads, and voltage references. Design of IC analog circuit building blocks | K91: =IF(_xlfn.IFNA(VLOOKUP(C91,Data!A:H,7,FALSE),"")=0, "", _xlfn.IFNA(HYPERLINK(VLOOKUP(C91,Data!A:H,7,FALSE),"Catalog Link"),"")) -> Catalog Link | L91: =IF(_xlfn.IFNA(VLOOKUP(C91,Data!A:I,8,FALSE),"")=0, "", _xlfn.IFNA(HYPERLINK(VLOOKUP(C91,Data!A:I,8,FALSE),"Additional Information"),"")) -> Additional Information | M91: =COUNTIF(N91:BL91,"x") -> 3 | Q91: x | Y91: x | BB91: x
A92: Yes | B92: ECE 45600 | C92: ECE 45600 | D92: ECE 45600 Digital Integrated Circuit Analysis And Design | E92: =IF(_xlfn.IFNA(VLOOKUP(B92,Data!B:G,3,FALSE),"")=0, "", _xlfn.IFNA(VLOOKUP(B92,Data!B:G,3,FALSE),"")) -> 3 | F92: Integrated Circuit & System Design, Electronic Design Automation | H92: =IF(_xlfn.IFNA(VLOOKUP(C92,Data!A:G,5,FALSE),"")=0, "Check course registration information", _xlfn.IFNA(VLOOKUP(C92,Data!A:G,5,FALSE),"")) -> ECE 20002 or (ECE 20200 and ECE 25500) and ECE 27000 and ECE 30500 | J92: =IF(_xlfn.IFNA(VLOOKUP(C92,Data!A:G,6,FALSE),"")=0, "Check course registration information", _xlfn.IFNA(VLOOKUP(C92,Data!A:G,6,FALSE),"")) -> As applied to digital integrated circuits, the MDs transistor is studied in depth-from its fabrication to its electrical characteristics. Combinational, sequential, and dynamic logic circuits are considered. While the focus of the course is on CMOS technology, bipolar, nMOS, and BiCMOS circuits are introduced as well. SPICE is used as both an analysis and design tool. Semiconductor memory circuits are also discussed | K92: =IF(_xlfn.IFNA(VLOOKUP(C92,Data!A:H,7,FALSE),"")=0, "", _xlfn.IFNA(HYPERLINK(VLOOKUP(C92,Data!A:H,7,FALSE),"Catalog Link"),"")) -> Catalog Link | L92: =IF(_xlfn.IFNA(VLOOKUP(C92,Data!A:I,8,FALSE),"")=0, "", _xlfn.IFNA(HYPERLINK(VLOOKUP(C92,Data!A:I,8,FALSE),"Additional Information"),"")) -> Additional Information | M92: =COUNTIF(N92:BL92,"x") -> 3 | T92: x | Y92: x | BB92: x
A93: Yes | B93: ECE 50616 | C93: ECE 50616 | D93: ECE 50616 Physics And Manufacturing Of Solar Cells | E93: =IF(_xlfn.IFNA(VLOOKUP(B93,Data!B:G,3,FALSE),"")=0, "", _xlfn.IFNA(VLOOKUP(B93,Data!B:G,3,FALSE),"")) -> 3 | F93: Semiconductor and Microelectronic Devices | H93: =IF(_xlfn.IFNA(VLOOKUP(C93,Data!A:G,5,FALSE),"")=0, "Check course registration information", _xlfn.IFNA(VLOOKUP(C93,Data!A:G,5,FALSE),"")) -> ECE 30500 or MSE 37000 or ME 31500 or ME 36300 or CHE 37800 or PHYS 33000 or CHM 37000 | J93: =IF(_xlfn.IFNA(VLOOKUP(C93,Data!A:G,6,FALSE),"")=0, "Check course registration information", _xlfn.IFNA(VLOOKUP(C93,Data!A:G,6,FALSE),"")) -> This course introduces the electronic, optical and material properties and the manufacturing of photovoltaic devices. Topics include electronic charge separation, transportation and recombination; optical concentration, trapping and confinement; material preparations in photovoltaic systems; bulk crystal, thin-film and organic photovoltaic device configurations; energy storage; as well as emerging concepts in photovoltaics. Discussions also involve the process and equipment for the manufacturing of various photovoltaic modules, with special emphasis on driving down the cost of photovoltaic systems | K93: =IF(_xlfn.IFNA(VLOOKUP(C93,Data!A:H,7,FALSE),"")=0, "", _xlfn.IFNA(HYPERLINK(VLOOKUP(C93,Data!A:H,7,FALSE),"Catalog Link"),"")) -> Catalog Link | L93: =IF(_xlfn.IFNA(VLOOKUP(C93,Data!A:I,8,FALSE),"")=0, "", _xlfn.IFNA(HYPERLINK(VLOOKUP(C93,Data!A:I,8,FALSE),"Additional Information"),"")) -> Additional Information | M93: =COUNTIF(N93:BL93,"x") -> 3 | Y93: x | AB93: x | BB93: x
A94: Yes | B94: ECE 50631 | C94: ECE 50631 | D94: ECE 50631 Fundamentals Of Current Flow | E94: =IF(_xlfn.IFNA(VLOOKUP(B94,Data!B:G,3,FALSE),"")=0, "", _xlfn.IFNA(VLOOKUP(B94,Data!B:G,3,FALSE),"")) -> 1 | F94: Semiconductor and Microelectronic Devices | H94: =IF(_xlfn.IFNA(VLOOKUP(C94,Data!A:G,5,FALSE),"")=0, "Check course registration information", _xlfn.IFNA(VLOOKUP(C94,Data!A:G,5,FALSE),"")) -> Junior status and above | J94: =IF(_xlfn.IFNA(VLOOKUP(C94,Data!A:G,6,FALSE),"")=0, "Check course registration information", _xlfn.IFNA(VLOOKUP(C94,Data!A:G,6,FALSE),"")) -> Traditional description of electronic motion through a solid is based on diffusive transport which means that the electron takes a random walk from the source to the drain. However, modern nanoelectronic devices often have channel lengths comparable to a mean free path so that electrons travel ballistically, or "like a bullet." This course provides a unified conceptual framework for ballistic and diffusive transport of both electrons and phonons, that is very different from what is taught in standard courses, but indispensable to understanding nanolectronic devices | K94: =IF(_xlfn.IFNA(VLOOKUP(C94,Data!A:H,7,FALSE),"")=0, "", _xlfn.IFNA(HYPERLINK(VLOOKUP(C94,Data!A:H,7,FALSE),"Catalog Link"),"")) -> Catalog Link | L94: =IF(_xlfn.IFNA(VLOOKUP(C94,Data!A:I,8,FALSE),"")=0, "", _xlfn.IFNA(HYPERLINK(VLOOKUP(C94,Data!A:I,8,FALSE),"Additional Information"),"")) -> Additional Information | M94: =COUNTIF(N94:BL94,"x") -> 2 | Y94: x | BB94: x
A95: Yes | B95: ECE 50632 | C95: ECE 50632 | D95: ECE 50632 Introduction to Quantum Transport | E95: =IF(_xlfn.IFNA(VLOOKUP(B95,Data!B:G,3,FALSE),"")=0, "", _xlfn.IFNA(VLOOKUP(B95,Data!B:G,3,FALSE),"")) -> 1 | F95: Semiconductor and Microelectronic Devices | H95: =IF(_xlfn.IFNA(VLOOKUP(C95,Data!A:G,5,FALSE),"")=0, "Check course registration information", _xlfn.IFNA(VLOOKUP(C95,Data!A:G,5,FALSE),"")) -> Junior status and above | J95: =IF(_xlfn.IFNA(VLOOKUP(C95,Data!A:G,6,FALSE),"")=0, "Check course registration information", _xlfn.IFNA(VLOOKUP(C95,Data!A:G,6,FALSE),"")) -> This course introduces the Schrodinger equation, uses the tight-binding method to discuss the concept of band structure and E(k) relations, along with simple quantum transport problems. No prior background in quantum mechanics or statistical mechanics is assumed | K95: =IF(_xlfn.IFNA(VLOOKUP(C95,Data!A:H,7,FALSE),"")=0, "", _xlfn.IFNA(HYPERLINK(VLOOKUP(C95,Data!A:H,7,FALSE),"Catalog Link"),"")) -> Catalog Link | L95: =IF(_xlfn.IFNA(VLOOKUP(C95,Data!A:I,8,FALSE),"")=0, "", _xlfn.IFNA(HYPERLINK(VLOOKUP(C95,Data!A:I,8,FALSE),"Additional Information"),"")) -> Additional Information | M95: =COUNTIF(N95:BL95,"x") -> 2 | Y95: x | AW95: x
A96: Yes | B96: ECE 50633 | C96: ECE 50633 | D96: ECE 50633 Boltzmann Law: Physics to Machine Learning | E96: =IF(_xlfn.IFNA(VLOOKUP(B96,Data!B:G,3,FALSE),"")=0, "", _xlfn.IFNA(VLOOKUP(B96,Data!B:G,3,FALSE),"")) -> 1 | F96: Semiconductor and Microelectronic Devices | H96: =IF(_xlfn.IFNA(VLOOKUP(C96,Data!A:G,5,FALSE),"")=0, "Check course registration information", _xlfn.IFNA(VLOOKUP(C96,Data!A:G,5,FALSE),"")) -> Junior status and above | J96: =IF(_xlfn.IFNA(VLOOKUP(C96,Data!A:G,6,FALSE),"")=0, "Check course registration information", _xlfn.IFNA(VLOOKUP(C96,Data!A:G,6,FALSE),"")) -> This course introduces the key concepts of equilibrium statistical mechanics leading to the celebrated Boltzmann law and how it leads to Boltzmann machines and related concepts in modern machine learning. No prior background in statistical mechanics is assumed | K96: =IF(_xlfn.IFNA(VLOOKUP(C96,Data!A:H,7,FALSE),"")=0, "", _xlfn.IFNA(HYPERLINK(VLOOKUP(C96,Data!A:H,7,FALSE),"Catalog Link"),"")) -> Catalog Link | L96: =IF(_xlfn.IFNA(VLOOKUP(C96,Data!A:I,8,FALSE),"")=0, "", _xlfn.IFNA(HYPERLINK(VLOOKUP(C96,Data!A:I,8,FALSE),"Additional Information"),"")) -> Additional Information | M96: =COUNTIF(N96:BL96,"x") -> 5 | O96: x | Y96: x | AH96: x | AM96: x | AW96: x
A97: Yes | B97: ECE 50641 | C97: ECE 50641 | D97: ECE 50641 Semiconductor Fundamentals | E97: =IF(_xlfn.IFNA(VLOOKUP(B97,Data!B:G,3,FALSE),"")=0, "", _xlfn.IFNA(VLOOKUP(B97,Data!B:G,3,FALSE),"")) -> 1 | F97: Semiconductor and Microelectronic Devices | H97: =IF(_xlfn.IFNA(VLOOKUP(C97,Data!A:G,5,FALSE),"")=0, "Check course registration information", _xlfn.IFNA(VLOOKUP(C97,Data!A:G,5,FALSE),"")) -> CHM 11500 or PHYS 24100 or PHYS 27200 or MA 26200 or MA 26600 | J97: =IF(_xlfn.IFNA(VLOOKUP(C97,Data!A:G,6,FALSE),"")=0, "Check course registration information", _xlfn.IFNA(VLOOKUP(C97,Data!A:G,6,FALSE),"")) -> This course about semiconductors is designed to provide a foundation to understand the operation of devices such as transistors, diodes, solar cells, light-emitting devices, etc. The course does not discuss devices - it prepares students to understand the operation of semiconductor devices. The treatment is physical and intuitive, and not heavily mathematical. Technology users will gain an understanding of the semiconductor physics that is the basis for devices. Semiconductor technology developers may find it a useful starting point for diving deeper into condensed matter physics, statistical mechanics, thermodynamics, and materials science. The course presents an electrical engineering perspective on semiconductors, but those in other fields may find it a useful introduction to the approach that has guided the development of semiconductor technology for the past 50+ years. Topics include semiconductor fundamentals such as energy bands, bandgaps, effective masses, electrons and holes, and elements of quantum mechanics. The Fermi function, doping, and carrier densities are then discussed. Carrier transport and generation-recombination are examined along with the important concept of quasi-Fermi levels. The course concludes with the "semiconductor equations," which provide a complete, mathematical description of electrons and holes in semiconductors (subject to some important simplifying assumptions) and ends with a discussion of how energy band diagrams provide a qualitative solution to these equations | K97: =IF(_xlfn.IFNA(VLOOKUP(C97,Data!A:H,7,FALSE),"")=0, "", _xlfn.IFNA(HYPERLINK(VLOOKUP(C97,Data!A:H,7,FALSE),"Catalog Link"),"")) -> Catalog Link | L97: =IF(_xlfn.IFNA(VLOOKUP(C97,Data!A:I,8,FALSE),"")=0, "", _xlfn.IFNA(HYPERLINK(VLOOKUP(C97,Data!A:I,8,FALSE),"Additional Information"),"")) -> Additional Information | M97: =COUNTIF(N97:BL97,"x") -> 2 | Y97: x | BB97: x
A98: Yes | B98: ECE 50642 | C98: ECE 50642 | D98: ECE 50642 Fundamentals of Transistors | E98: =IF(_xlfn.IFNA(VLOOKUP(B98,Data!B:G,3,FALSE),"")=0, "", _xlfn.IFNA(VLOOKUP(B98,Data!B:G,3,FALSE),"")) -> 1 | F98: Semiconductor and Microelectronic Devices | H98: =IF(_xlfn.IFNA(VLOOKUP(C98,Data!A:G,5,FALSE),"")=0, "Check course registration information", _xlfn.IFNA(VLOOKUP(C98,Data!A:G,5,FALSE),"")) -> ECE 30500 or ECE 50641 | J98: =IF(_xlfn.IFNA(VLOOKUP(C98,Data!A:G,6,FALSE),"")=0, "Check course registration information", _xlfn.IFNA(VLOOKUP(C98,Data!A:G,6,FALSE),"")) -> This course is designed for anyone seeking a sound, physical, intuitive understanding of how modern transistors operate. Important technology considerations and applications of transistors are also discussed. The focus is on MOSFETs for digital logic, but other types of transistors are briefly considered. The course is broadly accessible to students with only a very basic knowledge of semiconductor physics and electronic circuits and should be useful for advanced undergraduates, beginning graduate students, as well as practicing engineers and scientists. Topics include device metrics for digital and analog circuits, traditional MOSFET theory, the virtual source model, 1D and 2D electrostatics, Landauer/transmission approach to nanotransistors, the limits of MOSFETs, as well as a quick look at HEMTs, bipolar transistors, and compact circuit models | K98: =IF(_xlfn.IFNA(VLOOKUP(C98,Data!A:H,7,FALSE),"")=0, "", _xlfn.IFNA(HYPERLINK(VLOOKUP(C98,Data!A:H,7,FALSE),"Catalog Link"),"")) -> Catalog Link | L98: =IF(_xlfn.IFNA(VLOOKUP(C98,Data!A:I,8,FALSE),"")=0, "", _xlfn.IFNA(HYPERLINK(VLOOKUP(C98,Data!A:I,8,FALSE),"Additional Information"),"")) -> Additional Information | M98: =COUNTIF(N98:BL98,"x") -> 2 | Y98: x | BB98: x
A99: No | B99: ECE 50653 | C99: ECE 50653 | D99: ECE 50653 Fundamentals Of Nanoelectronics | E99: =IF(_xlfn.IFNA(VLOOKUP(B99,Data!B:G,3,FALSE),"")=0, "", _xlfn.IFNA(VLOOKUP(B99,Data!B:G,3,FALSE),"")) -> 3 | F99: Semiconductor and Microelectronic Devices | H99: =IF(_xlfn.IFNA(VLOOKUP(C99,Data!A:G,5,FALSE),"")=0, "Check course registration information", _xlfn.IFNA(VLOOKUP(C99,Data!A:G,5,FALSE),"")) -> MA 26200 or MA 26500 or MA 26600 | I99: Currently running as three 5-week modules: ECE 50631: Fundamentals of Current Flow, ECE 50632: Introduction to Quantum Transport and ECE 50633: Boltzmann Law: Physics to Machine Learning | J99: =IF(_xlfn.IFNA(VLOOKUP(C99,Data!A:G,6,FALSE),"")=0, "Check course registration information", _xlfn.IFNA(VLOOKUP(C99,Data!A:G,6,FALSE),"")) -> The modern smartphone is enabled by a billion-plus nano-transistors, each having an active region that is barely a few hundred atoms long. Interestingly the same amazing technology has also led to a deeper understanding of the nature of current flow on an atomic scale. The aim of this course is to make the fundamentals of nanoelectronics accessible to anyone in any branch of science or engineering, assuming very little background beyond linear algebra and differential equations, although we will be discussing advanced concepts in non-equilibrium statistical mechanics that should be of interest even to specialists. We first introduce a new perspective connecting the quantized conductance of short ballistic conductors to the familiar Ohm's law of long diffusive conductors, along with a brief description of the modern nano-transistor. We then address fundamental conceptual issues related to the meaning of resistance on an atomic scale, the interconversion of electricity and heat, the second law of thermodynamics and the fuel value of information. Finally we introduce the concepts of quantum transport as applied to modern nanoscale electronic devices | K99: =IF(_xlfn.IFNA(VLOOKUP(C99,Data!A:H,7,FALSE),"")=0, "", _xlfn.IFNA(HYPERLINK(VLOOKUP(C99,Data!A:H,7,FALSE),"Catalog Link"),"")) -> Catalog Link | L99: =IF(_xlfn.IFNA(VLOOKUP(C99,Data!A:I,8,FALSE),"")=0, "", _xlfn.IFNA(HYPERLINK(VLOOKUP(C99,Data!A:I,8,FALSE),"Additional Information"),"")) -> Additional Information | M99: =COUNTIF(N99:BL99,"x") -> 2 | Y99: x | BB99: x
A100: Yes | B100: ECE 51214 | C100: ECE 51214 | D100: ECE 51214 CMOS Analog IC Design | E100: =IF(_xlfn.IFNA(VLOOKUP(B100,Data!B:G,3,FALSE),"")=0, "", _xlfn.IFNA(VLOOKUP(B100,Data!B:G,3,FALSE),"")) -> 3 | F100: Integrated Circuit & System Design, Electronic Design Automation | H100: =IF(_xlfn.IFNA(VLOOKUP(C100,Data!A:G,5,FALSE),"")=0, "Check course registration information", _xlfn.IFNA(VLOOKUP(C100,Data!A:G,5,FALSE),"")) -> ECE 25500 | J100: =IF(_xlfn.IFNA(VLOOKUP(C100,Data!A:G,6,FALSE),"")=0, "Check course registration information", _xlfn.IFNA(VLOOKUP(C100,Data!A:G,6,FALSE),"")) -> The course covers general topics in CMOS analog IC design; biasing, noise, single stage amplifiers, differential amplifiers, OP-Amp, OTA, frequency domain analysis, and active filters. While the focus of the course is on CMOS IC design, design in bipolar andBi CMOS technologies are introduced as well. A design project is a key component of the course. The students conduct group or individual design projects. Process Design Kit and EDA tools are provided for the design projects | K100: =IF(_xlfn.IFNA(VLOOKUP(C100,Data!A:H,7,FALSE),"")=0, "", _xlfn.IFNA(HYPERLINK(VLOOKUP(C100,Data!A:H,7,FALSE),"Catalog Link"),"")) -> Catalog Link | L100: =IF(_xlfn.IFNA(VLOOKUP(C100,Data!A:I,8,FALSE),"")=0, "", _xlfn.IFNA(HYPERLINK(VLOOKUP(C100,Data!A:I,8,FALSE),"Additional Information"),"")) -> Additional Information | M100: =COUNTIF(N100:BL100,"x") -> 2 | Q100: x | AO100: x
...

Sheet Official Courses
A1: =LEFT(B1,FIND("-",B1)-2) -> ECE 30500 | B1: ECE 30500 - Semiconductor Devices Credit Hours: 3.00 | C1: Semiconductor and Microelectronic Devices | H1: =VLOOKUP(A1,Updated!B:D,3,FALSE) -> ECE 30500 Semiconductor Devices | J1: https://catalog.purdue.edu/preview_program.php?catoid=19&poid=35832&hl=%22semiconductor%22&returnto=search
A2: =LEFT(B2,FIND("-",B2)-2) -> ECE 45300 | B2: ECE 45300 - Fundamentals Of Nanoelectronics Credit Hours: 3.00 | C2: Semiconductor and Microelectronic Devices | H2: =VLOOKUP(A2,Updated!B:D,3,FALSE) -> ECE 45300 Fundamentals Of Nanoelectronics
A3: =LEFT(B3,FIND("-",B3)-2) -> ECE 50616 | B3: ECE 50616 - Physics And Manufacturing Of Solar Cells Credit Hours: 3.00 | C3: Semiconductor and Microelectronic Devices | H3: =VLOOKUP(A3,Updated!B:D,3,FALSE) -> ECE 50616 Physics And Manufacturing Of Solar Cells
A4: =LEFT(B4,FIND("-",B4)-2) -> ECE 50631 | B4: ECE 50631 - Fundamentals Of Current Flow Credit Hours: 1.00 | C4: Semiconductor and Microelectronic Devices | H4: =VLOOKUP(A4,Updated!B:D,3,FALSE) -> ECE 50631 Fundamentals Of Current Flow
A5: =LEFT(B5,FIND("-",B5)-2) -> ECE 50632 | B5: ECE 50632 - Introduction To Quantum Transport Credit Hours: 1.00 | C5: Semiconductor and Microelectronic Devices | H5: =VLOOKUP(A5,Updated!B:D,3,FALSE) -> ECE 50632 Introduction to Quantum Transport
A6: =LEFT(B6,FIND("-",B6)-2) -> ECE 50633 | B6: ECE 50633 - Boltzmann Law: Physics To Computing Credit Hours: 1.00 | C6: Semiconductor and Microelectronic Devices | H6: =VLOOKUP(A6,Updated!B:D,3,FALSE) -> ECE 50633 Boltzmann Law: Physics to Machine Learning
A7: =LEFT(B7,FIND("-",B7)-2) -> ECE 50641 | B7: ECE 50641 - Semiconductor Fundamentals Credit Hours: 1.00 | C7: Semiconductor and Microelectronic Devices | H7: =VLOOKUP(A7,Updated!B:D,3,FALSE) -> ECE 50641 Semiconductor Fundamentals
A8: =LEFT(B8,FIND("-",B8)-2) -> ECE 50642 | B8: ECE 50642 - Fundamental Of Transistors Credit Hours: 1.00 | C8: Semiconductor and Microelectronic Devices | H8: =VLOOKUP(A8,Updated!B:D,3,FALSE) -> ECE 50642 Fundamentals of Transistors
A9: =LEFT(B9,FIND("-",B9)-2) -> PHYS 32200 | B9: PHYS 32200 - Intermediate Optics Credit Hours: 3.00 | C9: Semiconductor and Microelectronic Devices | H9: =VLOOKUP(A9,Updated!B:D,3,FALSE) -> PHYS 32200 Intermediate Optics
A10: =LEFT(B10,FIND("-",B10)-2) -> PHYS 34900 | B10: PHYS 34900 - Introduction To Quantum Computing Credit Hours: 3.00 | C10: Semiconductor and Microelectronic Devices | H10: =VLOOKUP(A10,Updated!B:D,3,FALSE) -> PHYS 349 Introduction to Quantum Computing
A11: =LEFT(B11,FIND("-",B11)-2) -> PHYS 45000 | B11: PHYS 45000 - Intermediate Laboratory Credit Hours: 2.00 | C11: Semiconductor and Microelectronic Devices | H11: =VLOOKUP(A11,Updated!B:D,3,FALSE) -> PHYS450: Optics Laboratory I
A12: =LEFT(B12,FIND("-",B12)-2) -> PHYS 52600 | B12: PHYS 52600 - Physics Of Quantum Computing And Quantum Information Credit Hours: 3.00 | C12: Semiconductor and Microelectronic Devices | H12: =VLOOKUP(A12,Updated!B:D,3,FALSE) -> PHYS 526 Physics Of Quantum Computing And Quantum Information
A13: =LEFT(B13,FIND("-",B13)-2) -> PHYS 54500 | B13: PHYS 54500 - Solid-State Physics Credit Hours: 3.00 | C13: Semiconductor and Microelectronic Devices | H13: =VLOOKUP(A13,Updated!B:D,3,FALSE) -> PHYS 545 Solid State Physics
... A67: =LEFT(B67,FIND("-",B67)-2) -> SCOM 46300 | B67: SCOM 46300 - Supply Chain Analytics Credit Hours: 3.00 | C67: Semiconductor Manufacturing and Global Supply Chain Management | H67: =VLOOKUP(A67,Updated!B:D,3,FALSE) -> SCOM 46300 Supply Chain Analytics

Sheet Data
A1: Certificate Course Number | B1: Course Number | C1: Course | D1: Credits | E1: Pre-Requisites | F1: Course Description | G1: Catalog Link | H1: Additional Information
A2: CHE 20500 | B2: CHE 20500 | C2: CHE 20500 Chemical Engineering Calculations | D2: 4 | E2: ENGR 12100 or ENFY 12600 or ENGR 12600 or ENFY 13100 or ENGR 13100 or ENGR 13000 or VIP 17911 or ENGR 17911 or ENGR 16100 or EPCS 11100 or EPCS 12100 or ENFY 19500 or ENGR 19500 or ENGR 14100 or ENGR 16100) and (PHYS 17200 or (PHYS 16200 and PHYS 16300) or (ENGR 16200) and (MA 16100 or MA 16700 Minimum Grade of | F2: Quantitative applications of steady-state mass and energy balances to solve problems involving multi-component systems and multi-unit chemical processes. Single-component and multi-component phase equilibria, single-reaction and multiple-reaction stoichiometry, coupled mass and energy balances, chemical processes involving bypass and recycle streams | G2: https://selfservice.mypurdue.purdue.edu/prod/bwckctlg.p_disp_course_detail?cat_term_in=202710&subj_code_in=CHE&crse_numb_in=20500
A3: CHE 21100 | B3: CHE 21100 | C3: CHE 21100 Introductory Chemical Engineering Thermodynamics | D3: 4 | E3: CHE 20500 and (MA 26100 or MATH 26100 or MA 18200 or MA 17400 or MA 27100 or MA 26300 or MA 17200 | F3: Basic principles and concepts of thermodynamics applied to chemical engineering problems; use of basic thermodynamic functions of enthalpy, entropy, free energy to solutions, phase equilibria, and chemical equilibria; thermodynamic processes and efficiencies; equations of state; and relation of macroscopic to molecular properties | G3: https://selfservice.mypurdue.purdue.edu/prod/bwckctlg.p_disp_course_detail?cat_term_in=202710&subj_code_in=CHE&crse_numb_in=21100
A4: CHE 30600 | B4: CHE 30600 | C4: CHE 30600 Design Of Staged Separation Processes | D4: 3 | E4: CHE 20500 and CHE 21100 | F4: The application of equilibria and mass and energy balances for the design of staged separation processes. Use of various equilibrium data and thermodynamic principles for the design of batch and continuous distillation, absorption, stripping, and extraction systems. Stagewise calculations and graphical methods for design of binary systems. Design of multicomponent separators. Determination of stage efficiency and column size | G4: https://selfservice.mypurdue.purdue.edu/prod/bwckctlg.p_disp_course_detail?cat_term_in=202710&subj_code_in=CHE&crse_numb_in=30600
A5: CHE 32000 | B5: CHE 32000 | C5: CHE 32000 Statistical Modeling And Quality Enhancement | D5: 3 | E5: CHE 20500 or ABE 20100) and MA 26100 [concurrent ok] and (CHM 26100 or CHM 25500 [concurrent ok] or CHM 25700 [concurrent ok]) and (MA 26200 [concurrent ok] or MATH 26200 or MA 26500 [concurrent ok] or MA 35100 [concurrent ok] | F5: Statistical modeling methods, design of experiments, error analysis, curve fitting and regression, analysis of variance, confidence intervals, quality control and enhancement: emphasizes preparation for designing chemical engineering laboratory experiments and analyzing data | G5: https://selfservice.mypurdue.purdue.edu/prod/bwckctlg.p_disp_course_detail?cat_term_in=202710&subj_code_in=CHE&crse_numb_in=32000
A6: CHE 34800 | B6: CHE 34800 | C6: CHE 34800 Chemical Reaction Engineering | D6: 4 | E6: CHE 21100 and (MA 26600 [concurrent ok] or MA 30300 [concurrent ok] or MA 36600 [concurrent ok] or ME 58100 [concurrent ok] or MA 51400 [concurrent ok] | F6: Application of kinetic rate equations, mass balances and energy balances to the analysis and design of chemical reactors involving homogeneous and heterogeneous chemical reactions. Chemical equilibria, kinetic rate equations for homogeneous and heterogeneously catalyzed reactions, design of ideal isothermal reactors, effects of non-isothermal operation, effects of diffusion in porous catalysts and non-ideal mixing in continuous flow reactors | G6: https://selfservice.mypurdue.purdue.edu/prod/bwckctlg.p_disp_course_detail?cat_term_in=202710&subj_code_in=CHE&crse_numb_in=34800
A7: CHE 37700 | B7: CHE 37700 | C7: CHE 37700 Momentum Transfer | D7: 4 | E7: CHE 21100 and (MA 26600 [concurrent ok] or MA 30300 [concurrent ok] or MA 36600 [concurrent ok] or MA 51400 [concurrent ok] or ME 58100 [concurrent ok] | F7: Differential (microscopic) and integral (macroscopic) mass, momentum, and energy balances. Newtonian and non-Newtonian fluids. Fluid statics. One-dimensional steady and transient laminar flows. Turbulence. Dimensional analysis and similarity. Friction factors and drag coefficients. Applications to engineering analysis of practical problems. Introduction to numerical analysis and visualization of flows | G7: https://selfservice.mypurdue.purdue.edu/prod/bwckctlg.p_disp_course_detail?cat_term_in=202710&subj_code_in=CHE&crse_numb_in=37700
A8: CHE 37800 | B8: CHE 37800 | C8: CHE 37800 Heat And Mass Transfer | D8: 4 | E8: CHE 21100 and CHE 37700 | F8: Macroscopic and differential energy balances. Heat transfer coefficients for free and forced convection and phase change. Conductive and radiative heat transfer. Applications to heat transfer equipment design and compressible fluid flow. Macroscopic and differential species balances. Mass transfer coefficients and analogies. Mass transfer with and without chemical reaction. Mass transfer equipment design | G8: https://selfservice.mypurdue.purdue.edu/prod/bwckctlg.p_disp_course_detail?cat_term_in=202710&subj_code_in=CHE&crse_numb_in=37800
A9: CHE 42000 | B9: CHE 42000 | C9: CHE 42000 Process Safety Management And Analysis | D9: 3 | E9: CHE 34800 [concurrent ok] and CHE 37800 [concurrent ok] | F9: Develop knowledge of process safety management and analysis in the process industries, including hazard identification, hazard analysis and risk management | G9: https://selfservice.mypurdue.purdue.edu/prod/bwckctlg.p_disp_course_detail?cat_term_in=202710&subj_code_in=CHE&crse_numb_in=42000
A10: CHE 43500 | B10: CHE 43500 | C10: CHE 43500 Chemical Engineering Laboratory | D10: 4 | E10: CHE 32000 and CHE 34800 and CHE 37800 and CHE 30600 | F10: Quantitative experimental study of projects involving problems in fluid mechanics and heat and mass transfer or operation and evaluation of equipment; projects include analysis and data-based design of operations involving mass transfer such as distillation, absorption, drying, humidification, etc.; study of rates and equilibria in simple chemical reaction systems; study of chemical processes; application of methods of data analysis in practice; some library work; emphasis on group work, report writing, and oral communication | G10: https://selfservice.mypurdue.purdue.edu/prod/bwckctlg.p_disp_course_detail?cat_term_in=202710&subj_code_in=CHE&crse_numb_in=43500
A11: CHE 45000 | B11: CHE 45000 | C11: CHE 45000 Design And Analysis Of Processing Systems | D11: 4 | E11: CHE 30600 and CHE 37800 and CHE 42000 and CHE 45600 and CHE 43500 [concurrent ok] | F11: Use of process synthesis methods and concepts; detailed design of unit operation equipment, the economics of chemical plants and flow sheet optimization methods. Synthesize, develop, and evaluate a preliminary design of a chemical process that meets market requirements for a specific product. Analysis of design alternatives using case studies and optimization methods | G11: https://selfservice.mypurdue.purdue.edu/prod/bwckctlg.p_disp_course_detail?cat_term_in=202710&subj_code_in=CHE&crse_numb_in=45000
A12: CHE 45600 | B12: CHE 45600 | C12: CHE 45600 Process Dynamics And Control | D12: 3 | E12: CHE 37700 and CHE 34800 [concurrent ok] and CHE 37800 [concurrent ok] | F12: Dynamic response and control of chemical processing equipment, such as heat exchangers, chemical reactors, and absorption towers. Use is made of fundamental techniques of servomechanism theory, such as block diagrams, transfer functions, and frequency response. Introduction to advanced control techniques | G12: https://selfservice.mypurdue.purdue.edu/prod/bwckctlg.p_disp_course_detail?cat_term_in=202710&subj_code_in=CHE&crse_numb_in=45600
A13: CHE 53600 | B13: CHE 53600 | C13: CHE 53600 Particulate Systems | D13: 3 | E13: CHE 37700 | F13: A broad overview of the fundamental concepts in particulate systems including particle characterization, particle size measurement, sedimentation, fluidization, gas and liquid conveying, particle storage, fluid-particle separation, particle size enlargement and reduction, particle mixing and hazards associated with the handling of particulate solids. Practical applications are emphasized, with a focus on how particles behave differently than fluids | G13: https://selfservice.mypurdue.purdue.edu/prod/bwckctlg.p_disp_course_detail?cat_term_in=202710&subj_code_in=CHE&crse_numb_in=53600
... A22: CHE 56400 | B22: CHE 56400 | C22: CHE 56400 Organic Electronic Materials And Devices | D22: 3 | E22: CHM 26100 or CHM 25500 or CHM 25700 | F22: This course introduces the synthesis, optoelectronic properties, transport physics, and device operation of organic and hybrid electronic materials and devices. This course will review how the molecular architecture of small molecule and polymer semiconductors can be turned to alter the optoelectronic properties of the materials in solution and in the solid state. A number of relevant materials interactions will be covered, including: photoexcitation and recombination, intermolecular charge transport mechanisms, and energy transfer processes. Additionally, we will observe how these processes are relevant to applications such as organic field-effect transistors (OFETs), organic light-emitting diodes (OLEDs), organic photovoltaic (OPV) devices, and organic memory elements. Finally, a new type of organic-inorganic hybrid material called hybrid halide perovskite will be introduced | G22: https://selfservice.mypurdue.purdue.edu/prod/bwckctlg.p_disp_course_detail?cat_term_in=202710&subj_code_in=CHE&crse_numb_in=56400
A23: CHE 59700 | B23: CHE 59700 | C23: CHE 59700 Crystallization Systems in Engr | G23: https://selfservice.mypurdue.purdue.edu/prod/bwckctlg.p_disp_course_detail?cat_term_in=202710&subj_code_in=CHE&crse_numb_in=59700
A24: CHE 59700-1 | B24: CHE 59700 | C24: CHE 59700 Industial Catalytic Processes | G24: https://selfservice.mypurdue.purdue.edu/prod/bwckctlg.p_disp_course_detail?cat_term_in=202710&subj_code_in=CHE&crse_numb_in=59700
A25: CHE 59700-2 | B25: CHE 59700 | C25: CHE 59700 Industrial Chemical Technology | G25: https://selfservice.mypurdue.purdue.edu/prod/bwckctlg.p_disp_course_detail?cat_term_in=202710&subj_code_in=CHE&crse_numb_in=59700
A26: CHE 59700-3 | B26: CHE 59700 | C26: CHE 59700 Org Elec Materials and Devices | G26: https://selfservice.mypurdue.purdue.edu/prod/bwckctlg.p_disp_course_detail?cat_term_in=202710&subj_code_in=CHE&crse_numb_in=59700
A27: CHE 59700-4 | B27: CHE 59700 | C27: CHE 59700 Process Synthesis | G27: https://selfservice.mypurdue.purdue.edu/prod/bwckctlg.p_disp_course_detail?cat_term_in=202710&subj_code_in=CHE&crse_numb_in=59700
A28: CHE 59700-5 | B28: CHE 59700 | C28: CHE 59700 System Analysis of Energy Prod/ Energy Systems | G28: https://selfservice.mypurdue.purdue.edu/prod/bwckctlg.p_disp_course_detail?cat_term_in=202710&subj_code_in=CHE&crse_numb_in=59700
A29: CHE 59700-6 | B29: CHE 59700 | C29: CHE 59700 Data Science in ChE | G29: https://selfservice.mypurdue.purdue.edu/prod/bwckctlg.p_disp_course_detail?cat_term_in=202710&subj_code_in=CHE&crse_numb_in=59700
A30: CHE 59700-7 | B30: CHE 59700 | C30: CHE 59700 Manufacturing Advanced Composites | G30: https://selfservice.mypurdue.purdue.edu/prod/bwckctlg.p_disp_course_detail?cat_term_in=202710&subj_code_in=CHE&crse_numb_in=59700
A31: CHE 59700A | B31: CHE 59700A | C31: CHE 59700A Risk Management In The Design, Development And Optimization Of New Products And Processes | D31: 3 | F31: Legacy information online. | G31: https://selfservice.mypurdue.purdue.edu/prod/bwckctlg.p_disp_course_detail?cat_term_in=202710&subj_code_in=CHE&crse_numb_in=59700A | H31: https://purdue.edu/registrar/legacy/Home/Course/19R0432D0AAIK1HTMJ70
A32: CHE 59700C | B32: CHE 59700C | C32: CHE 59700C Intro to Energy Stor Sys | D32: 3 | F32: Now CHE 56000 | G32: https://selfservice.mypurdue.purdue.edu/prod/bwckctlg.p_disp_course_detail?cat_term_in=202710&subj_code_in=CHE&crse_numb_in=59700C
A33: CHE 56000 | B33: CHE 56000 | C33: CHE 56000 Introduction To Energy Storage Systems | D33: 3 | E33: Senior status and above | F33: Energy Storage Systems Laboratory course is designed to introduce fundamentals of electrochemistry and electrochemical engineering of rechargeable lithium ion batteries (LIBs) to undergraduate and graduate students. The course will be reviewing working principles of LIBs, hands-on experience on their assembly, charge-discharge testing, data analysis and related safety aspects. Strong emphasis will be given on the Li-ion battery technology, nanotechnology implementation and the materials design. Beyond conventional Li-ion systems and Pb-acid batteries, next generation Na-ion, K-ion and Li-S batteries will be discussed and designed. Students will be fabricating and testing high energy density batteries utilizing engineered electrodes, electrolytes and separators. Broader perspectives on sustainable, cost effective, longer lasting battery manufacturing will be provided. | G33: https://selfservice.mypurdue.purdue.edu/prod/bwckctlg.p_disp_course_detail?cat_term_in=202710&subj_code_in=CHE&crse_numb_in=56000
A34: CHE 59700N | B34: CHE 59700N | C34: CHE 59700N Intro to Nanoscale | D34: 3 | F34: Legacy information online. | G34: https://selfservice.mypurdue.purdue.edu/prod/bwckctlg.p_disp_course_detail?cat_term_in=202710&subj_code_in=CHE&crse_numb_in=59700N | H34: https://purdue.edu/registrar/legacy/Home/Course/19R02F2CXGZL21JDJTB1
A35: CHE 59700Q | B35: CHE 59700Q | C35: CHE 59700Q Intr. Quantum Cntrl Engr | G35: https://selfservice.mypurdue.purdue.edu/prod/bwckctlg.p_disp_course_detail?cat_term_in=202710&subj_code_in=CHE&crse_numb_in=59700Q
A36: CHE 59700S | B36: CHE 59700S | C36: CHE 59700S Advanced Solar Conversion | G36: https://selfservice.mypurdue.purdue.edu/prod/bwckctlg.p_disp_course_detail?cat_term_in=202710&subj_code_in=CHE&crse_numb_in=59700S
A37: CHM 11500 | B37: CHM 11500 | C37: CHM 11500 General Chemistry-I (UCC: SCI) | D37: 4 | E37: MA 15900 or MA 15800 or MA 15400 or MATH 15400 or MA 16100 [concurrent ok] or MA 16500 [concurrent ok] or MA 22300 [concurrent ok] or MA 23100 [concurrent ok] or MA 16010 [concurrent ok]) or ALEKS Math Assessment 075 or SATR Math 620 or SAT Mathematics 600 or ACT Math 26 | F37: Stoichiometry; atomic structure; periodic properties; ionic and covalent bonding; molecular geometry; gases, liquids, and solids; crystal structure; thermochemistry; descriptive chemistry of metals and non-metals. Required of students majoring in science and students in engineering who are not in CHM 12300. One year of high school chemistry or one semester of college chemistry required. CTL:IPS 1721 General Chemistry I w/lab | G37: https://selfservice.mypurdue.purdue.edu/prod/bwckctlg.p_disp_course_detail?cat_term_in=202710&subj_code_in=CHM&crse_numb_in=11500
A38: CHM 11600 | B38: CHM 11600 | C38: CHM 11600 General Chemistry-II (UCC: SCI) | D38: 4 | E38: CHM 11200 or CHM 11500 or CHM 12500 or CHM 10901 or CHM 12901 or CHM 12300 or CHM 13500 or (CHEM C1050 and CHEM C1250) or (CHEM C1010 and CHEM C1210 | F38: A continuation of CHM 11500. Solutions; quantitative equilibria in aqueous solution; introductory thermodynamics; oxidation-reduction and electrochemistry; chemical kinetics; qualitative analysis; further descriptive chemistry of metals and nonmetals. CTL:IPS 1722 General Chemistry II w/lab | G38: https://selfservice.mypurdue.purdue.edu/prod/bwckctlg.p_disp_course_detail?cat_term_in=202710&subj_code_in=CHM&crse_numb_in=11600
A39: CHM 22404 | B39: CHM 22404 | C39: CHM 22404 Quantitative Analysis | D39: 3 | E39: CHM 11600 or CHM 12600 or CHM 12901 or CHM 13600 or (CHM 11610 and CHM 11620 | F39: Introduction to approaches analytical chemists use to analyze the composition of matter, including statistics, calibration, and understanding chemical equilibrium (acid/base, complexation, solubility, polyprotic acid treatment, acid/base/redox/precipitation titrations); general approaches to analysis at the trace level; recognition and evaluation of possible sources of error and how error propagates; introduction to how light interacts with matter (and how analytical chemists can take advantage of this) | G39: https://selfservice.mypurdue.purdue.edu/prod/bwckctlg.p_disp_course_detail?cat_term_in=202710&subj_code_in=CHM&crse_numb_in=22404
A40: CHM 24100 | B40: CHM 24100 | C40: CHM 24100 Introductory Inorganic Chemistry | D40: 4 | E40: CHM 11600 or CHM 12600 or CHM 13600 or (CHEM C1020 and CHEM C1220) or (CHEM C1060 and CHEM C1260 | F40: Descriptive inorganic chemistry dealing in a systematic way with the elements and the structures, properties, and reactions of their compounds. Required of students majoring in chemistry | G40: https://selfservice.mypurdue.purdue.edu/prod/bwckctlg.p_disp_course_detail?cat_term_in=202710&subj_code_in=CHM&crse_numb_in=24100
A41: CHM 26100 | B41: CHM 26100 | C41: CHM 26100 Organic Chemistry I | D41: 3 | E41: CHM 11600 or CHM 11610 or CHM 12600 or CHM 13600 or CHM 12901 or (CHEM C1060 and CHEM C1260 | F41: A comprehensive study of the chemical principles underlying aliphatic and aromatic compounds. The syntheses and reactions of these materials are discussed. Modern theory and stereochemistry are stressed to illustrate the logic inherent in the subject matter and to demonstrate the predictability of many chemical transformations. Recommended for students majoring in chemical engineering. If not a chemical engineering major, see CHM 26505 Organic Chemistry | G41: https://selfservice.mypurdue.purdue.edu/prod/bwckctlg.p_disp_course_detail?cat_term_in=202710&subj_code_in=CHM&crse_numb_in=26100
A42: CHM 26200 | B42: CHM 26200 | C42: CHM 26200 Organic Chemistry II | D42: 3 | E42: CHM 26100 or CHEM C3410 or CHM 26505 | F42: A continuation of CHM 26100, but a broader scope. The chemistry of a variety of functional groups is discussed. Theory is employed extensively to demonstrate the coherence underlying seemingly diverse transformations. Qualitative organic analysis is introduced, with particular emphasis on spectroscopic methods | G42: https://selfservice.mypurdue.purdue.edu/prod/bwckctlg.p_disp_course_detail?cat_term_in=202710&subj_code_in=CHM&crse_numb_in=26200
A43: CHM 32100 | B43: CHM 32100 | C43: CHM 32100 Analytical Chemistry I | D43: 4 | E43: CHM 22404 or FS 16300 | F43: Quantitative measurements on complex chemical systems that show matrix effects or require isolation of a component prior to its determination; general approaches to quantitative problems at the trace level; critical comparisons of competitive procedures with emphasis on principles of separation processes, including chromatography; recognition and evaluation of possible sources of error; approaches for optimizing conditions so as to minimize time and/or effort required to attain prescribed levels of accuracy and precision. Required of students majoring in chemistry | G43: https://selfservice.mypurdue.purdue.edu/prod/bwckctlg.p_disp_course_detail?cat_term_in=202710&subj_code_in=CHM&crse_numb_in=32100
A44: CHM 34200 | B44: CHM 34200 | C44: CHM 34200 Inorganic Chemistry | D44: 3 | E44: CHM 25600 or CHM 26200 or CHM 26605 or MCMP 20500 or PHSC 20500 | F44: Interpretation and correlation of the reactions and properties of inorganic compounds in terms of their electronic and molecular structures. A survey of the preparations and reactivities of important compounds of the representative elements, with an emphasis on group trends. The elementary chemistry of the transition metals, including magnetic and spectral properties of coordination compounds | G44: https://selfservice.mypurdue.purdue.edu/prod/bwckctlg.p_disp_course_detail?cat_term_in=202710&subj_code_in=CHM&crse_numb_in=34200
A45: CHM 37300 | B45: CHM 37300 | C45: CHM 37300 Physical Chemistry I | D45: 3 | E45: CHM 11600 or CHM 12600 or CHM 12901 or CHM 13600) and (MA 16200 or MA 16600 or MATH 16600) and (PHYS 22100 or PHYS 24100 or PHYS 25100 or PHYS 27200 | F45: Physical chemistry of matter. Properties of gases, liquids, and solids; equations of state; thermodynamics; energy, heat, and work; entropy; spontaneity and equilibrium; chemical potential; chemical equilibrium; phase diagrams; colligative properties | G45: https://selfservice.mypurdue.purdue.edu/prod/bwckctlg.p_disp_course_detail?cat_term_in=202710&subj_code_in=CHM&crse_numb_in=37300
A46: CHM 37301 | B46: CHM 37301 | C46: CHM 37301 Physical Chemistry Laboratory I | D46: 1 | E46: CHM 37300 [concurrent ok] | F46: A physical chemistry laboratory course that will provide students with hands-on experience that illustrates the core concepts presented in the associated physical chemistry lecture course CHM 37300 | G46: https://selfservice.mypurdue.purdue.edu/prod/bwckctlg.p_disp_course_detail?cat_term_in=202710&subj_code_in=CHM&crse_numb_in=37301
A47: CHM 37400 | B47: CHM 37400 | C47: CHM 37400 Physical Chemistry II | D47: 3 | E47: CHM 37300 | F47: Physical chemistry of molecules. Wave properties of matter; quantum mechanics of translation, rotation, and vibration; atomic structure; molecular orbitals; quantum states; statistical mechanics; chemical kinetics; collision theory; transition state theory | G47: https://selfservice.mypurdue.purdue.edu/prod/bwckctlg.p_disp_course_detail?cat_term_in=202710&subj_code_in=CHM&crse_numb_in=37400
A48: CHM 37401 | B48: CHM 37401 | C48: CHM 37401 Physical Chemistry Laboratory II | D48: 1 | E48: CHM 37000 [concurrent ok] or CHM 37400 [concurrent ok] | F48: A physical chemistry laboratory course that will provide students with hands-on experience that illustrates the core concepts presented in the associated physical chemistry lecture course CHM 37400 | G48: https://selfservice.mypurdue.purdue.edu/prod/bwckctlg.p_disp_course_detail?cat_term_in=202710&subj_code_in=CHM&crse_numb_in=37401
... A51: CHM 48100 | B51: CHM 48100 | C51: CHM 48100 Environmental Chemistry | D51: 3 | E51: CHM 11600 or CHM 10901 or CHM 12901 or CHM 12600 or CHM 13600) and (MA 16100 or MA 16500 or MA 16010 | F51: Survey of chemical aspects of environmental problems and the application of chemistry to their solution. Topics will include atmospheric pollution problems, groundwater pollution and waste disposal problems, inorganic water pollutants, and the occurrence and fate of toxic organic compounds and other substances in the environment | G51: https://selfservice.mypurdue.purdue.edu/prod/bwckctlg.p_disp_course_detail?cat_term_in=202710&subj_code_in=CHM&crse_numb_in=48100
A52: CHM 48700 | B52: CHM 48700 | C52: CHM 48700 Cooperative Work Experience V | E52: CHM 38600 | F52: Cooperative Work Experience | G52: https://selfservice.mypurdue.purdue.edu/prod/bwckctlg.p_disp_course_detail?cat_term_in=202710&subj_code_in=CHM&crse_numb_in=48700
A53: CHM 57900 | B53: CHM 57900 | C53: CHM 57900 Computational Chemistry | D53: 3 | E53: CHM 37400 | F53: Theoretical basis and practical applications of computational methods relevant to chemical and biochemical research problems | G53: https://selfservice.mypurdue.purdue.edu/prod/bwckctlg.p_disp_course_detail?cat_term_in=202710&subj_code_in=CHM&crse_numb_in=57900
A54: CHM 58100 | B54: CHM 58100 | C54: CHM 58100 Atmospheric Chemistry | D54: 3 | E54: CHM 24100 or CHM 25500 or CHM 26100 or CHM 26505 or EAS 23000 or NRES 23000 | F54: (EAPS 52100) An introduction to the chemistry of the earth's atmosphere. Covers evolution of the earth's atmosphere, its physical and chemical structure, its natural chemical composition and oxidative properties, and human impacts, including increasing tropospheric ozone, decreasing stratospheric ozone, climate change, and acidic deposition | G54: https://selfservice.mypurdue.purdue.edu/prod/bwckctlg.p_disp_course_detail?cat_term_in=202710&subj_code_in=CHM&crse_numb_in=58100
A55: CHM 60500 | B55: CHM 60500 | C55: CHM 60500 Safety In The Chemistry Laboratory | D55: 0 | F55: Lectures on safe practices in the chemistry laboratory. Required of students doing research in chemistry | G55: https://selfservice.mypurdue.purdue.edu/prod/bwckctlg.p_disp_course_detail?cat_term_in=202710&subj_code_in=CHM&crse_numb_in=60500
A56: CHM 62000 | B56: CHM 62000 | C56: CHM 62000 Spectrochemical Instrumentation | D56: 3 | F56: A critical review of instrumental methods of analysis, with particular emphasis on spectroscopic techniques. Topics include: methods of measurement; analog and digital electronics; optics and spectrophotometric modules; and instrumental methods in UV-visible, infrared, and NMR spectroscopies. Prerequisite: introductory analytical and two semesters of physical chemistry | G56: https://selfservice.mypurdue.purdue.edu/prod/bwckctlg.p_disp_course_detail?cat_term_in=202710&subj_code_in=CHM&crse_numb_in=62000
A57: CHM 62100 | B57: CHM 62100 | C57: CHM 62100 Advanced Analytical Chemistry | D57: 3 | F57: A critical survey of recent developments in chemical and instrumental methods of analysis. Prerequisite: CHM 32100, 42400 | G57: https://selfservice.mypurdue.purdue.edu/prod/bwckctlg.p_disp_course_detail?cat_term_in=202710&subj_code_in=CHM&crse_numb_in=62100
A58: CHM 64100 | B58: CHM 64100 | C58: CHM 64100 Advanced Inorganic Chemistry-I | D58: 3 | F58: Survey of main group and transition metal chemistry. Main group special topics, bonding and structure of boron hydrides. Coordination chemistry, bonding models in coordination compounds. Transition metal organometallic chemistry, ligand types and reactivity patterns. Survey of inorganic NMR spectroscopy. Prerequisite: CHM 34200 | G58: https://selfservice.mypurdue.purdue.edu/prod/bwckctlg.p_disp_course_detail?cat_term_in=202710&subj_code_in=CHM&crse_numb_in=64100
A59: CHM 64200 | B59: CHM 64200 | C59: CHM 64200 Advanced Inorganic Chemistry-II | D59: 3 | F59: Physical inorganic chemistry. Applications of group theory to chemistry and spectroscopy, especially vibrational and electronic spectra of transition metal complexes. Molecular orbital theory and theoretical bases for reactivity. Magnetic properties and electron paramagnetic resonance (EPR) spectroscopy of inorganic materials. Prerequisite: CHM 34200 | G59: https://selfservice.mypurdue.purdue.edu/prod/bwckctlg.p_disp_course_detail?cat_term_in=202710&subj_code_in=CHM&crse_numb_in=64200
A60: CHM 64400 | B60: CHM 64400 | C60: CHM 64400 Solid State Chemistry | D60: 3 | F60: The chemistry of solids, including a discussion of ionic crystals, metals, alloys, and binary compounds, and their characterizations by various physical methods. Description of chemical reactions, phase changes, and catalysis in terms of current theories of the solid state. Prerequisite: CHM 34200, 37400 | G60: https://selfservice.mypurdue.purdue.edu/prod/bwckctlg.p_disp_course_detail?cat_term_in=202710&subj_code_in=CHM&crse_numb_in=64400
A61: CHM 64600 | B61: CHM 64600 | C61: CHM 64600 Kinetics. Mech. Inorganic Reactions | D61: 3 | F61: Chemical kinetics, reaction orders, mechanisms and rate expressions; experimental techniques; transition state theory; reactions in solution; complex mechanisms; linear free-energy relationships; acid-base catalysis and proton-transfer reactions; redox reactions (electron and atom transfer, oxidative addition-reductive elimination); substitution reactions of metal ion and organometallic complexes; homogeneous catalysis; and heterogeneous reactions. Prerequisite: CHM 34200 | G61: https://selfservice.mypurdue.purdue.edu/prod/bwckctlg.p_disp_course_detail?cat_term_in=202710&subj_code_in=CHM&crse_numb_in=64600
A62: CHM 64700 | B62: CHM 64700 | C62: CHM 64700 Transition Metal-Organomet. Chem. | D62: 3 | F62: A study of the chemistry and physical properties of compounds of the transition metals. Halides, oxides, and oxy-salts; transition metal carbonyls and derivatives; pi-bonded organometallic compounds; catalysis; spectral and magnetic properties of compounds. Prerequisite: CHM 64100 | G62: https://selfservice.mypurdue.purdue.edu/prod/bwckctlg.p_disp_course_detail?cat_term_in=202710&subj_code_in=CHM&crse_numb_in=64700
A63: CHM 65100 | B63: CHM 65100 | C63: CHM 65100 Advanced Organic Chemistry | D63: 3 | F63: Modern structural organic chemistry, including introductions to molecular orbital theory and reaction mechanisms. Prerequisite: a year's course in organic chemistry | G63: https://selfservice.mypurdue.purdue.edu/prod/bwckctlg.p_disp_course_detail?cat_term_in=202710&subj_code_in=CHM&crse_numb_in=65100
A64: CHM 66800 | B64: CHM 66800 | C64: CHM 66800 Physical Organic Chemistry | D64: 3 | F64: The theoretical and mechanistic bases for structure and reactivity in organic chemistry is discussed. Individual topics include kinetics and thermodynamics, molecular orbital theory, stereochemistry and reactive intermediates as applied to the mechanisms of organic reactions. Prerequisite: CHM 56300 or 65100 | G64: https://selfservice.mypurdue.purdue.edu/prod/bwckctlg.p_disp_course_detail?cat_term_in=202710&subj_code_in=CHM&crse_numb_in=66800
A65: CHM 67100 | B65: CHM 67100 | C65: CHM 67100 Advanced Physical Chemistry | D65: 3 | F65: Selected topics, including atomic and molecular structure and modern theories underlying thermodynamics and chemical kinetics. Prerequisite: CHM 57800 | G65: https://selfservice.mypurdue.purdue.edu/prod/bwckctlg.p_disp_course_detail?cat_term_in=202710&subj_code_in=CHM&crse_numb_in=67100
A66: CHM 67300 | B66: CHM 67300 | C66: CHM 67300 Computational Quantum Chemistry | D66: 3 | F66: Semiempirical and molecular-mechanics treatments of large molecules, ab initio methods, modern density functional theory, Green's functions, multichannel quantum defect theory, global optimization methods. Prerequisite: CHM 67100 | G66: https://selfservice.mypurdue.purdue.edu/prod/bwckctlg.p_disp_course_detail?cat_term_in=202710&subj_code_in=CHM&crse_numb_in=67300
A67: CHM 67500 | B67: CHM 67500 | C67: CHM 67500 Chemical Kinetics | D67: 3 | F67: Or 3.00. Experimental and theoretical consideration of chemical reaction rates and mechanisms | G67: https://selfservice.mypurdue.purdue.edu/prod/bwckctlg.p_disp_course_detail?cat_term_in=202710&subj_code_in=CHM&crse_numb_in=67500
A68: CHM 67605 | B68: CHM 67605 | C68: CHM 67605 Molecular Spectroscopy | D68: 3 | E68: CHM 67100 | F68: Theoretical and experimental fundamentals of the interactions between molecules and electromagnetic waves. Topics include electronic, vibrational, and rotational spectroscopies, and laser-based methods. Prerequisites: CHM 67100 | G68: https://selfservice.mypurdue.purdue.edu/prod/bwckctlg.p_disp_course_detail?cat_term_in=202710&subj_code_in=CHM&crse_numb_in=67605
A69: CHM 67900 | B69: CHM 67900 | C69: CHM 67900 Chemical Thermodynamics | D69: 3 | F69: Advanced thermodynamics of chemical and phase equilibria, of electrolytic and non-electrolytic solutions, and of imperfect gases. Prerequisite: CHM 57800 | G69: https://selfservice.mypurdue.purdue.edu/prod/bwckctlg.p_disp_course_detail?cat_term_in=202710&subj_code_in=CHM&crse_numb_in=67900
A70: CHM 68200 | B70: CHM 68200 | C70: CHM 68200 Statistical Thermodynamics | D70: 3 | F70: Application of statistical mechanics to the description of imperfect gases, liquids, and solutions; to order-disorder phenomena in solids and surfaces; and to absolute reaction rate theory. Prerequisite: CHM 67100, 67900 | G70: https://selfservice.mypurdue.purdue.edu/prod/bwckctlg.p_disp_course_detail?cat_term_in=202710&subj_code_in=CHM&crse_numb_in=68200
A71: CHM 69600 | B71: CHM 69600 | C71: CHM 69600 Sustainability and Green Chemistry | G71: https://selfservice.mypurdue.purdue.edu/prod/bwckctlg.p_disp_course_detail?cat_term_in=202710&subj_code_in=CHM&crse_numb_in=69600
A72: CHM 69600-1 | B72: CHM 69600 | C72: CHM 69600 Foundations of Soft Materials | G72: https://selfservice.mypurdue.purdue.edu/prod/bwckctlg.p_disp_course_detail?cat_term_in=202710&subj_code_in=CHM&crse_numb_in=69600
A73: ECE 20001 | B73: ECE 20001 | C73: ECE 20001 Electrical Engineering Fundamentals I | D73: 3 | E73: ENGR 13000 or ENGR 13100 or ENGR 14100 or ENGR 16100 or ENGR 13300 or ENGR 19600) and ((ENGR 16100 and ENGR 16200) or PHYS 17200 or PHYS 15200) and (MA 16600 or MA 16200 or MATH 16600) and (MA 26100 [concurrent ok] or MA 17400 [concurrent ok] or MA 18200 [concurrent ok] or MA 27101 [concurrent ok] | F73: This course covers fundamental concepts and applications for electrical and computer engineers as well as for engineers who need to gain a broad understanding of these disciplines. The course starts by the basic concepts of charge, current, and voltage as well as their expressions with regards to resistors and resistive circuits. Essential concepts, devices, theorems, and applications of direct-current (DC), 1st order, and alternating-current (AC) circuits are subsequently discussed. Besides electrical devices and circuits, basic electronic components including diodes and transistors as well as their primary applications are also discussed | G73: https://selfservice.mypurdue.purdue.edu/prod/bwckctlg.p_disp_course_detail?cat_term_in=202710&subj_code_in=ECE&crse_numb_in=20001 | H73: https://engineering.purdue.edu/ECE/Academics/Undergraduates/UGO/CourseInfo/courseInfo?courseid=716&show=true&type=undergrad
A74: ECE 20002 | B74: ECE 20002 | C74: ECE 20002 Electrical Engineering Fundamentals II | D74: 3 | E74: ECE 20001 and (MA 26200 [concurrent ok] or MA 26600 [concurrent ok] or MA 36600 [concurrent ok] | F74: Continuation of Electrical and Computer Engineering Fundamentals I. The course covers the mathematical and computational foundations of (1) linear circuit analysis and (2) simple nonlinear circuits with a small number of transistors. Topics include: AC and DC analysis of simple MOSFET circuits, especially single-transistor amplifiers; op-amp circuits; mathematical methods for time-domain analysis of linear, time-invariant (LTI) systems (homogeneous and particular solutions, convolution, the Laplace transform, and the transfer function); and frequency-domain analysis and design of LTI systems (especially Bode plots and filter design). Permission of Department required | G74: https://selfservice.mypurdue.purdue.edu/prod/bwckctlg.p_disp_course_detail?cat_term_in=202710&subj_code_in=ECE&crse_numb_in=20002 | H74: https://engineering.purdue.edu/ECE/Academics/Undergraduates/UGO/CourseInfo/courseInfo?courseid=725&show=true&type=undergrad
A75: ECE 30500 | B75: ECE 30500 | C75: ECE 30500 Semiconductor Devices | D75: 3 | E75: ECE 20002 or ECE 25500) and (PHYS 27200 or PHYS 24100 or PHYS 26100 or PHYS 25100) and (MA 26600 or MA 26200 or MA 36600 | F75: Introduces and explains terminology, models, properties, and concepts associated with semiconductor devices. Provides detailed insight into the internal workings of the "building-block" device structures such as the pn-junction diode, Schottky diode, BJT, and MOSFET. Presents information about a wide variety of other devices including solar cells, LEDs, HBTs, and modern field-effect devices. Systematically develops the analytical tools needed to solve practical device problems | G75: https://selfservice.mypurdue.purdue.edu/prod/bwckctlg.p_disp_course_detail?cat_term_in=202710&subj_code_in=ECE&crse_numb_in=30500 | H75: https://engineering.purdue.edu/ECE/Academics/Undergraduates/UGO/CourseInfo/courseInfo?courseid=40&show=true&type=undergrad
A76: ECE 30600 | B76: ECE 30600 | C76: ECE 30600 Electronic Circuits and Systems Laboratory | D76: 1 | E76: ECE 20008 or ECE 20800) and ECE 30100 [concurrent ok] and ECE 30200 [concurrent ok] | F76: Experiments in electronic circuits and systems, including spectral analysis techniques, sampling, distortion measurements, random signals, signal-to-noise ratio and correlation | G76: https://selfservice.mypurdue.purdue.edu/prod/bwckctlg.p_disp_course_detail?cat_term_in=202710&subj_code_in=ECE&crse_numb_in=30600 | H76: https://engineering.purdue.edu/ECE/Academics/Undergraduates/UGO/CourseInfo/courseInfo?courseid=84&show=true&type=undergrad
A77: ECE 30653 | B77: ECE 30653 | C77: ECE 30653 Introduction to Nanotechnology and Quantum Science and Technology | D77: 3 | E77: MA 26100 and (MA 26600 or MA 26200) and (PHYS 27200 or PHYS 24100) and (CHM 11500 or (CHM 11100 and CHM 11200 | F77: This interdisciplinary course offers an introduction to nanotechnology and quantum science and technology for undergraduate students in science and engineering. The students will develop understanding of interdisciplinary nature of these fields and utilize concepts in physics, chemistry and mechanics to describe and analyze unique properties of quantum and nanoscale objects. The course will provide the opportunity to get exposed to highly interdisciplinary nature of today's most active and rapidly expanding fields of research and technologies | G77: https://selfservice.mypurdue.purdue.edu/prod/bwckctlg.p_disp_course_detail?cat_term_in=202710&subj_code_in=ECE&crse_numb_in=30653 | H77: https://engineering.purdue.edu/ECE/Academics/Undergraduates/UGO/CourseInfo/courseInfo?courseid=812&show=true&type=undergrad
A78: ECE 31033 | B78: ECE 31033 | C78: ECE 31033 Power Electronics | D78: 3 | E78: ECE 20002 or ECE 25500 | F78: Introduction to the fundamental operating principles of power conditioning circuits that are currently being used to effect power flow from AC to DC and vice versa. Emphasis is on the relationship between form and function of these circuits. Circuits discussed will include AC/DC line-commutated converters, DC/DC converters, DC/variable frequency converters, resonant converters, and AC/AC converters. Computer simulations will be used as a part of the coursework | G78: https://selfservice.mypurdue.purdue.edu/prod/bwckctlg.p_disp_course_detail?cat_term_in=202710&subj_code_in=ECE&crse_numb_in=31033 | H78: https://engineering.purdue.edu/ECE/Academics/Undergraduates/UGO/CourseInfo/courseInfo?courseid=810&show=true&type=undergrad
A79: ECE 33700 | B79: ECE 33700 | C79: ECE 33700 ASIC Design Laboratory | D79: 2 | E79: ECE 27000 | F79: Introduction to standard cell design of Application Specific Integrated Circuits (ASICs) using modern hardware description languages (HDLs). Emphasis on how to write HDL code that will map readily to hardware. Laboratory experiments using commercial grade computer-aided design (CAD) tools for HDL based design, logic simulation, automatic placement and routing, timing analysis and verification | G79: https://selfservice.mypurdue.purdue.edu/prod/bwckctlg.p_disp_course_detail?cat_term_in=202710&subj_code_in=ECE&crse_numb_in=33700 | H79: https://engineering.purdue.edu/ECE/Academics/Undergraduates/UGO/CourseInfo/courseInfo?courseid=613&show=true&type=undergrad
A80: ECE 36200 | B80: ECE 36200 | C80: ECE 36200 Microprocessor Systems And Interfacing | D80: 4 | E80: ECE 27000 and (ENGR 11700 or CS 15900 | F80: An introduction to basic computer organization, microprocessor instruction sets, assembly language programming, and microcontroller peripherals | G80: https://selfservice.mypurdue.purdue.edu/prod/bwckctlg.p_disp_course_detail?cat_term_in=202710&subj_code_in=ECE&crse_numb_in=36200 | H80: https://engineering.purdue.edu/ECE/Academics/Undergraduates/UGO/CourseInfo/courseInfo?courseid=612&show=true&type=undergrad
A81: ECE 40655 | B81: ECE 40655 | C81: ECE 40655 Digital Integrated Circuit Analysis and Design | D81: 3 | E81: ECE 20002 and ECE 30500 [concurrent ok] | F81: As applied to digital integrated circuits, the MDs transistor is studied in depth-from its fabrication to its electrical characteristics. Combinational, sequential, and dynamic logic circuits are considered. While the focus of the course is on CMOS technology, bipolar, nMOS, and BiCMOS circuits are introduced as well. SPICE is used as both an analysis and design tool. Semiconductor memory circuits are also discussed | G81: https://selfservice.mypurdue.purdue.edu/prod/bwckctlg.p_disp_course_detail?cat_term_in=202710&subj_code_in=ECE&crse_numb_in=40655 | H81: https://engineering.purdue.edu/ECE/Academics/Undergraduates/UGO/CourseInfo/courseInfo?courseid=869&show=true&type=undergrad
A82: ECE 40656 | B82: ECE 40656 | C82: ECE 40656 CMOS Analog and Mixed Signal Integrated Circuits | D82: 3 | E82: ECE 20002 | F82: This course is a review of technology and modeling of CMOS transistors; Analysis, and design of CMOS monolithic integrated circuits for analog and mixed-signal applications. Consideration of amplifier circuit design, and fabrication techniques with circuit simulation using Cadence. Simple and advanced CMOS operational amplifiers, comparators, sample and hold circuits, switch capacitor circuits and data converters; Design of analog and mixed-signal circuit building blocks | G82: https://selfservice.mypurdue.purdue.edu/prod/bwckctlg.p_disp_course_detail?cat_term_in=202710&subj_code_in=ECE&crse_numb_in=40656 | H82: https://engineering.purdue.edu/ECE/Academics/Undergraduates/UGO/CourseInfo/courseInfo?courseid=870&show=true&type=undergrad
A83: ECE 43300 | B83: ECE 43300 | C83: ECE 43300 Power Electronics | D83: 3 | E83: ECE 20002 or ECE 25500 | F83: Introduction to the fundamental operating principles of power conditioning circuits that are currently being used to effect power flow from AC to DC and vice versa. Emphasis is on the relationship between form and function of these circuits. Circuits discussed will include AC/DC line-commutated converters, DC/DC converters, DC/variable frequency converters, resonant converters, and AC/AC converters. Computer simulations will be used as a part of the coursework | G83: https://selfservice.mypurdue.purdue.edu/prod/bwckctlg.p_disp_course_detail?cat_term_in=202710&subj_code_in=ECE&crse_numb_in=43300 | H83: https://engineering.purdue.edu/ECE/Academics/Undergraduates/UGO/CourseInfo/courseInfo?courseid=543&show=true&type=undergrad
A84: ECE 43700 | B84: ECE 43700 | C84: ECE 43700 Computer Design and Prototyping | D84: 4 | E84: ECE 33700 and ECE 36200 | F84: An introduction to computer organization and design, including instruction set selection, arithmetic logic unit design, data path design, control strategies, pipelining, memory hierarchy, and I/O interface design | G84: https://selfservice.mypurdue.purdue.edu/prod/bwckctlg.p_disp_course_detail?cat_term_in=202710&subj_code_in=ECE&crse_numb_in=43700 | H84: https://engineering.purdue.edu/ECE/Academics/Undergraduates/UGO/CourseInfo/courseInfo?courseid=143&show=true&type=undergrad
... A113: ECE 59500-11 | B113: ECE 59500 | C113: ECE 59500 MEMS III: Applications in MEMS | D113: 1 | E113: ECE 59500 MEMS II | F113: This module surveys both established and emergent applications of MEMS. With the growing demand for cheap, microscale, low power sensors, the first part of this course will cover MEMS sensor applications including inertial, chemical, field, and IR sensor devices. We will discuss limits of sensitivity, design, fabrication, and system-level integration. Other topics will include microrobotics, optical MEMS, BioMEMS and Lab on a Chip, and quantum computing with MEMS/NEMS. | G113: https://selfservice.mypurdue.purdue.edu/prod/bwckctlg.p_disp_course_detail?cat_term_in=202710&subj_code_in=ECE&crse_numb_in=59500 | H113: https://engineering.purdue.edu/ECE/Academics/Undergraduates/UGO/CourseInfo/courseInfo?courseid=733&show=true&type=grad
A114: ECE 59500-12 | B114: ECE 59500 | C114: ECE 59500 Fundamentals of Current Flow | D114: 1 | E114: N/A | F114: Replaced with 50631 | G114: https://selfservice.mypurdue.purdue.edu/prod/bwckctlg.p_disp_course_detail?cat_term_in=202710&subj_code_in=ECE&crse_numb_in=59500
A115: ECE 59500-13 | B115: ECE 59500 | C115: ECE 59500 Introduction to Quantum Transport | D115: 1 | E115: N/A | F115: Replaced with 50632 | G115: https://selfservice.mypurdue.purdue.edu/prod/bwckctlg.p_disp_course_detail?cat_term_in=202710&subj_code_in=ECE&crse_numb_in=59500
A116: ECE 59500-14 | B116: ECE 59500 | C116: ECE 59500 Microfabrication Fundamentals | D116: 1 | E116: MA 26600 and [PHYS 27200 or PHYS 24100] and CHM 11500 | F116: Introduction to principles of microfabrication, including lithography, deposition, etching and planarization. This course provides a framework for understanding processes used in manufacturing of semiconductor devices, integrated circuits, microphotonic and micro-electromechanical systems (MEMS) components. | G116: https://selfservice.mypurdue.purdue.edu/prod/bwckctlg.p_disp_course_detail?cat_term_in=202710&subj_code_in=ECE&crse_numb_in=59500 | H116: https://engineering.purdue.edu/ECE/Academics/Undergraduates/UGO/CourseInfo/courseInfo?courseid=740&show=true&type=undergrad
A117: ECE 59500-15 | B117: ECE 59500 | C117: ECE 59500 Primer on Semiconductors | D117: 1 | E117: (ECE 20002 or ECE 25500) and (PHYS 27200 or PHYS 24100 or PHYS 26100 or PHYS 25100) and (MA 26600 or MA 26200 or MA 3660) | F117: This course about semiconductors is designed to provide a foundation to understand the operation of devices such as transistors, diodes, solar cells, light-emitting devices, etc. The course does not discuss devices ??? it prepares students to understand the operation of semiconductor devices. The treatment is physical and intuitive, and not heavily mathematical. Technology users will gain an understanding of the semiconductor physics that is the basis for devices. Semiconductor technology developers may find it a useful starting point for diving deeper into condensed matter physics, statistical mechanics, thermodynamics, and materials science. The course presents an electrical engineering perspective on semiconductors, but those in other fields may find it a useful introduction to the approach that has guided the development of semiconductor technology for the past 50+ years. Topics include semiconductor fundamentals such as energy bands, bandgaps, effective masses, electrons and holes, and elements of quantum mechanics. The Fermi function, doping, and carrier densities are then discussed. Carrier transport and generation-recombination are examined along with the important concept of quasi-Fermi levels. The course concludes with the ???semiconductor equations,??? which provide a complete, mathematical description of electrons and holes in semiconductors (subject to some important simplifying assumptions) and ends with a discussion of how energy band diagrams provide a qualitative solution to these equations. | G117: https://selfservice.mypurdue.purdue.edu/prod/bwckctlg.p_disp_course_detail?cat_term_in=202710&subj_code_in=ECE&crse_numb_in=59500 | H117: https://engineering.purdue.edu/ECE/Academics/Undergraduates/UGO/CourseInfo/courseInfo?courseid=720&show=true&type=undergrad
A118: ECE 59500-16 | B118: ECE 59500 | C118: ECE 59500 Semiconductor Fundamentals | G118: https://selfservice.mypurdue.purdue.edu/prod/bwckctlg.p_disp_course_detail?cat_term_in=202710&subj_code_in=ECE&crse_numb_in=59500
A119: ECE 59500-17 | B119: ECE 59500 | C119: ECE 59500 Semiconductor Manufacturing | D119: 1 | E119: [MA 26200 or MA 26600] and [PHYS 27200 or PHYS 24100] and CHM 11500 and [ECE 59500 Microfabrication Fundamentals or (ECE 59500 MEMS I: Microfabrication and Materials for MEMS) | F119: Introduction to manufacturing processes suitable for CMOS and CMOS-compatible integrated devices. Unit processes for multi-level metal interconnects, including physical deposition, plasma enhanced chemical vapor deposition, copper plating, chemical mechanical polishing of dielectrics and metals. Process development of Si/Ge, low-k dielectrics, metal gates, 3D NANDs and photonic devices, etc. | G119: https://selfservice.mypurdue.purdue.edu/prod/bwckctlg.p_disp_course_detail?cat_term_in=202710&subj_code_in=ECE&crse_numb_in=59500 | H119: https://engineering.purdue.edu/ECE/Academics/Undergraduates/UGO/CourseInfo/courseInfo?courseid=742&show=true&type=undergrad
A120: ECE 59500-18 | B120: ECE 59500 | C120: ECE 59500 Theory & Practice of Solar Cells: A Cell to System Perspec | D120: 1 | E120: ECE 30500 or ECE 60600 or ECE 69500A (Primer on Semiconductor Fundamentals) or equivalent | F120: This course is designed for students from all disciplines in engineering and science seeking to learn about how solar cells function, how they are connected into modules, how modules are assembled into panels, and how panels are fielded in solar farms. The basics of solar farms are covered as well as the reliability of solar cells. The course is at the advanced undergraduate / beginning graduate student level. | G120: https://selfservice.mypurdue.purdue.edu/prod/bwckctlg.p_disp_course_detail?cat_term_in=202710&subj_code_in=ECE&crse_numb_in=59500 | H120: https://engineering.purdue.edu/ECE/Academics/Undergraduates/UGO/CourseInfo/courseInfo?courseid=712&show=true&type=undergrad
A121: ECE 59500-19 | B121: ECE 59500IC | C121: ECE 59500IC Integrated Circuit/MEMS Fabrication | D121: 3 | E121: ECE 30500 | F121: This course is an updated version of ECE 55700 and will provide students state-of-the-art knowledge in the area of Micro and Nanofabrication Technology. Course topics include substrate, oxidation, lithography, etching (dry and wet), thin film deposition (physical vapor deposition, chemical vapor deposition, atomic layer deposition, epitaxy), diffusion and ion implantation, chemical mechanical polishing, metallization, packaging and integration. The course will include both lectures and hands-on training through VFabLab. | G121: https://selfservice.mypurdue.purdue.edu/prod/bwckctlg.p_disp_course_detail?cat_term_in=202710&subj_code_in=ECE&crse_numb_in=59500IC | H121: https://engineering.purdue.edu/ECE/Academics/Undergraduates/UGO/CourseInfo/courseInfo?courseid=822&show=true&type=grad
A122: ECE 60420 | B122: ECE 60420 | C122: ECE 60420 Radio Frequency Integrated Circuits | D122: 3 | F122: This course aims at analysis and design of CMOS integrated radio frequency (RF), microwave and mm-wave circuits. Various modules of an RF transceiver are discussed including low noise amplifiers, mixers, oscillators, frequency synthesizers and power amplifiers. A term project on design of an RF to mm-wave module is also required | G122: https://selfservice.mypurdue.purdue.edu/prod/bwckctlg.p_disp_course_detail?cat_term_in=202710&subj_code_in=ECE&crse_numb_in=60420 | H122: https://engineering.purdue.edu/ECE/Academics/Undergraduates/UGO/CourseInfo/courseInfo?courseid=650&show=true&type=grad
A123: ECE 60421 | B123: ECE 60421 | C123: ECE 60421 Nanophotonics and Metamaterials | D123: 3 | F123: The course will cover nanoscale processes and devices and their applications for manipulating light on the nanoscale. The following topics will be covered: Fundamentals, Maxwell's equations, light-matter interaction, dispersion, EM properties of nanostructures; Photonic crystals and photonic crystal fibers; Photonic and plasmonic nanocircuits; Silicon nanophotonics; Metal optics; Manipulating light with plasmonic nanostructures; Plasmonic nano-sensors; Near-field optics; Metamaterials: artificial magnetism and negative refractive index; Metamaterials: superlens and hyperlens; Transformation optics and cloaking; Nanolasers; Tunable and active plasmonic materials; Refractory plasmonics; Plasmonics for energy conversion, data storage and biomed applications; Metasurfaces; Intro to quantum photonics. Prerequisites by Topic: Basic knowledge of electromagnetism and solid state materials, Maxwell equations and band structure of solids | G123: https://selfservice.mypurdue.purdue.edu/prod/bwckctlg.p_disp_course_detail?cat_term_in=202710&subj_code_in=ECE&crse_numb_in=60421 | H123: https://engineering.purdue.edu/ECE/Academics/Undergraduates/UGO/CourseInfo/courseInfo?courseid=673&show=true&type=grad
A124: ECE 60422 | B124: ECE 60422 | C124: ECE 60422 Primer on RF Circuit Design | D124: 1 | F124: This course covers the fundamentals of RF design. It is designed as a first course for students or engineers with limited background in high-frequency electronics. Engineers that need to understand the 'RF language' and gain working knowledge of critical RF concepts will benefit from taking this course. Students in this class will learn the basic RF tools and design principles. By the end of this class students will be able to understand important RF concepts and how these are related to the design of practical RF blocks. Pre-requisite: ECE 31100 or equivalent | G124: https://selfservice.mypurdue.purdue.edu/prod/bwckctlg.p_disp_course_detail?cat_term_in=202710&subj_code_in=ECE&crse_numb_in=60422 | H124: https://engineering.purdue.edu/ECE/Academics/Undergraduates/UGO/CourseInfo/courseInfo?courseid=692&show=true&type=grad
A125: ECE 60423 | B125: ECE 60423 | C125: ECE 60423 RF System Design | D125: 1 | F125: Following the 'Primer on RF Design' course, this class focuses on system-level issues. We discuss several important design considerations including noise, non-linearity, distortion, sensitivity and dynamic range and their impact in selecting the appropriate system architecture. The course also covers common receiver architectures including superheterodyne and direct-conversion receivers. Pre-requisite: ECE 60422 | G125: https://selfservice.mypurdue.purdue.edu/prod/bwckctlg.p_disp_course_detail?cat_term_in=202710&subj_code_in=ECE&crse_numb_in=60423 | H125: https://engineering.purdue.edu/ECE/Academics/Undergraduates/UGO/CourseInfo/courseInfo?courseid=714&show=true&type=grad
A126: ECE 60424 | B126: ECE 60424 | C126: ECE 60424 RF Design: Passive And Active Components | D126: 1 | F126: Following the 'Primer on RF Design' course, this class focuses on passive and active components. We use the techniques learnt in the previous course, to design advanced RF devices including couplers, filters and amplifiers. Current research topics are discussed as appropriate. Pre-requisite: ECE 60422 | G126: https://selfservice.mypurdue.purdue.edu/prod/bwckctlg.p_disp_course_detail?cat_term_in=202710&subj_code_in=ECE&crse_numb_in=60424 | H126: https://engineering.purdue.edu/ECE/Academics/Undergraduates/UGO/CourseInfo/courseInfo?courseid=715&show=true&type=grad
A127: ECE 60431 | B127: ECE 60431 | C127: ECE 60431 Fiber Optic Communications | D127: 3 | F127: Optical fiber waveguides: ray and wave models, single-mode and multimode fibers. Fiber loss and dispersion mechanisms. Optical sources: LEDs and laser diodes, modulation. Photodetectors: PIN and avalanche photodiodes. Optical amplifiers: EDFA gain, noise. Wavelength-division multiplexing. Coherent communications. System design and link budgets. | G127: https://selfservice.mypurdue.purdue.edu/prod/bwckctlg.p_disp_course_detail?cat_term_in=202710&subj_code_in=ECE&crse_numb_in=60431 | H127: https://engineering.purdue.edu/ECE/Academics/Undergraduates/UGO/CourseInfo/courseInfo?courseid=707&show=true&type=grad
A128: ECE 60614 | B128: ECE 60614 | C128: ECE 60614 Reliab Phys Nanoelectr Trans | D128: 3 | E128: ECE 60600 required; ECE 61200 and ECE 55800 are recommended | F128: This course will focus on the physics of reliability of small semiconductor devices. In traditional courses on device physics, the students learn how to compute current through a device in response to applied voltage. However, as transistors are turned on and off trillions of times during the years of operation, gradually defects accumulate within the device so that at some point the transistor does not work anymore. The course will explore the physics and mathematics regarding how and when things break - a topic of great interest to semiconductor device engineers. Prerequisites: ECE 60600 required; ECE 61200 and ECE 55800 are recommended | G128: https://selfservice.mypurdue.purdue.edu/prod/bwckctlg.p_disp_course_detail?cat_term_in=202710&subj_code_in=ECE&crse_numb_in=60614 | H128: https://engineering.purdue.edu/ECE/Academics/Undergraduates/UGO/CourseInfo/courseInfo?courseid=660&show=true&type=grad
A129: ECE 68800 | B129: ECE 68800 | C129: ECE 68800 VLSI Testing and Verification | D129: 3 | F129: Discusses different aspects of VLSI testing and formal verification of designs. Design and manufacturing defect models are introduced along with test generation and fault simulation algorithms targeting the different fault models. Both combinational and sequential logic testing are covered, and different synthesis for testability schemes such as BIST (Built-In-Self-Test), scan path design, etc., are introduced. Other new and emerging test and verification techniques also are discussed. Offered every third semester. Prerequisite: ECE 55900 | G129: https://selfservice.mypurdue.purdue.edu/prod/bwckctlg.p_disp_course_detail?cat_term_in=202710&subj_code_in=ECE&crse_numb_in=68800 | H129: https://engineering.purdue.edu/ECE/Academics/Undergraduates/UGO/CourseInfo/courseInfo?courseid=449&show=true&type=grad
A130: ECE 69500 | B130: ECE 69500 | C130: ECE 69500 Hardware for Machine Learning | D130: 3 | E130: Undergraduate level understanding of traditional computer architecture, circuits and basic linear algebra. Some exposure to deep learning algorithms is beneficial but not required. | F130: This course offers an in-depth exploration of how advances in deep learning algorithms have driven innovations in hardware design, and vice versa. It covers advancements in traditional computing architectures, specialized machine learning accelerators, and novel paradigms like compute-in-memory and neuromorphic computing. Students will develop the skills to formulate algorithm-hardware co-design techniques for designing/optimizing hardware tailored for deep learning algorithms. | G130: https://selfservice.mypurdue.purdue.edu/prod/bwckctlg.p_disp_course_detail?cat_term_in=202710&subj_code_in=ECE&crse_numb_in=69500 | H130: https://engineering.purdue.edu/ECE/Academics/Undergraduates/UGO/CourseInfo/courseInfo?courseid=859&show=true&type=grad
A131: ECET 22700 | B131: ECET 22700 | C131: ECET 22700 DC and Pulse Electronics | D131: 3 | E131: ECET 17700 or ECET 22400 or ECE 20001 and ECE 20007) and (MA 16010 or MA 22700 or MA 22300 or MA 22100 or MA 16100 or MA 16300 or MA 16500 or MA 16700 or MA 21900 or MA 22500 or MA 22900 or MATH M1190 or MATH M2080 or MATH M2150 or MATH 16300 | F131: Capacitors, inductors, oscillators, rectifiers, bipolar and MOSFET power switches, switching power supplies, half-and full-H bridges, switching audio power amplifiers, and linear regulators are studied. Computer-aided analysis of circuits is utilized | G131: https://selfservice.mypurdue.purdue.edu/prod/bwckctlg.p_disp_course_detail?cat_term_in=202710&subj_code_in=ECET&crse_numb_in=22700
A132: ECET 22900 | B132: ECET 22900 | C132: ECET 22900 Concurrent Digital Systems | D132: 3 | E132: ENGT 18000 and ENGT 18100) or ENGT 18200 or ECET 12000 or ECET 22400 or (ECE 20001 and ECE 20007 | F132: This course establishes a foundation for concurrent digital systems. Common methods of describing digital circuit operation are studied along with the techniques for translation between any two methods. Basic building blocks of digital systems are defined and applied. Analysis techniques for combinational and sequential logic circuits or subsystems are covered. Computer-based development tools, programmable logic devices, and technical reference sources are used to build, test, and evaluate digital systems | G132: https://selfservice.mypurdue.purdue.edu/prod/bwckctlg.p_disp_course_detail?cat_term_in=202710&subj_code_in=ECET&crse_numb_in=22900
A133: ECET 22900 | B133: ECET 22900 | C133: ECET 22900 Concurrent Digital Systems | D133: 3 | E133: ENGT 18000 and ENGT 18100) or ENGT 18200 or ECET 12000 or ECET 22400 or (ECE 20001 and ECE 20007 | F133: This course establishes a foundation for concurrent digital systems. Common methods of describing digital circuit operation are studied along with the techniques for translation between any two methods. Basic building blocks of digital systems are defined and applied. Analysis techniques for combinational and sequential logic circuits or subsystems are covered. Computer-based development tools, programmable logic devices, and technical reference sources are used to build, test, and evaluate digital systems | G133: https://selfservice.mypurdue.purdue.edu/prod/bwckctlg.p_disp_course_detail?cat_term_in=202710&subj_code_in=ECET&crse_numb_in=22900
A134: ECET 32900 | B134: ECET 32900 | C134: ECET 32900 Advanced embedded systems | D134: 3 | E134: ECET 27900 | F134: This course focuses on the study and application of real-time embedded systems. Real-time operating systems (RTOS) are introduced and applied. Students learn and use programming and scripting languages to discover the advantages and limitations of RTOS application in the lab | G134: https://selfservice.mypurdue.purdue.edu/prod/bwckctlg.p_disp_course_detail?cat_term_in=202710&subj_code_in=ECET&crse_numb_in=32900
A135: ECET 33300 | B135: ECET 33300 | C135: ECET 33300 Power Electronic Energy Systems | D135: 3 | E135: ECET 22700 and ECET 37600 | F135: A study of the fundamentals and applications of switch-mode DC-DC and DC-AC power electronic converters, with emphasis on controller and power stage design tailored to specific applications such as grid-interactive inverter-based resources and electric vehicles | G135: https://selfservice.mypurdue.purdue.edu/prod/bwckctlg.p_disp_course_detail?cat_term_in=202710&subj_code_in=ECET&crse_numb_in=33300
A136: ECET 33300-1 | B136: ECET 33300 | C136: ECET 33300 Power Electronics in Energy Systems | D136: 3 | E136: ECET 22700 and ECET 37600 | F136: A study of the fundamentals and applications of switch-mode DC-DC and DC-AC power electronic converters, with emphasis on controller and power stage design tailored to specific applications such as grid-interactive inverter-based resources and electric vehicles | G136: https://selfservice.mypurdue.purdue.edu/prod/bwckctlg.p_disp_course_detail?cat_term_in=202710&subj_code_in=ECET&crse_numb_in=33300
A137: ECET 34900 | B137: ECET 34900 | C137: ECET 34900 Advanced Digital Systems | D137: 3 | E137: ECET 17900 and ECET 22900 | F137: This course investigates complex digital systems that are implemented with field programmable gate arrays (FPGAs) using concurrent and sequential digital design techniques. Applications will include serial communications, digital signal processing, memory systems and video generation | G137: https://selfservice.mypurdue.purdue.edu/prod/bwckctlg.p_disp_course_detail?cat_term_in=202710&subj_code_in=ECET&crse_numb_in=34900
A138: ECET 36900 | B138: ECET 36900 | C138: ECET 36900 Applied computer vision for sensing and automation | D138: 3 | E138: CS 18000 or CS 17700 or CS 15900 or CNIT 10500 or CNIT 15501) and (ECET 22400 or ECET 17700 or (ECE 20001 and ECE 20007) or (ECE 20100 and ECE 20700 | F138: This course provides fundamental knowledge of integrated computer imaging or vision systems for sensing, quality control and automation applications. Fundamental basis of optics, illumination, camera types with associated technologies, and image acquisition to develop a customized computer imaging or vision systems will be covered. Algorithms for image processing, image analysis and pattern recognition will also be covered. Emerging technologies-based integrated computer vision or imaging system for sensor system, inspection, quality control and automation in different sectors (medical, manufacturing, security, construction etc.) will be examined. Parallel laboratory hands-on experience will allow the students to apply and validate the concepts learned in the lecture | G138: https://selfservice.mypurdue.purdue.edu/prod/bwckctlg.p_disp_course_detail?cat_term_in=202710&subj_code_in=ECET&crse_numb_in=36900
...

Sheet Categories
A1: Electronics Packaging, Heterogeneous Integration, and Thermal Management
A2: Integrated Circuit & System Design, Electronic Design Automation
A3: Semiconductor and Microelectronic Devices
A4: Semiconductor Manufacturing and Global Supply Chain Management
A5: Semiconductor Materials, Characterization, and Processing
A6: Experiential learning
A7: uncategorized
A8: N/A

Sheet Sheet3
A1: Certificate Course Number | B1: Course Number | C1: Course | D1: Credits | E1: Pre-Requisites | F1: Course Description | G1: Catalog Link | H1: Additional Information
A2: CHE 20500 | B2: CHE 20500 | C2: CHE 20500 Chemical Engineering Calculations | D2: 4 | E2: ENGR 12100 or ENFY 12600 or ENGR 12600 or ENFY 13100 or ENGR 13100 or ENGR 13000 or VIP 17911 or ENGR 17911 or ENGR 16100 or EPCS 11100 or EPCS 12100 or ENFY 19500 or ENGR 19500 or ENGR 14100 or ENGR 16100) and (PHYS 17200 or (PHYS 16200 and PHYS 16300) or (ENGR 16200) and (MA 16100 or MA 16700 Minimum Grade of | F2: Quantitative applications of steady-state mass and energy balances to solve problems involving multi-component systems and multi-unit chemical processes. Single-component and multi-component phase equilibria, single-reaction and multiple-reaction stoichiometry, coupled mass and energy balances, chemical processes involving bypass and recycle streams | G2: https://selfservice.mypurdue.purdue.edu/prod/bwckctlg.p_disp_course_detail?cat_term_in=202710&subj_code_in=CHE&crse_numb_in=20500
A3: CHE 21100 | B3: CHE 21100 | C3: CHE 21100 Introductory Chemical Engineering Thermodynamics | D3: 4 | E3: CHE 20500 and (MA 26100 or MATH 26100 or MA 18200 or MA 17400 or MA 27100 or MA 26300 or MA 17200 | F3: Basic principles and concepts of thermodynamics applied to chemical engineering problems; use of basic thermodynamic functions of enthalpy, entropy, free energy to solutions, phase equilibria, and chemical equilibria; thermodynamic processes and efficiencies; equations of state; and relation of macroscopic to molecular properties | G3: https://selfservice.mypurdue.purdue.edu/prod/bwckctlg.p_disp_course_detail?cat_term_in=202710&subj_code_in=CHE&crse_numb_in=21100
A4: CHE 30600 | B4: CHE 30600 | C4: CHE 30600 Design Of Staged Separation Processes | D4: 3 | E4: CHE 20500 and CHE 21100 | F4: The application of equilibria and mass and energy balances for the design of staged separation processes. Use of various equilibrium data and thermodynamic principles for the design of batch and continuous distillation, absorption, stripping, and extraction systems. Stagewise calculations and graphical methods for design of binary systems. Design of multicomponent separators. Determination of stage efficiency and column size | G4: https://selfservice.mypurdue.purdue.edu/prod/bwckctlg.p_disp_course_detail?cat_term_in=202710&subj_code_in=CHE&crse_numb_in=30600
